Workbook
Name Cosumo_Negocio: Consumo!$A$1:$J$2746

Sheet Productos
A1: Código | B1: Producto | C1: Tipo | D1: Precio Neto | E1: IVA Dev | F1: Precio Venta | G1: Costo Unit | H1: Utilidad | I1: Margen
A2: TO-01 | B2: Toalla 160x80 Az | C2: Toalla | D2: 8992 | E2: =ROUND(Productos[[#This Row],[Precio Neto]]*0.19,0) -> 1708 | F2: =Productos[[#This Row],[Precio Neto]]+Productos[[#This Row],[IVA Dev]] -> 10700 | G2: =IFERROR(SUMIF('Receta'!$A$2:$A$266,Productos!A2,'Receta'!$K$2:$K$266),"") -> 6007.185 | H2: =IFERROR(Productos!$F2-Productos!$G2,"") -> 4692.815 | I2: =IFERROR(Productos!$H2/Productos!$G2,"") -> 0.78120035
A3: TO-02 | B3: Toalla 160x80 Ro | C3: Toalla | D3: 8992 | E3: =ROUND(Productos[[#This Row],[Precio Neto]]*0.19,0) -> 1708 | F3: =Productos[[#This Row],[Precio Neto]]+Productos[[#This Row],[IVA Dev]] -> 10700 | G3: =IFERROR(SUMIF('Receta'!$A$2:$A$266,Productos!A3,'Receta'!$K$2:$K$266),"") -> 5927.56 | H3: =IFERROR(Productos!$F3-Productos!$G3,"") -> 4772.44 | I3: =IFERROR(Productos!$H3/Productos!$G3,"") -> 0.80512724
A4: TO-03 | B4: Toalla 160x80 Am | C4: Toalla | D4: 8992 | E4: =ROUND(Productos[[#This Row],[Precio Neto]]*0.19,0) -> 1708 | F4: =Productos[[#This Row],[Precio Neto]]+Productos[[#This Row],[IVA Dev]] -> 10700 | G4: =IFERROR(SUMIF('Receta'!$A$2:$A$266,Productos!A4,'Receta'!$K$2:$K$266),"") -> 5927.56 | H4: =IFERROR(Productos!$F4-Productos!$G4,"") -> 4772.44 | I4: =IFERROR(Productos!$H4/Productos!$G4,"") -> 0.80512724
A5: TO-04 | B5: Toalla 160x80 Vp | C5: Toalla | D5: 8992 | E5: =ROUND(Productos[[#This Row],[Precio Neto]]*0.19,0) -> 1708 | F5: =Productos[[#This Row],[Precio Neto]]+Productos[[#This Row],[IVA Dev]] -> 10700 | G5: =IFERROR(SUMIF('Receta'!$A$2:$A$266,Productos!A5,'Receta'!$K$2:$K$266),"") -> 5927.56 | H5: =IFERROR(Productos!$F5-Productos!$G5,"") -> 4772.44 | I5: =IFERROR(Productos!$H5/Productos!$G5,"") -> 0.80512724
A6: TO-05 | B6: Toalla 160x80 Ca | C6: Toalla | D6: 8992 | E6: =ROUND(Productos[[#This Row],[Precio Neto]]*0.19,0) -> 1708 | F6: =Productos[[#This Row],[Precio Neto]]+Productos[[#This Row],[IVA Dev]] -> 10700 | G6: =IFERROR(SUMIF('Receta'!$A$2:$A$266,Productos!A6,'Receta'!$K$2:$K$266),"") -> 5927.56 | H6: =IFERROR(Productos!$F6-Productos!$G6,"") -> 4772.44 | I6: =IFERROR(Productos!$H6/Productos!$G6,"") -> 0.80512724
A7: TO-06 | B7: Toalla 160x80 Fu | C7: Toalla | D7: 8992 | E7: =ROUND(Productos[[#This Row],[Precio Neto]]*0.19,0) -> 1708 | F7: =Productos[[#This Row],[Precio Neto]]+Productos[[#This Row],[IVA Dev]] -> 10700 | G7: =IFERROR(SUMIF('Receta'!$A$2:$A$266,Productos!A7,'Receta'!$K$2:$K$266),"") -> 5927.56 | H7: =IFERROR(Productos!$F7-Productos!$G7,"") -> 4772.44 | I7: =IFERROR(Productos!$H7/Productos!$G7,"") -> 0.80512724
A8: TO-07 | B8: Toalla 160x80 Na | C8: Toalla | D8: 8992 | E8: =ROUND(Productos[[#This Row],[Precio Neto]]*0.19,0) -> 1708 | F8: =Productos[[#This Row],[Precio Neto]]+Productos[[#This Row],[IVA Dev]] -> 10700 | G8: =IFERROR(SUMIF('Receta'!$A$2:$A$266,Productos!A8,'Receta'!$K$2:$K$266),"") -> 5927.56 | H8: =IFERROR(Productos!$F8-Productos!$G8,"") -> 4772.44 | I8: =IFERROR(Productos!$H8/Productos!$G8,"") -> 0.80512724
A9: TO-08 | B9: Toalla 160x80 Ne | C9: Toalla | D9: 8992 | E9: =ROUND(Productos[[#This Row],[Precio Neto]]*0.19,0) -> 1708 | F9: =Productos[[#This Row],[Precio Neto]]+Productos[[#This Row],[IVA Dev]] -> 10700 | G9: =IFERROR(SUMIF('Receta'!$A$2:$A$266,Productos!A9,'Receta'!$K$2:$K$266),"") -> 5927.56 | H9: =IFERROR(Productos!$F9-Productos!$G9,"") -> 4772.44 | I9: =IFERROR(Productos!$H9/Productos!$G9,"") -> 0.80512724
A10: TO-09 | B10: Toalla 80x40 Na | C10: Toalla | D10: 7983 | E10: =ROUND(Productos[[#This Row],[Precio Neto]]*0.19,0) -> 1517 | F10: =Productos[[#This Row],[Precio Neto]]+Productos[[#This Row],[IVA Dev]] -> 9500 | G10: =IFERROR(SUMIF('Receta'!$A$2:$A$266,Productos!A10,'Receta'!$K$2:$K$266),"") -> 2226.89 | H10: =IFERROR(Productos!$F10-Productos!$G10,"") -> 7273.11 | I10: =IFERROR(Productos!$H10/Productos!$G10,"") -> 3.2660392
A11: TO-10 | B11: Toalla 40x40 Na | C11: Toalla | D11: 3782 | E11: =ROUND(Productos[[#This Row],[Precio Neto]]*0.19,0) -> 719 | F11: =Productos[[#This Row],[Precio Neto]]+Productos[[#This Row],[IVA Dev]] -> 4501 | G11: =IFERROR(SUMIF('Receta'!$A$2:$A$266,Productos!A11,'Receta'!$K$2:$K$266),"") -> 1465.945 | H11: =IFERROR(Productos!$F11-Productos!$G11,"") -> 3035.055 | I11: =IFERROR(Productos!$H11/Productos!$G11,"") -> 2.0703744
A12: TO-11 | B12: Toalla 160x110 Na | C12: Toalla | D12: 11092 | E12: =ROUND(Productos[[#This Row],[Precio Neto]]*0.19,0) -> 2107 | F12: =Productos[[#This Row],[Precio Neto]]+Productos[[#This Row],[IVA Dev]] -> 13199 | G12: =IFERROR(SUMIF('Receta'!$A$2:$A$266,Productos!A12,'Receta'!$K$2:$K$266),"") -> 8696.34 | H12: =IFERROR(Productos!$F12-Productos!$G12,"") -> 4502.66 | I12: =IFERROR(Productos!$H12/Productos!$G12,"") -> 0.51776494
A13: TO-12 | B13: Toalla 160x110 Li | C13: Toalla | D13: 11092 | E13: =ROUND(Productos[[#This Row],[Precio Neto]]*0.19,0) -> 2107 | F13: =Productos[[#This Row],[Precio Neto]]+Productos[[#This Row],[IVA Dev]] -> 13199 | G13: =IFERROR(SUMIF('Receta'!$A$2:$A$266,Productos!A13,'Receta'!$K$2:$K$266),"") -> 6161.34 | H13: =IFERROR(Productos!$F13-Productos!$G13,"") -> 7037.66 | I13: =IFERROR(Productos!$H13/Productos!$G13,"") -> 1.1422288
... A23: TU-08 | B23: Turbante Ro | C23: Turbante | D23: 4706 | E23: =ROUND(Productos[[#This Row],[Precio Neto]]*0.19,0) -> 894 | F23: =Productos[[#This Row],[Precio Neto]]+Productos[[#This Row],[IVA Dev]] -> 5600 | G23: =IFERROR(SUMIF('Receta'!$A$2:$A$266,Productos!A23,'Receta'!$K$2:$K$266),"") -> 1498.3363 | H23: =IFERROR(Productos!$F23-Productos!$G23,"") -> 4101.6637 | I23: =IFERROR(Productos!$H23/Productos!$G23,"") -> 2.7374788
D24: 0 | E24: =ROUND(Productos[[#This Row],[Precio Neto]]*0.19,0) -> 0 | F24: =Productos[[#This Row],[Precio Neto]]+Productos[[#This Row],[IVA Dev]] -> 0 | G24: =IFERROR(SUMIF('Receta'!$A$2:$A$266,Productos!A24,'Receta'!$K$2:$K$266),"") -> 0 | H24: =IFERROR(Productos!$F24-Productos!$G24,"") -> 0 | I24: =IFERROR(Productos!$H24/Productos!$G24,"")

Sheet Materias Primas
A1: Código | B1: Materia Prima | C1: Tipo | D1: Cantidad | E1: Unidad | F1: Costo Neto | G1: IVA Cred | H1: Costo Base | I1: Costo Ref | J1: CU
A2: TE-01 | B2: Microfibra Dep 160 Na | C2: MP | D2: 1 | E2: Mts | F2: 4118 | G2: =ROUND(Materias_Primas[[#This Row],[Costo Neto]]*0.19,0) -> 782 | H2: =Materias_Primas[[#This Row],[Costo Neto]]+Materias_Primas[[#This Row],[IVA Cred]] -> 4900 | I2: {=MAX(IF(Compras!$F$11:$F$155='Materias Primas'!$A2,Compras!$M$11:$M$155,'Materias Primas'!$H2))} -> 4900 | J2: =IFERROR(ROUND(I2/D2,0),"") -> 4900
A3: TE-02 | B3: Microfibra Dep 160 Li | C3: MP | D3: 1 | E3: Mts | F3: 4118 | G3: =ROUND(Materias_Primas[[#This Row],[Costo Neto]]*0.19,0) -> 782 | H3: =Materias_Primas[[#This Row],[Costo Neto]]+Materias_Primas[[#This Row],[IVA Cred]] -> 4900 | I3: {=MAX(IF(Compras!$F$11:$F$155='Materias Primas'!$A3,Compras!$M$11:$M$155,'Materias Primas'!$H3))} -> 4900 | J3: =IFERROR(ROUND(I3/D3,0),"") -> 4900
A4: TE-03 | B4: Microfibra Dep 160 Fu | C4: MP | D4: 1 | E4: Mts | F4: 4118 | G4: =ROUND(Materias_Primas[[#This Row],[Costo Neto]]*0.19,0) -> 782 | H4: =Materias_Primas[[#This Row],[Costo Neto]]+Materias_Primas[[#This Row],[IVA Cred]] -> 4900 | I4: {=MAX(IF(Compras!$F$11:$F$155='Materias Primas'!$A4,Compras!$M$11:$M$155,'Materias Primas'!$H4))} -> 4900 | J4: =IFERROR(ROUND(I4/D4,0),"") -> 4900
A5: TE-04 | B5: Microfibra Dep 160 Ca | C5: MP | D5: 1 | E5: Mts | F5: 4118 | G5: =ROUND(Materias_Primas[[#This Row],[Costo Neto]]*0.19,0) -> 782 | H5: =Materias_Primas[[#This Row],[Costo Neto]]+Materias_Primas[[#This Row],[IVA Cred]] -> 4900 | I5: {=MAX(IF(Compras!$F$11:$F$155='Materias Primas'!$A5,Compras!$M$11:$M$155,'Materias Primas'!$H5))} -> 4900 | J5: =IFERROR(ROUND(I5/D5,0),"") -> 4900
A6: TE-05 | B6: Microfibra Dep 160 Ne | C6: MP | D6: 1 | E6: Mts | F6: 4118 | G6: =ROUND(Materias_Primas[[#This Row],[Costo Neto]]*0.19,0) -> 782 | H6: =Materias_Primas[[#This Row],[Costo Neto]]+Materias_Primas[[#This Row],[IVA Cred]] -> 4900 | I6: {=MAX(IF(Compras!$F$11:$F$155='Materias Primas'!$A6,Compras!$M$11:$M$155,'Materias Primas'!$H6))} -> 4900 | J6: =IFERROR(ROUND(I6/D6,0),"") -> 4900
A7: TE-06 | B7: Microfibra Dep 160 Am | C7: MP | D7: 1 | E7: Mts | F7: 4118 | G7: =ROUND(Materias_Primas[[#This Row],[Costo Neto]]*0.19,0) -> 782 | H7: =Materias_Primas[[#This Row],[Costo Neto]]+Materias_Primas[[#This Row],[IVA Cred]] -> 4900 | I7: {=MAX(IF(Compras!$F$11:$F$155='Materias Primas'!$A7,Compras!$M$11:$M$155,'Materias Primas'!$H7))} -> 4900 | J7: =IFERROR(ROUND(I7/D7,0),"") -> 4900
A8: TE-07 | B8: Microfibra Dep 160 Ro | C8: MP | D8: 1 | E8: Mts | F8: 4118 | G8: =ROUND(Materias_Primas[[#This Row],[Costo Neto]]*0.19,0) -> 782 | H8: =Materias_Primas[[#This Row],[Costo Neto]]+Materias_Primas[[#This Row],[IVA Cred]] -> 4900 | I8: {=MAX(IF(Compras!$F$11:$F$155='Materias Primas'!$A8,Compras!$M$11:$M$155,'Materias Primas'!$H8))} -> 4900 | J8: =IFERROR(ROUND(I8/D8,0),"") -> 4900
A9: TE-08 | B9: Microfibra Dep 160 Vp | C9: MP | D9: 1 | E9: Mts | F9: 4118 | G9: =ROUND(Materias_Primas[[#This Row],[Costo Neto]]*0.19,0) -> 782 | H9: =Materias_Primas[[#This Row],[Costo Neto]]+Materias_Primas[[#This Row],[IVA Cred]] -> 4900 | I9: {=MAX(IF(Compras!$F$11:$F$155='Materias Primas'!$A9,Compras!$M$11:$M$155,'Materias Primas'!$H9))} -> 4900 | J9: =IFERROR(ROUND(I9/D9,0),"") -> 4900
A10: TE-09 | B10: Microfibra Dep 160 Az | C10: MP | D10: 1 | E10: Mts | F10: 4118 | G10: =ROUND(Materias_Primas[[#This Row],[Costo Neto]]*0.19,0) -> 782 | H10: =Materias_Primas[[#This Row],[Costo Neto]]+Materias_Primas[[#This Row],[IVA Cred]] -> 4900 | I10: {=MAX(IF(Compras!$F$11:$F$155='Materias Primas'!$A10,Compras!$M$11:$M$155,'Materias Primas'!$H10))} -> 4900 | J10: =IFERROR(ROUND(I10/D10,0),"") -> 4900
A11: TE-10 | B11: Bistrech 150 cm Ne | C11: MP | D11: 1 | E11: Mts | F11: 655 | G11: =ROUND(Materias_Primas[[#This Row],[Costo Neto]]*0.19,0) -> 124 | H11: =Materias_Primas[[#This Row],[Costo Neto]]+Materias_Primas[[#This Row],[IVA Cred]] -> 779 | I11: {=MAX(IF(Compras!$F$11:$F$155='Materias Primas'!$A11,Compras!$M$11:$M$155,'Materias Primas'!$H11))} -> 779 | J11: =IFERROR(ROUND(I11/D11,0),"") -> 779
A12: TE-11 | B12: Bistrech 300 cm Ne | C12: MP | D12: 1 | E12: Mts | F12: 1597 | G12: =ROUND(Materias_Primas[[#This Row],[Costo Neto]]*0.19,0) -> 303 | H12: =Materias_Primas[[#This Row],[Costo Neto]]+Materias_Primas[[#This Row],[IVA Cred]] -> 1900 | I12: {=MAX(IF(Compras!$F$11:$F$155='Materias Primas'!$A12,Compras!$M$11:$M$155,'Materias Primas'!$H12))} -> 1900 | J12: =IFERROR(ROUND(I12/D12,0),"") -> 1900
A13: TE-12 | B13: Mantel Spandex 180 Ne | C13: PT | D13: 1 | E13: Uni | F13: 0 | G13: =ROUND(Materias_Primas[[#This Row],[Costo Neto]]*0.19,0) -> 0 | H13: =Materias_Primas[[#This Row],[Costo Neto]]+Materias_Primas[[#This Row],[IVA Cred]] -> 0 | I13: {=MAX(IF(Compras!$F$11:$F$155='Materias Primas'!$A13,Compras!$M$11:$M$155,'Materias Primas'!$H13))} -> 0 | J13: =IFERROR(ROUND(I13/D13,0),"") -> 0
... A29: HI-03 | B29: Hilo Poliester | C29: MP | D29: 1 | E29: Uni | F29: 748 | G29: =ROUND(Materias_Primas[[#This Row],[Costo Neto]]*0.19,0) -> 142 | H29: =Materias_Primas[[#This Row],[Costo Neto]]+Materias_Primas[[#This Row],[IVA Cred]] -> 890 | I29: {=MAX(IF(Compras!$F$11:$F$155='Materias Primas'!$A29,Compras!$M$11:$M$155,'Materias Primas'!$H29))} -> 890 | J29: =IFERROR(ROUND(I29/D29,0),"") -> 890
F30: 0 | G30: =ROUND(Materias_Primas[[#This Row],[Costo Neto]]*0.19,0) -> 0 | H30: =Materias_Primas[[#This Row],[Costo Neto]]+Materias_Primas[[#This Row],[IVA Cred]] -> 0 | I30: {=MAX(IF(Compras!$F$11:$F$155='Materias Primas'!$A30,Compras!$M$11:$M$155,'Materias Primas'!$H30))} -> 0 | J30: =IFERROR(ROUND(I30/D30,0),"")
F31: 0 | G31: =ROUND(Materias_Primas[[#This Row],[Costo Neto]]*0.19,0) -> 0 | H31: =Materias_Primas[[#This Row],[Costo Neto]]+Materias_Primas[[#This Row],[IVA Cred]] -> 0 | I31: {=MAX(IF(Compras!$F$11:$F$155='Materias Primas'!$A31,Compras!$M$11:$M$155,'Materias Primas'!$H31))} -> 0 | J31: =IFERROR(ROUND(I31/D31,0),"")
F32: 0 | G32: =ROUND(Materias_Primas[[#This Row],[Costo Neto]]*0.19,0) -> 0 | H32: =Materias_Primas[[#This Row],[Costo Neto]]+Materias_Primas[[#This Row],[IVA Cred]] -> 0 | I32: {=MAX(IF(Compras!$F$11:$F$155='Materias Primas'!$A32,Compras!$M$11:$M$155,'Materias Primas'!$H32))} -> 0 | J32: =IFERROR(ROUND(I32/D32,0),"")
F33: 0 | G33: =ROUND(Materias_Primas[[#This Row],[Costo Neto]]*0.19,0) -> 0 | H33: =Materias_Primas[[#This Row],[Costo Neto]]+Materias_Primas[[#This Row],[IVA Cred]] -> 0 | I33: {=MAX(IF(Compras!$F$11:$F$155='Materias Primas'!$A33,Compras!$M$11:$M$155,'Materias Primas'!$H33))} -> 0 | J33: =IFERROR(ROUND(I33/D33,0),"")
F34: 0 | G34: =ROUND(Materias_Primas[[#This Row],[Costo Neto]]*0.19,0) -> 0 | H34: =Materias_Primas[[#This Row],[Costo Neto]]+Materias_Primas[[#This Row],[IVA Cred]] -> 0 | I34: {=MAX(IF(Compras!$F$11:$F$155='Materias Primas'!$A34,Compras!$M$11:$M$155,'Materias Primas'!$H34))} -> 0 | J34: =IFERROR(ROUND(I34/D34,0),"")
F35: 0 | G35: =ROUND(Materias_Primas[[#This Row],[Costo Neto]]*0.19,0) -> 0 | H35: =Materias_Primas[[#This Row],[Costo Neto]]+Materias_Primas[[#This Row],[IVA Cred]] -> 0 | I35: {=MAX(IF(Compras!$F$11:$F$155='Materias Primas'!$A35,Compras!$M$11:$M$155,'Materias Primas'!$H35))} -> 0 | J35: =IFERROR(ROUND(I35/D35,0),"")
F36: 0 | G36: =ROUND(Materias_Primas[[#This Row],[Costo Neto]]*0.19,0) -> 0 | H36: =Materias_Primas[[#This Row],[Costo Neto]]+Materias_Primas[[#This Row],[IVA Cred]] -> 0 | I36: {=MAX(IF(Compras!$F$11:$F$155='Materias Primas'!$A36,Compras!$M$11:$M$155,'Materias Primas'!$H36))} -> 0 | J36: =IFERROR(ROUND(I36/D36,0),"")
F37: 0 | G37: =ROUND(Materias_Primas[[#This Row],[Costo Neto]]*0.19,0) -> 0 | H37: =Materias_Primas[[#This Row],[Costo Neto]]+Materias_Primas[[#This Row],[IVA Cred]] -> 0 | I37: {=MAX(IF(Compras!$F$11:$F$155='Materias Primas'!$A37,Compras!$M$11:$M$155,'Materias Primas'!$H37))} -> 0 | J37: =IFERROR(ROUND(I37/D37,0),"")
F38: 0 | G38: =ROUND(Materias_Primas[[#This Row],[Costo Neto]]*0.19,0) -> 0 | H38: =Materias_Primas[[#This Row],[Costo Neto]]+Materias_Primas[[#This Row],[IVA Cred]] -> 0 | I38: {=MAX(IF(Compras!$F$11:$F$155='Materias Primas'!$A38,Compras!$M$11:$M$155,'Materias Primas'!$H38))} -> 0 | J38: =IFERROR(ROUND(I38/D38,0),"")
F39: 0 | G39: =ROUND(Materias_Primas[[#This Row],[Costo Neto]]*0.19,0) -> 0 | H39: =Materias_Primas[[#This Row],[Costo Neto]]+Materias_Primas[[#This Row],[IVA Cred]] -> 0 | I39: {=MAX(IF(Compras!$F$11:$F$155='Materias Primas'!$A39,Compras!$M$11:$M$155,'Materias Primas'!$H39))} -> 0 | J39: =IFERROR(ROUND(I39/D39,0),"")
F40: 0 | G40: =ROUND(Materias_Primas[[#This Row],[Costo Neto]]*0.19,0) -> 0 | H40: =Materias_Primas[[#This Row],[Costo Neto]]+Materias_Primas[[#This Row],[IVA Cred]] -> 0 | I40: {=MAX(IF(Compras!$F$11:$F$155='Materias Primas'!$A40,Compras!$M$11:$M$155,'Materias Primas'!$H40))} -> 0 | J40: =IFERROR(ROUND(I40/D40,0),"")
A41: GA-01 | B41: Locomoción | D41: 1 | E41: Uni | F41: 840 | G41: =ROUND(Materias_Primas[[#This Row],[Costo Neto]]*0.19,0) -> 160 | H41: =Materias_Primas[[#This Row],[Costo Neto]]+Materias_Primas[[#This Row],[IVA Cred]] -> 1000 | I41: {=MAX(IF(Compras!$F$11:$F$155='Materias Primas'!$A41,Compras!$M$11:$M$155,'Materias Primas'!$H41))} -> 1000 | J41: =IFERROR(ROUND(I41/D41,0),"") -> 1000
F42: 0 | G42: =ROUND(Materias_Primas[[#This Row],[Costo Neto]]*0.19,0) -> 0 | H42: =Materias_Primas[[#This Row],[Costo Neto]]+Materias_Primas[[#This Row],[IVA Cred]] -> 0 | I42: {=MAX(IF(Compras!$F$11:$F$155='Materias Primas'!$A42,Compras!$M$11:$M$155,'Materias Primas'!$H42))} -> 0 | J42: =IFERROR(ROUND(I42/D42,0),"")
F43: 0 | G43: =ROUND(Materias_Primas[[#This Row],[Costo Neto]]*0.19,0) -> 0 | H43: =Materias_Primas[[#This Row],[Costo Neto]]+Materias_Primas[[#This Row],[IVA Cred]] -> 0 | I43: {=MAX(IF(Compras!$F$11:$F$155='Materias Primas'!$A43,Compras!$M$11:$M$155,'Materias Primas'!$H43))} -> 0 | J43: =IFERROR(ROUND(I43/D43,0),"")
A44: SE-01 | B44: DTF | D44: 1 | E44: Cm2 | F44: 30 | G44: =ROUND(Materias_Primas[[#This Row],[Costo Neto]]*0.19,0) -> 6 | H44: =Materias_Primas[[#This Row],[Costo Neto]]+Materias_Primas[[#This Row],[IVA Cred]] -> 36 | I44: {=MAX(IF(Compras!$F$11:$F$155='Materias Primas'!$A44,Compras!$M$11:$M$155,'Materias Primas'!$H44))} -> 36 | J44: =IFERROR(ROUND(I44/D44,0),"") -> 36
F45: 0 | G45: =ROUND(Materias_Primas[[#This Row],[Costo Neto]]*0.19,0) -> 0 | H45: =Materias_Primas[[#This Row],[Costo Neto]]+Materias_Primas[[#This Row],[IVA Cred]] -> 0 | I45: {=MAX(IF(Compras!$F$11:$F$155='Materias Primas'!$A45,Compras!$M$11:$M$155,'Materias Primas'!$H45))} -> 0 | J45: =IFERROR(ROUND(I45/D45,0),"")
F46: 0 | G46: =ROUND(Materias_Primas[[#This Row],[Costo Neto]]*0.19,0) -> 0 | H46: =Materias_Primas[[#This Row],[Costo Neto]]+Materias_Primas[[#This Row],[IVA Cred]] -> 0 | I46: {=MAX(IF(Compras!$F$11:$F$155='Materias Primas'!$A46,Compras!$M$11:$M$155,'Materias Primas'!$H46))} -> 0 | J46: =IFERROR(ROUND(I46/D46,0),"")
F47: 0 | G47: =ROUND(Materias_Primas[[#This Row],[Costo Neto]]*0.19,0) -> 0 | H47: =Materias_Primas[[#This Row],[Costo Neto]]+Materias_Primas[[#This Row],[IVA Cred]] -> 0 | I47: {=MAX(IF(Compras!$F$11:$F$155='Materias Primas'!$A47,Compras!$M$11:$M$155,'Materias Primas'!$H47))} -> 0 | J47: =IFERROR(ROUND(I47/D47,0),"")
F48: 0 | G48: =ROUND(Materias_Primas[[#This Row],[Costo Neto]]*0.19,0) -> 0 | H48: =Materias_Primas[[#This Row],[Costo Neto]]+Materias_Primas[[#This Row],[IVA Cred]] -> 0 | I48: {=MAX(IF(Compras!$F$11:$F$155='Materias Primas'!$A48,Compras!$M$11:$M$155,'Materias Primas'!$H48))} -> 0 | J48: =IFERROR(ROUND(I48/D48,0),"")
F49: 0 | G49: =ROUND(Materias_Primas[[#This Row],[Costo Neto]]*0.19,0) -> 0 | H49: =Materias_Primas[[#This Row],[Costo Neto]]+Materias_Primas[[#This Row],[IVA Cred]] -> 0 | I49: {=MAX(IF(Compras!$F$11:$F$155='Materias Primas'!$A49,Compras!$M$11:$M$155,'Materias Primas'!$H49))} -> 0 | J49: =IFERROR(ROUND(I49/D49,0),"")
F50: 0 | G50: =ROUND(Materias_Primas[[#This Row],[Costo Neto]]*0.19,0) -> 0 | H50: =Materias_Primas[[#This Row],[Costo Neto]]+Materias_Primas[[#This Row],[IVA Cred]] -> 0 | I50: {=MAX(IF(Compras!$F$11:$F$155='Materias Primas'!$A50,Compras!$M$11:$M$155,'Materias Primas'!$H50))} -> 0 | J50: =IFERROR(ROUND(I50/D50,0),"")
F51: 0 | G51: =ROUND(Materias_Primas[[#This Row],[Costo Neto]]*0.19,0) -> 0 | H51: =Materias_Primas[[#This Row],[Costo Neto]]+Materias_Primas[[#This Row],[IVA Cred]] -> 0 | I51: {=MAX(IF(Compras!$F$11:$F$155='Materias Primas'!$A51,Compras!$M$11:$M$155,'Materias Primas'!$H51))} -> 0 | J51: =IFERROR(ROUND(I51/D51,0),"")
F52: 0 | G52: =ROUND(Materias_Primas[[#This Row],[Costo Neto]]*0.19,0) -> 0 | H52: =Materias_Primas[[#This Row],[Costo Neto]]+Materias_Primas[[#This Row],[IVA Cred]] -> 0 | I52: {=MAX(IF(Compras!$F$11:$F$155='Materias Primas'!$A52,Compras!$M$11:$M$155,'Materias Primas'!$H52))} -> 0 | J52: =IFERROR(ROUND(I52/D52,0),"")
F53: 0 | G53: =ROUND(Materias_Primas[[#This Row],[Costo Neto]]*0.19,0) -> 0 | H53: =Materias_Primas[[#This Row],[Costo Neto]]+Materias_Primas[[#This Row],[IVA Cred]] -> 0 | I53: {=MAX(IF(Compras!$F$11:$F$155='Materias Primas'!$A53,Compras!$M$11:$M$155,'Materias Primas'!$H53))} -> 0 | J53: =IFERROR(ROUND(I53/D53,0),"")
F54: 0 | G54: =ROUND(Materias_Primas[[#This Row],[Costo Neto]]*0.19,0) -> 0 | H54: =Materias_Primas[[#This Row],[Costo Neto]]+Materias_Primas[[#This Row],[IVA Cred]] -> 0 | I54: {=MAX(IF(Compras!$F$11:$F$155='Materias Primas'!$A54,Compras!$M$11:$M$155,'Materias Primas'!$H54))} -> 0 | J54: =IFERROR(ROUND(I54/D54,0),"")
F55: 0 | G55: =ROUND(Materias_Primas[[#This Row],[Costo Neto]]*0.19,0) -> 0 | H55: =Materias_Primas[[#This Row],[Costo Neto]]+Materias_Primas[[#This Row],[IVA Cred]] -> 0 | I55: {=MAX(IF(Compras!$F$11:$F$155='Materias Primas'!$A55,Compras!$M$11:$M$155,'Materias Primas'!$H55))} -> 0 | J55: =IFERROR(ROUND(I55/D55,0),"")
F56: 0 | G56: =ROUND(Materias_Primas[[#This Row],[Costo Neto]]*0.19,0) -> 0 | H56: =Materias_Primas[[#This Row],[Costo Neto]]+Materias_Primas[[#This Row],[IVA Cred]] -> 0 | I56: {=MAX(IF(Compras!$F$11:$F$155='Materias Primas'!$A56,Compras!$M$11:$M$155,'Materias Primas'!$H56))} -> 0 | J56: =IFERROR(ROUND(I56/D56,0),"")
... F59: 0 | G59: =ROUND(Materias_Primas[[#This Row],[Costo Neto]]*0.19,0) -> 0 | H59: =Materias_Primas[[#This Row],[Costo Neto]]+Materias_Primas[[#This Row],[IVA Cred]] -> 0 | I59: {=MAX(IF(Compras!$F$11:$F$155='Materias Primas'!$A59,Compras!$M$11:$M$155,'Materias Primas'!$H59))} -> 0 | J59: =IFERROR(ROUND(I59/D59,0),"")

Sheet Receta
A1: Código | B1: Nombre P | C1: Cant PR | D1: ÍTEM | E1: M P | F1: TIPO | G1: Nombre | H1: Cant MP | I1: Unid | J1: C R | K1: CU | L1: Tipo2
A2: TO-07 | B2: =IFERROR(VLOOKUP('Receta'!$A2,Productos[#All],2,0),"") -> Toalla 160x80 Na | C2: 1 | D2: 1 | E2: TE-01 | F2: =IFERROR(VLOOKUP(E2,Materias_Primas[#All],3,0),"") -> MP | G2: =IFERROR(VLOOKUP('Receta'!$E2,Materias_Primas[#All],2,0),"") -> Microfibra Dep 160 Na | H2: 0.8 | I2: =IFERROR(VLOOKUP('Receta'!$E2,Materias_Primas[#All],5,0),"") -> Mts | J2: =IFERROR(H2*VLOOKUP('Receta'!$E2,Materias_Primas[#All],10,0),"") -> 3920 | K2: =IFERROR('Receta'!$J2/'Receta'!$C2,"") -> 3920 | L2: =IFERROR(VLOOKUP('Receta'!$A2,Productos[#All],3,0),"") -> Toalla
A3: TO-07 | B3: =IFERROR(VLOOKUP('Receta'!$A3,Productos[#All],2,0),"") -> Toalla 160x80 Na | C3: 1 | D3: 2 | E3: HI-01 | F3: =IFERROR(VLOOKUP(E3,Materias_Primas[#All],3,0),"") -> IN | G3: =IFERROR(VLOOKUP('Receta'!$E3,Materias_Primas[#All],2,0),"") -> Hilo Overlock Verde | H3: =1/25 -> 0.04 | I3: =IFERROR(VLOOKUP('Receta'!$E3,Materias_Primas[#All],5,0),"") -> Uni | J3: =IFERROR(H3*VLOOKUP('Receta'!$E3,Materias_Primas[#All],10,0),"") -> 51.96 | K3: =IFERROR('Receta'!$J3/'Receta'!$C3,"") -> 51.96 | L3: =IFERROR(VLOOKUP('Receta'!$A3,Productos[#All],3,0),"") -> Toalla
A4: TO-07 | B4: =IFERROR(VLOOKUP('Receta'!$A4,Productos[#All],2,0),"") -> Toalla 160x80 Na | C4: 1 | D4: 3 | E4: HI-02 | F4: =IFERROR(VLOOKUP(E4,Materias_Primas[#All],3,0),"") -> IN | G4: =IFERROR(VLOOKUP('Receta'!$E4,Materias_Primas[#All],2,0),"") -> Hilo Recta Verde | H4: 0.04 | I4: =IFERROR(VLOOKUP('Receta'!$E4,Materias_Primas[#All],5,0),"") -> Uni | J4: =IFERROR(H4*VLOOKUP('Receta'!$E4,Materias_Primas[#All],10,0),"") -> 35.6 | K4: =IFERROR('Receta'!$J4/'Receta'!$C4,"") -> 35.6 | L4: =IFERROR(VLOOKUP('Receta'!$A4,Productos[#All],3,0),"") -> Toalla
A5: TO-07 | B5: =IFERROR(VLOOKUP('Receta'!$A5,Productos[#All],2,0),"") -> Toalla 160x80 Na | C5: 1 | D5: 4 | E5: GA-01 | F5: =IFERROR(VLOOKUP(E5,Materias_Primas[#All],3,0),"") -> 0 | G5: =IFERROR(VLOOKUP('Receta'!$E5,Materias_Primas[#All],2,0),"") -> Locomoción | H5: 0.1 | I5: =IFERROR(VLOOKUP('Receta'!$E5,Materias_Primas[#All],5,0),"") -> Uni | J5: =IFERROR(H5*VLOOKUP('Receta'!$E5,Materias_Primas[#All],10,0),"") -> 100 | K5: =IFERROR('Receta'!$J5/'Receta'!$C5,"") -> 100 | L5: =IFERROR(VLOOKUP('Receta'!$A5,Productos[#All],3,0),"") -> Toalla
A6: TO-06 | B6: =IFERROR(VLOOKUP('Receta'!$A6,Productos[#All],2,0),"") -> Toalla 160x80 Fu | C6: 1 | D6: 1 | E6: TE-03 | F6: =IFERROR(VLOOKUP(E6,Materias_Primas[#All],3,0),"") -> MP | G6: =IFERROR(VLOOKUP('Receta'!$E6,Materias_Primas[#All],2,0),"") -> Microfibra Dep 160 Fu | H6: 0.8 | I6: =IFERROR(VLOOKUP('Receta'!$E6,Materias_Primas[#All],5,0),"") -> Mts | J6: =IFERROR(H6*VLOOKUP('Receta'!$E6,Materias_Primas[#All],10,0),"") -> 3920 | K6: =IFERROR('Receta'!$J6/'Receta'!$C6,"") -> 3920 | L6: =IFERROR(VLOOKUP('Receta'!$A6,Productos[#All],3,0),"") -> Toalla
A7: TO-06 | B7: =IFERROR(VLOOKUP('Receta'!$A7,Productos[#All],2,0),"") -> Toalla 160x80 Fu | C7: 1 | D7: 2 | E7: HI-01 | F7: =IFERROR(VLOOKUP(E7,Materias_Primas[#All],3,0),"") -> IN | G7: =IFERROR(VLOOKUP('Receta'!$E7,Materias_Primas[#All],2,0),"") -> Hilo Overlock Verde | H7: =1/25 -> 0.04 | I7: =IFERROR(VLOOKUP('Receta'!$E7,Materias_Primas[#All],5,0),"") -> Uni | J7: =IFERROR(H7*VLOOKUP('Receta'!$E7,Materias_Primas[#All],10,0),"") -> 51.96 | K7: =IFERROR('Receta'!$J7/'Receta'!$C7,"") -> 51.96 | L7: =IFERROR(VLOOKUP('Receta'!$A7,Productos[#All],3,0),"") -> Toalla
A8: TO-06 | B8: =IFERROR(VLOOKUP('Receta'!$A8,Productos[#All],2,0),"") -> Toalla 160x80 Fu | C8: 1 | D8: 3 | E8: HI-02 | F8: =IFERROR(VLOOKUP(E8,Materias_Primas[#All],3,0),"") -> IN | G8: =IFERROR(VLOOKUP('Receta'!$E8,Materias_Primas[#All],2,0),"") -> Hilo Recta Verde | H8: 0.04 | I8: =IFERROR(VLOOKUP('Receta'!$E8,Materias_Primas[#All],5,0),"") -> Uni | J8: =IFERROR(H8*VLOOKUP('Receta'!$E8,Materias_Primas[#All],10,0),"") -> 35.6 | K8: =IFERROR('Receta'!$J8/'Receta'!$C8,"") -> 35.6 | L8: =IFERROR(VLOOKUP('Receta'!$A8,Productos[#All],3,0),"") -> Toalla
A9: TO-06 | B9: =IFERROR(VLOOKUP('Receta'!$A9,Productos[#All],2,0),"") -> Toalla 160x80 Fu | C9: 1 | D9: 4 | E9: GA-01 | F9: =IFERROR(VLOOKUP(E9,Materias_Primas[#All],3,0),"") -> 0 | G9: =IFERROR(VLOOKUP('Receta'!$E9,Materias_Primas[#All],2,0),"") -> Locomoción | H9: 0.1 | I9: =IFERROR(VLOOKUP('Receta'!$E9,Materias_Primas[#All],5,0),"") -> Uni | J9: =IFERROR(H9*VLOOKUP('Receta'!$E9,Materias_Primas[#All],10,0),"") -> 100 | K9: =IFERROR('Receta'!$J9/'Receta'!$C9,"") -> 100 | L9: =IFERROR(VLOOKUP('Receta'!$A9,Productos[#All],3,0),"") -> Toalla
A10: TO-01 | B10: =IFERROR(VLOOKUP('Receta'!$A10,Productos[#All],2,0),"") -> Toalla 160x80 Az | C10: 1 | D10: 1 | E10: TE-09 | F10: =IFERROR(VLOOKUP(E10,Materias_Primas[#All],3,0),"") -> MP | G10: =IFERROR(VLOOKUP('Receta'!$E10,Materias_Primas[#All],2,0),"") -> Microfibra Dep 160 Az | H10: 0.8 | I10: =IFERROR(VLOOKUP('Receta'!$E10,Materias_Primas[#All],5,0),"") -> Mts | J10: =IFERROR(H10*VLOOKUP('Receta'!$E10,Materias_Primas[#All],10,0),"") -> 3920 | K10: =IFERROR('Receta'!$J10/'Receta'!$C10,"") -> 3920 | L10: =IFERROR(VLOOKUP('Receta'!$A10,Productos[#All],3,0),"") -> Toalla
A11: TO-01 | B11: =IFERROR(VLOOKUP('Receta'!$A11,Productos[#All],2,0),"") -> Toalla 160x80 Az | C11: 1 | D11: 2 | E11: HI-01 | F11: =IFERROR(VLOOKUP(E11,Materias_Primas[#All],3,0),"") -> IN | G11: =IFERROR(VLOOKUP('Receta'!$E11,Materias_Primas[#All],2,0),"") -> Hilo Overlock Verde | H11: =1/25 -> 0.04 | I11: =IFERROR(VLOOKUP('Receta'!$E11,Materias_Primas[#All],5,0),"") -> Uni | J11: =IFERROR(H11*VLOOKUP('Receta'!$E11,Materias_Primas[#All],10,0),"") -> 51.96 | K11: =IFERROR('Receta'!$J11/'Receta'!$C11,"") -> 51.96 | L11: =IFERROR(VLOOKUP('Receta'!$A11,Productos[#All],3,0),"") -> Toalla
A12: TO-01 | B12: =IFERROR(VLOOKUP('Receta'!$A12,Productos[#All],2,0),"") -> Toalla 160x80 Az | C12: 1 | D12: 3 | E12: HI-02 | F12: =IFERROR(VLOOKUP(E12,Materias_Primas[#All],3,0),"") -> IN | G12: =IFERROR(VLOOKUP('Receta'!$E12,Materias_Primas[#All],2,0),"") -> Hilo Recta Verde | H12: 0.04 | I12: =IFERROR(VLOOKUP('Receta'!$E12,Materias_Primas[#All],5,0),"") -> Uni | J12: =IFERROR(H12*VLOOKUP('Receta'!$E12,Materias_Primas[#All],10,0),"") -> 35.6 | K12: =IFERROR('Receta'!$J12/'Receta'!$C12,"") -> 35.6 | L12: =IFERROR(VLOOKUP('Receta'!$A12,Productos[#All],3,0),"") -> Toalla
A13: TO-01 | B13: =IFERROR(VLOOKUP('Receta'!$A13,Productos[#All],2,0),"") -> Toalla 160x80 Az | C13: 1 | D13: 4 | E13: GA-01 | F13: =IFERROR(VLOOKUP(E13,Materias_Primas[#All],3,0),"") -> 0 | G13: =IFERROR(VLOOKUP('Receta'!$E13,Materias_Primas[#All],2,0),"") -> Locomoción | H13: 0.1 | I13: =IFERROR(VLOOKUP('Receta'!$E13,Materias_Primas[#All],5,0),"") -> Uni | J13: =IFERROR(H13*VLOOKUP('Receta'!$E13,Materias_Primas[#All],10,0),"") -> 100 | K13: =IFERROR('Receta'!$J13/'Receta'!$C13,"") -> 100 | L13: =IFERROR(VLOOKUP('Receta'!$A13,Productos[#All],3,0),"") -> Toalla
A14: TO-02 | B14: =IFERROR(VLOOKUP('Receta'!$A14,Productos[#All],2,0),"") -> Toalla 160x80 Ro | C14: 1 | D14: 1 | E14: TE-07 | F14: =IFERROR(VLOOKUP(E14,Materias_Primas[#All],3,0),"") -> MP | G14: =IFERROR(VLOOKUP('Receta'!$E14,Materias_Primas[#All],2,0),"") -> Microfibra Dep 160 Ro | H14: 0.8 | I14: =IFERROR(VLOOKUP('Receta'!$E14,Materias_Primas[#All],5,0),"") -> Mts | J14: =IFERROR(H14*VLOOKUP('Receta'!$E14,Materias_Primas[#All],10,0),"") -> 3920 | K14: =IFERROR('Receta'!$J14/'Receta'!$C14,"") -> 3920 | L14: =IFERROR(VLOOKUP('Receta'!$A14,Productos[#All],3,0),"") -> Toalla
A15: TO-02 | B15: =IFERROR(VLOOKUP('Receta'!$A15,Productos[#All],2,0),"") -> Toalla 160x80 Ro | C15: 1 | D15: 2 | E15: HI-01 | F15: =IFERROR(VLOOKUP(E15,Materias_Primas[#All],3,0),"") -> IN | G15: =IFERROR(VLOOKUP('Receta'!$E15,Materias_Primas[#All],2,0),"") -> Hilo Overlock Verde | H15: =1/25 -> 0.04 | I15: =IFERROR(VLOOKUP('Receta'!$E15,Materias_Primas[#All],5,0),"") -> Uni | J15: =IFERROR(H15*VLOOKUP('Receta'!$E15,Materias_Primas[#All],10,0),"") -> 51.96 | K15: =IFERROR('Receta'!$J15/'Receta'!$C15,"") -> 51.96 | L15: =IFERROR(VLOOKUP('Receta'!$A15,Productos[#All],3,0),"") -> Toalla
A16: TO-02 | B16: =IFERROR(VLOOKUP('Receta'!$A16,Productos[#All],2,0),"") -> Toalla 160x80 Ro | C16: 1 | D16: 3 | E16: HI-02 | F16: =IFERROR(VLOOKUP(E16,Materias_Primas[#All],3,0),"") -> IN | G16: =IFERROR(VLOOKUP('Receta'!$E16,Materias_Primas[#All],2,0),"") -> Hilo Recta Verde | H16: 0.04 | I16: =IFERROR(VLOOKUP('Receta'!$E16,Materias_Primas[#All],5,0),"") -> Uni | J16: =IFERROR(H16*VLOOKUP('Receta'!$E16,Materias_Primas[#All],10,0),"") -> 35.6 | K16: =IFERROR('Receta'!$J16/'Receta'!$C16,"") -> 35.6 | L16: =IFERROR(VLOOKUP('Receta'!$A16,Productos[#All],3,0),"") -> Toalla
A17: TO-02 | B17: =IFERROR(VLOOKUP('Receta'!$A17,Productos[#All],2,0),"") -> Toalla 160x80 Ro | C17: 1 | D17: 4 | E17: GA-01 | F17: =IFERROR(VLOOKUP(E17,Materias_Primas[#All],3,0),"") -> 0 | G17: =IFERROR(VLOOKUP('Receta'!$E17,Materias_Primas[#All],2,0),"") -> Locomoción | H17: 0.1 | I17: =IFERROR(VLOOKUP('Receta'!$E17,Materias_Primas[#All],5,0),"") -> Uni | J17: =IFERROR(H17*VLOOKUP('Receta'!$E17,Materias_Primas[#All],10,0),"") -> 100 | K17: =IFERROR('Receta'!$J17/'Receta'!$C17,"") -> 100 | L17: =IFERROR(VLOOKUP('Receta'!$A17,Productos[#All],3,0),"") -> Toalla
A18: TO-04 | B18: =IFERROR(VLOOKUP('Receta'!$A18,Productos[#All],2,0),"") -> Toalla 160x80 Vp | C18: 1 | D18: 1 | E18: TE-08 | F18: =IFERROR(VLOOKUP(E18,Materias_Primas[#All],3,0),"") -> MP | G18: =IFERROR(VLOOKUP('Receta'!$E18,Materias_Primas[#All],2,0),"") -> Microfibra Dep 160 Vp | H18: 0.8 | I18: =IFERROR(VLOOKUP('Receta'!$E18,Materias_Primas[#All],5,0),"") -> Mts | J18: =IFERROR(H18*VLOOKUP('Receta'!$E18,Materias_Primas[#All],10,0),"") -> 3920 | K18: =IFERROR('Receta'!$J18/'Receta'!$C18,"") -> 3920 | L18: =IFERROR(VLOOKUP('Receta'!$A18,Productos[#All],3,0),"") -> Toalla
A19: TO-04 | B19: =IFERROR(VLOOKUP('Receta'!$A19,Productos[#All],2,0),"") -> Toalla 160x80 Vp | C19: 1 | D19: 2 | E19: HI-01 | F19: =IFERROR(VLOOKUP(E19,Materias_Primas[#All],3,0),"") -> IN | G19: =IFERROR(VLOOKUP('Receta'!$E19,Materias_Primas[#All],2,0),"") -> Hilo Overlock Verde | H19: =1/25 -> 0.04 | I19: =IFERROR(VLOOKUP('Receta'!$E19,Materias_Primas[#All],5,0),"") -> Uni | J19: =IFERROR(H19*VLOOKUP('Receta'!$E19,Materias_Primas[#All],10,0),"") -> 51.96 | K19: =IFERROR('Receta'!$J19/'Receta'!$C19,"") -> 51.96 | L19: =IFERROR(VLOOKUP('Receta'!$A19,Productos[#All],3,0),"") -> Toalla
A20: TO-04 | B20: =IFERROR(VLOOKUP('Receta'!$A20,Productos[#All],2,0),"") -> Toalla 160x80 Vp | C20: 1 | D20: 3 | E20: HI-02 | F20: =IFERROR(VLOOKUP(E20,Materias_Primas[#All],3,0),"") -> IN | G20: =IFERROR(VLOOKUP('Receta'!$E20,Materias_Primas[#All],2,0),"") -> Hilo Recta Verde | H20: 0.04 | I20: =IFERROR(VLOOKUP('Receta'!$E20,Materias_Primas[#All],5,0),"") -> Uni | J20: =IFERROR(H20*VLOOKUP('Receta'!$E20,Materias_Primas[#All],10,0),"") -> 35.6 | K20: =IFERROR('Receta'!$J20/'Receta'!$C20,"") -> 35.6 | L20: =IFERROR(VLOOKUP('Receta'!$A20,Productos[#All],3,0),"") -> Toalla
A21: TO-04 | B21: =IFERROR(VLOOKUP('Receta'!$A21,Productos[#All],2,0),"") -> Toalla 160x80 Vp | C21: 1 | D21: 4 | E21: GA-01 | F21: =IFERROR(VLOOKUP(E21,Materias_Primas[#All],3,0),"") -> 0 | G21: =IFERROR(VLOOKUP('Receta'!$E21,Materias_Primas[#All],2,0),"") -> Locomoción | H21: 0.1 | I21: =IFERROR(VLOOKUP('Receta'!$E21,Materias_Primas[#All],5,0),"") -> Uni | J21: =IFERROR(H21*VLOOKUP('Receta'!$E21,Materias_Primas[#All],10,0),"") -> 100 | K21: =IFERROR('Receta'!$J21/'Receta'!$C21,"") -> 100 | L21: =IFERROR(VLOOKUP('Receta'!$A21,Productos[#All],3,0),"") -> Toalla
A22: TO-05 | B22: =IFERROR(VLOOKUP('Receta'!$A22,Productos[#All],2,0),"") -> Toalla 160x80 Ca | C22: 1 | D22: 1 | E22: TE-04 | F22: =IFERROR(VLOOKUP(E22,Materias_Primas[#All],3,0),"") -> MP | G22: =IFERROR(VLOOKUP('Receta'!$E22,Materias_Primas[#All],2,0),"") -> Microfibra Dep 160 Ca | H22: 0.8 | I22: =IFERROR(VLOOKUP('Receta'!$E22,Materias_Primas[#All],5,0),"") -> Mts | J22: =IFERROR(H22*VLOOKUP('Receta'!$E22,Materias_Primas[#All],10,0),"") -> 3920 | K22: =IFERROR('Receta'!$J22/'Receta'!$C22,"") -> 3920 | L22: =IFERROR(VLOOKUP('Receta'!$A22,Productos[#All],3,0),"") -> Toalla
A23: TO-05 | B23: =IFERROR(VLOOKUP('Receta'!$A23,Productos[#All],2,0),"") -> Toalla 160x80 Ca | C23: 1 | D23: 2 | E23: HI-01 | F23: =IFERROR(VLOOKUP(E23,Materias_Primas[#All],3,0),"") -> IN | G23: =IFERROR(VLOOKUP('Receta'!$E23,Materias_Primas[#All],2,0),"") -> Hilo Overlock Verde | H23: =1/25 -> 0.04 | I23: =IFERROR(VLOOKUP('Receta'!$E23,Materias_Primas[#All],5,0),"") -> Uni | J23: =IFERROR(H23*VLOOKUP('Receta'!$E23,Materias_Primas[#All],10,0),"") -> 51.96 | K23: =IFERROR('Receta'!$J23/'Receta'!$C23,"") -> 51.96 | L23: =IFERROR(VLOOKUP('Receta'!$A23,Productos[#All],3,0),"") -> Toalla
A24: TO-05 | B24: =IFERROR(VLOOKUP('Receta'!$A24,Productos[#All],2,0),"") -> Toalla 160x80 Ca | C24: 1 | D24: 3 | E24: HI-02 | F24: =IFERROR(VLOOKUP(E24,Materias_Primas[#All],3,0),"") -> IN | G24: =IFERROR(VLOOKUP('Receta'!$E24,Materias_Primas[#All],2,0),"") -> Hilo Recta Verde | H24: 0.04 | I24: =IFERROR(VLOOKUP('Receta'!$E24,Materias_Primas[#All],5,0),"") -> Uni | J24: =IFERROR(H24*VLOOKUP('Receta'!$E24,Materias_Primas[#All],10,0),"") -> 35.6 | K24: =IFERROR('Receta'!$J24/'Receta'!$C24,"") -> 35.6 | L24: =IFERROR(VLOOKUP('Receta'!$A24,Productos[#All],3,0),"") -> Toalla
A25: TO-05 | B25: =IFERROR(VLOOKUP('Receta'!$A25,Productos[#All],2,0),"") -> Toalla 160x80 Ca | C25: 1 | D25: 4 | E25: GA-01 | F25: =IFERROR(VLOOKUP(E25,Materias_Primas[#All],3,0),"") -> 0 | G25: =IFERROR(VLOOKUP('Receta'!$E25,Materias_Primas[#All],2,0),"") -> Locomoción | H25: 0.1 | I25: =IFERROR(VLOOKUP('Receta'!$E25,Materias_Primas[#All],5,0),"") -> Uni | J25: =IFERROR(H25*VLOOKUP('Receta'!$E25,Materias_Primas[#All],10,0),"") -> 100 | K25: =IFERROR('Receta'!$J25/'Receta'!$C25,"") -> 100 | L25: =IFERROR(VLOOKUP('Receta'!$A25,Productos[#All],3,0),"") -> Toalla
A26: TO-08 | B26: =IFERROR(VLOOKUP('Receta'!$A26,Productos[#All],2,0),"") -> Toalla 160x80 Ne | C26: 1 | D26: 1 | E26: TE-05 | F26: =IFERROR(VLOOKUP(E26,Materias_Primas[#All],3,0),"") -> MP | G26: =IFERROR(VLOOKUP('Receta'!$E26,Materias_Primas[#All],2,0),"") -> Microfibra Dep 160 Ne | H26: 0.8 | I26: =IFERROR(VLOOKUP('Receta'!$E26,Materias_Primas[#All],5,0),"") -> Mts | J26: =IFERROR(H26*VLOOKUP('Receta'!$E26,Materias_Primas[#All],10,0),"") -> 3920 | K26: =IFERROR('Receta'!$J26/'Receta'!$C26,"") -> 3920 | L26: =IFERROR(VLOOKUP('Receta'!$A26,Productos[#All],3,0),"") -> Toalla
A27: TO-08 | B27: =IFERROR(VLOOKUP('Receta'!$A27,Productos[#All],2,0),"") -> Toalla 160x80 Ne | C27: 1 | D27: 2 | E27: HI-01 | F27: =IFERROR(VLOOKUP(E27,Materias_Primas[#All],3,0),"") -> IN | G27: =IFERROR(VLOOKUP('Receta'!$E27,Materias_Primas[#All],2,0),"") -> Hilo Overlock Verde | H27: =1/25 -> 0.04 | I27: =IFERROR(VLOOKUP('Receta'!$E27,Materias_Primas[#All],5,0),"") -> Uni | J27: =IFERROR(H27*VLOOKUP('Receta'!$E27,Materias_Primas[#All],10,0),"") -> 51.96 | K27: =IFERROR('Receta'!$J27/'Receta'!$C27,"") -> 51.96 | L27: =IFERROR(VLOOKUP('Receta'!$A27,Productos[#All],3,0),"") -> Toalla
A28: TO-08 | B28: =IFERROR(VLOOKUP('Receta'!$A28,Productos[#All],2,0),"") -> Toalla 160x80 Ne | C28: 1 | D28: 3 | E28: HI-02 | F28: =IFERROR(VLOOKUP(E28,Materias_Primas[#All],3,0),"") -> IN | G28: =IFERROR(VLOOKUP('Receta'!$E28,Materias_Primas[#All],2,0),"") -> Hilo Recta Verde | H28: 0.04 | I28: =IFERROR(VLOOKUP('Receta'!$E28,Materias_Primas[#All],5,0),"") -> Uni | J28: =IFERROR(H28*VLOOKUP('Receta'!$E28,Materias_Primas[#All],10,0),"") -> 35.6 | K28: =IFERROR('Receta'!$J28/'Receta'!$C28,"") -> 35.6 | L28: =IFERROR(VLOOKUP('Receta'!$A28,Productos[#All],3,0),"") -> Toalla
A29: TO-08 | B29: =IFERROR(VLOOKUP('Receta'!$A29,Productos[#All],2,0),"") -> Toalla 160x80 Ne | C29: 1 | D29: 4 | E29: GA-01 | F29: =IFERROR(VLOOKUP(E29,Materias_Primas[#All],3,0),"") -> 0 | G29: =IFERROR(VLOOKUP('Receta'!$E29,Materias_Primas[#All],2,0),"") -> Locomoción | H29: 0.1 | I29: =IFERROR(VLOOKUP('Receta'!$E29,Materias_Primas[#All],5,0),"") -> Uni | J29: =IFERROR(H29*VLOOKUP('Receta'!$E29,Materias_Primas[#All],10,0),"") -> 100 | K29: =IFERROR('Receta'!$J29/'Receta'!$C29,"") -> 100 | L29: =IFERROR(VLOOKUP('Receta'!$A29,Productos[#All],3,0),"") -> Toalla
A30: TO-09 | B30: =IFERROR(VLOOKUP('Receta'!$A30,Productos[#All],2,0),"") -> Toalla 80x40 Na | C30: 1 | D30: 1 | E30: TE-01 | F30: =IFERROR(VLOOKUP(E30,Materias_Primas[#All],3,0),"") -> MP | G30: =IFERROR(VLOOKUP('Receta'!$E30,Materias_Primas[#All],2,0),"") -> Microfibra Dep 160 Na | H30: 0.2 | I30: =IFERROR(VLOOKUP('Receta'!$E30,Materias_Primas[#All],5,0),"") -> Mts | J30: =IFERROR(H30*VLOOKUP('Receta'!$E30,Materias_Primas[#All],10,0),"") -> 980 | K30: =IFERROR('Receta'!$J30/'Receta'!$C30,"") -> 980 | L30: =IFERROR(VLOOKUP('Receta'!$A30,Productos[#All],3,0),"") -> Toalla
A31: TO-09 | B31: =IFERROR(VLOOKUP('Receta'!$A31,Productos[#All],2,0),"") -> Toalla 80x40 Na | C31: 1 | D31: 2 | E31: HI-01 | F31: =IFERROR(VLOOKUP(E31,Materias_Primas[#All],3,0),"") -> IN | G31: =IFERROR(VLOOKUP('Receta'!$E31,Materias_Primas[#All],2,0),"") -> Hilo Overlock Verde | H31: =1/100 -> 0.01 | I31: =IFERROR(VLOOKUP('Receta'!$E31,Materias_Primas[#All],5,0),"") -> Uni | J31: =IFERROR(H31*VLOOKUP('Receta'!$E31,Materias_Primas[#All],10,0),"") -> 12.99 | K31: =IFERROR('Receta'!$J31/'Receta'!$C31,"") -> 12.99 | L31: =IFERROR(VLOOKUP('Receta'!$A31,Productos[#All],3,0),"") -> Toalla
A32: TO-09 | B32: =IFERROR(VLOOKUP('Receta'!$A32,Productos[#All],2,0),"") -> Toalla 80x40 Na | C32: 1 | D32: 3 | E32: HI-02 | F32: =IFERROR(VLOOKUP(E32,Materias_Primas[#All],3,0),"") -> IN | G32: =IFERROR(VLOOKUP('Receta'!$E32,Materias_Primas[#All],2,0),"") -> Hilo Recta Verde | H32: 0.01 | I32: =IFERROR(VLOOKUP('Receta'!$E32,Materias_Primas[#All],5,0),"") -> Uni | J32: =IFERROR(H32*VLOOKUP('Receta'!$E32,Materias_Primas[#All],10,0),"") -> 8.9 | K32: =IFERROR('Receta'!$J32/'Receta'!$C32,"") -> 8.9 | L32: =IFERROR(VLOOKUP('Receta'!$A32,Productos[#All],3,0),"") -> Toalla
A33: TO-09 | B33: =IFERROR(VLOOKUP('Receta'!$A33,Productos[#All],2,0),"") -> Toalla 80x40 Na | C33: 1 | D33: 4 | E33: GA-01 | F33: =IFERROR(VLOOKUP(E33,Materias_Primas[#All],3,0),"") -> 0 | G33: =IFERROR(VLOOKUP('Receta'!$E33,Materias_Primas[#All],2,0),"") -> Locomoción | H33: 0.25 | I33: =IFERROR(VLOOKUP('Receta'!$E33,Materias_Primas[#All],5,0),"") -> Uni | J33: =IFERROR(H33*VLOOKUP('Receta'!$E33,Materias_Primas[#All],10,0),"") -> 250 | K33: =IFERROR('Receta'!$J33/'Receta'!$C33,"") -> 250 | L33: =IFERROR(VLOOKUP('Receta'!$A33,Productos[#All],3,0),"") -> Toalla
A34: TO-10 | B34: =IFERROR(VLOOKUP('Receta'!$A34,Productos[#All],2,0),"") -> Toalla 40x40 Na | C34: 1 | D34: 1 | E34: TE-01 | F34: =IFERROR(VLOOKUP(E34,Materias_Primas[#All],3,0),"") -> MP | G34: =IFERROR(VLOOKUP('Receta'!$E34,Materias_Primas[#All],2,0),"") -> Microfibra Dep 160 Na | H34: 0.1 | I34: =IFERROR(VLOOKUP('Receta'!$E34,Materias_Primas[#All],5,0),"") -> Mts | J34: =IFERROR(H34*VLOOKUP('Receta'!$E34,Materias_Primas[#All],10,0),"") -> 490 | K34: =IFERROR('Receta'!$J34/'Receta'!$C34,"") -> 490 | L34: =IFERROR(VLOOKUP('Receta'!$A34,Productos[#All],3,0),"") -> Toalla
A35: TO-10 | B35: =IFERROR(VLOOKUP('Receta'!$A35,Productos[#All],2,0),"") -> Toalla 40x40 Na | C35: 1 | D35: 2 | E35: HI-01 | F35: =IFERROR(VLOOKUP(E35,Materias_Primas[#All],3,0),"") -> IN | G35: =IFERROR(VLOOKUP('Receta'!$E35,Materias_Primas[#All],2,0),"") -> Hilo Overlock Verde | H35: 0.005 | I35: =IFERROR(VLOOKUP('Receta'!$E35,Materias_Primas[#All],5,0),"") -> Uni | J35: =IFERROR(H35*VLOOKUP('Receta'!$E35,Materias_Primas[#All],10,0),"") -> 6.495 | K35: =IFERROR('Receta'!$J35/'Receta'!$C35,"") -> 6.495 | L35: =IFERROR(VLOOKUP('Receta'!$A35,Productos[#All],3,0),"") -> Toalla
A36: TO-10 | B36: =IFERROR(VLOOKUP('Receta'!$A36,Productos[#All],2,0),"") -> Toalla 40x40 Na | C36: 1 | D36: 3 | E36: HI-02 | F36: =IFERROR(VLOOKUP(E36,Materias_Primas[#All],3,0),"") -> IN | G36: =IFERROR(VLOOKUP('Receta'!$E36,Materias_Primas[#All],2,0),"") -> Hilo Recta Verde | H36: 0.005 | I36: =IFERROR(VLOOKUP('Receta'!$E36,Materias_Primas[#All],5,0),"") -> Uni | J36: =IFERROR(H36*VLOOKUP('Receta'!$E36,Materias_Primas[#All],10,0),"") -> 4.45 | K36: =IFERROR('Receta'!$J36/'Receta'!$C36,"") -> 4.45 | L36: =IFERROR(VLOOKUP('Receta'!$A36,Productos[#All],3,0),"") -> Toalla
A37: TO-10 | B37: =IFERROR(VLOOKUP('Receta'!$A37,Productos[#All],2,0),"") -> Toalla 40x40 Na | C37: 1 | D37: 4 | E37: GA-01 | F37: =IFERROR(VLOOKUP(E37,Materias_Primas[#All],3,0),"") -> 0 | G37: =IFERROR(VLOOKUP('Receta'!$E37,Materias_Primas[#All],2,0),"") -> Locomoción | H37: 0.12 | I37: =IFERROR(VLOOKUP('Receta'!$E37,Materias_Primas[#All],5,0),"") -> Uni | J37: =IFERROR(H37*VLOOKUP('Receta'!$E37,Materias_Primas[#All],10,0),"") -> 120 | K37: =IFERROR('Receta'!$J37/'Receta'!$C37,"") -> 120 | L37: =IFERROR(VLOOKUP('Receta'!$A37,Productos[#All],3,0),"") -> Toalla
A38: TO-11 | B38: =IFERROR(VLOOKUP('Receta'!$A38,Productos[#All],2,0),"") -> Toalla 160x110 Na | C38: 1 | D38: 1 | E38: TE-01 | F38: =IFERROR(VLOOKUP(E38,Materias_Primas[#All],3,0),"") -> MP | G38: =IFERROR(VLOOKUP('Receta'!$E38,Materias_Primas[#All],2,0),"") -> Microfibra Dep 160 Na | H38: =0.8*1.5 -> 1.2 | I38: =IFERROR(VLOOKUP('Receta'!$E38,Materias_Primas[#All],5,0),"") -> Mts | J38: =IFERROR(H38*VLOOKUP('Receta'!$E38,Materias_Primas[#All],10,0),"") -> 5880 | K38: =IFERROR('Receta'!$J38/'Receta'!$C38,"") -> 5880 | L38: =IFERROR(VLOOKUP('Receta'!$A38,Productos[#All],3,0),"") -> Toalla
A39: TO-11 | B39: =IFERROR(VLOOKUP('Receta'!$A39,Productos[#All],2,0),"") -> Toalla 160x110 Na | C39: 1 | D39: 2 | E39: HI-01 | F39: =IFERROR(VLOOKUP(E39,Materias_Primas[#All],3,0),"") -> IN | G39: =IFERROR(VLOOKUP('Receta'!$E39,Materias_Primas[#All],2,0),"") -> Hilo Overlock Verde | H39: =1.5/25 -> 0.06 | I39: =IFERROR(VLOOKUP('Receta'!$E39,Materias_Primas[#All],5,0),"") -> Uni | J39: =IFERROR(H39*VLOOKUP('Receta'!$E39,Materias_Primas[#All],10,0),"") -> 77.94 | K39: =IFERROR('Receta'!$J39/'Receta'!$C39,"") -> 77.94 | L39: =IFERROR(VLOOKUP('Receta'!$A39,Productos[#All],3,0),"") -> Toalla
A40: TO-11 | B40: =IFERROR(VLOOKUP('Receta'!$A40,Productos[#All],2,0),"") -> Toalla 160x110 Na | C40: 1 | D40: 3 | E40: HI-02 | F40: =IFERROR(VLOOKUP(E40,Materias_Primas[#All],3,0),"") -> IN | G40: =IFERROR(VLOOKUP('Receta'!$E40,Materias_Primas[#All],2,0),"") -> Hilo Recta Verde | H40: 0.06 | I40: =IFERROR(VLOOKUP('Receta'!$E40,Materias_Primas[#All],5,0),"") -> Uni | J40: =IFERROR(H40*VLOOKUP('Receta'!$E40,Materias_Primas[#All],10,0),"") -> 53.4 | K40: =IFERROR('Receta'!$J40/'Receta'!$C40,"") -> 53.4 | L40: =IFERROR(VLOOKUP('Receta'!$A40,Productos[#All],3,0),"") -> Toalla
A41: TO-11 | B41: =IFERROR(VLOOKUP('Receta'!$A41,Productos[#All],2,0),"") -> Toalla 160x110 Na | C41: 1 | D41: 4 | E41: GA-01 | F41: =IFERROR(VLOOKUP(E41,Materias_Primas[#All],3,0),"") -> 0 | G41: =IFERROR(VLOOKUP('Receta'!$E41,Materias_Primas[#All],2,0),"") -> Locomoción | H41: 0.15 | I41: =IFERROR(VLOOKUP('Receta'!$E41,Materias_Primas[#All],5,0),"") -> Uni | J41: =IFERROR(H41*VLOOKUP('Receta'!$E41,Materias_Primas[#All],10,0),"") -> 150 | K41: =IFERROR('Receta'!$J41/'Receta'!$C41,"") -> 150 | L41: =IFERROR(VLOOKUP('Receta'!$A41,Productos[#All],3,0),"") -> Toalla
A42: TO-12 | B42: =IFERROR(VLOOKUP('Receta'!$A42,Productos[#All],2,0),"") -> Toalla 160x110 Li | C42: 1 | D42: 1 | E42: TE-02 | F42: =IFERROR(VLOOKUP(E42,Materias_Primas[#All],3,0),"") -> MP | G42: =IFERROR(VLOOKUP('Receta'!$E42,Materias_Primas[#All],2,0),"") -> Microfibra Dep 160 Li | H42: =0.8*1.5 -> 1.2 | I42: =IFERROR(VLOOKUP('Receta'!$E42,Materias_Primas[#All],5,0),"") -> Mts | J42: =IFERROR(H42*VLOOKUP('Receta'!$E42,Materias_Primas[#All],10,0),"") -> 5880 | K42: =IFERROR('Receta'!$J42/'Receta'!$C42,"") -> 5880 | L42: =IFERROR(VLOOKUP('Receta'!$A42,Productos[#All],3,0),"") -> Toalla
A43: TO-12 | B43: =IFERROR(VLOOKUP('Receta'!$A43,Productos[#All],2,0),"") -> Toalla 160x110 Li | C43: 1 | D43: 2 | E43: HI-01 | F43: =IFERROR(VLOOKUP(E43,Materias_Primas[#All],3,0),"") -> IN | G43: =IFERROR(VLOOKUP('Receta'!$E43,Materias_Primas[#All],2,0),"") -> Hilo Overlock Verde | H43: =1.5/25 -> 0.06 | I43: =IFERROR(VLOOKUP('Receta'!$E43,Materias_Primas[#All],5,0),"") -> Uni | J43: =IFERROR(H43*VLOOKUP('Receta'!$E43,Materias_Primas[#All],10,0),"") -> 77.94 | K43: =IFERROR('Receta'!$J43/'Receta'!$C43,"") -> 77.94 | L43: =IFERROR(VLOOKUP('Receta'!$A43,Productos[#All],3,0),"") -> Toalla
A44: TO-12 | B44: =IFERROR(VLOOKUP('Receta'!$A44,Productos[#All],2,0),"") -> Toalla 160x110 Li | C44: 1 | D44: 3 | E44: HI-02 | F44: =IFERROR(VLOOKUP(E44,Materias_Primas[#All],3,0),"") -> IN | G44: =IFERROR(VLOOKUP('Receta'!$E44,Materias_Primas[#All],2,0),"") -> Hilo Recta Verde | H44: 0.06 | I44: =IFERROR(VLOOKUP('Receta'!$E44,Materias_Primas[#All],5,0),"") -> Uni | J44: =IFERROR(H44*VLOOKUP('Receta'!$E44,Materias_Primas[#All],10,0),"") -> 53.4 | K44: =IFERROR('Receta'!$J44/'Receta'!$C44,"") -> 53.4 | L44: =IFERROR(VLOOKUP('Receta'!$A44,Productos[#All],3,0),"") -> Toalla
A45: TO-12 | B45: =IFERROR(VLOOKUP('Receta'!$A45,Productos[#All],2,0),"") -> Toalla 160x110 Li | C45: 1 | D45: 4 | E45: GA-01 | F45: =IFERROR(VLOOKUP(E45,Materias_Primas[#All],3,0),"") -> 0 | G45: =IFERROR(VLOOKUP('Receta'!$E45,Materias_Primas[#All],2,0),"") -> Locomoción | H45: 0.15 | I45: =IFERROR(VLOOKUP('Receta'!$E45,Materias_Primas[#All],5,0),"") -> Uni | J45: =IFERROR(H45*VLOOKUP('Receta'!$E45,Materias_Primas[#All],10,0),"") -> 150 | K45: =IFERROR('Receta'!$J45/'Receta'!$C45,"") -> 150 | L45: =IFERROR(VLOOKUP('Receta'!$A45,Productos[#All],3,0),"") -> Toalla
A46: TU-01 | B46: =IFERROR(VLOOKUP('Receta'!$A46,Productos[#All],2,0),"") -> Turbante Ca | C46: 8 | D46: 1 | E46: TE-04 | F46: =IFERROR(VLOOKUP(E46,Materias_Primas[#All],3,0),"") -> MP | G46: =IFERROR(VLOOKUP('Receta'!$E46,Materias_Primas[#All],2,0),"") -> Microfibra Dep 160 Ca | H46: 0.13 | I46: =IFERROR(VLOOKUP('Receta'!$E46,Materias_Primas[#All],5,0),"") -> Mts | J46: =IFERROR(H46*VLOOKUP('Receta'!$E46,Materias_Primas[#All],10,0),"") -> 637 | K46: =IFERROR('Receta'!$J46/'Receta'!$C46,"") -> 79.625 | L46: =IFERROR(VLOOKUP('Receta'!$A46,Productos[#All],3,0),"") -> Turbante
A47: TU-01 | B47: =IFERROR(VLOOKUP('Receta'!$A47,Productos[#All],2,0),"") -> Turbante Ca | C47: 100 | D47: 2 | E47: HI-01 | F47: =IFERROR(VLOOKUP(E47,Materias_Primas[#All],3,0),"") -> IN | G47: =IFERROR(VLOOKUP('Receta'!$E47,Materias_Primas[#All],2,0),"") -> Hilo Overlock Verde | H47: 2 | I47: =IFERROR(VLOOKUP('Receta'!$E47,Materias_Primas[#All],5,0),"") -> Uni | J47: =IFERROR(H47*VLOOKUP('Receta'!$E47,Materias_Primas[#All],10,0),"") -> 2598 | K47: =IFERROR('Receta'!$J47/'Receta'!$C47,"") -> 25.98 | L47: =IFERROR(VLOOKUP('Receta'!$A47,Productos[#All],3,0),"") -> Turbante
A48: TU-01 | B48: =IFERROR(VLOOKUP('Receta'!$A48,Productos[#All],2,0),"") -> Turbante Ca | C48: 100 | D48: 3 | E48: HI-03 | F48: =IFERROR(VLOOKUP(E48,Materias_Primas[#All],3,0),"") -> MP | G48: =IFERROR(VLOOKUP('Receta'!$E48,Materias_Primas[#All],2,0),"") -> Hilo Poliester | H48: 3 | I48: =IFERROR(VLOOKUP('Receta'!$E48,Materias_Primas[#All],5,0),"") -> Uni | J48: =IFERROR(H48*VLOOKUP('Receta'!$E48,Materias_Primas[#All],10,0),"") -> 2670 | K48: =IFERROR('Receta'!$J48/'Receta'!$C48,"") -> 26.7 | L48: =IFERROR(VLOOKUP('Receta'!$A48,Productos[#All],3,0),"") -> Turbante
A49: TU-01 | B49: =IFERROR(VLOOKUP('Receta'!$A49,Productos[#All],2,0),"") -> Turbante Ca | C49: 1 | D49: 4 | E49: GA-01 | F49: =IFERROR(VLOOKUP(E49,Materias_Primas[#All],3,0),"") -> 0 | G49: =IFERROR(VLOOKUP('Receta'!$E49,Materias_Primas[#All],2,0),"") -> Locomoción | H49: 0.02 | I49: =IFERROR(VLOOKUP('Receta'!$E49,Materias_Primas[#All],5,0),"") -> Uni | J49: =IFERROR(H49*VLOOKUP('Receta'!$E49,Materias_Primas[#All],10,0),"") -> 20 | K49: =IFERROR('Receta'!$J49/'Receta'!$C49,"") -> 20 | L49: =IFERROR(VLOOKUP('Receta'!$A49,Productos[#All],3,0),"") -> Turbante
A50: TU-01 | B50: =IFERROR(VLOOKUP('Receta'!$A50,Productos[#All],2,0),"") -> Turbante Ca | C50: 1 | D50: 5 | E50: MO-01 | F50: =IFERROR(VLOOKUP(E50,Materias_Primas[#All],3,0),"") -> MO | G50: =IFERROR(VLOOKUP('Receta'!$E50,Materias_Primas[#All],2,0),"") -> Corte | H50: 2 | I50: =IFERROR(VLOOKUP('Receta'!$E50,Materias_Primas[#All],5,0),"") -> Min | J50: =IFERROR(H50*VLOOKUP('Receta'!$E50,Materias_Primas[#All],10,0),"") -> 130 | K50: =IFERROR('Receta'!$J50/'Receta'!$C50,"") -> 130 | L50: =IFERROR(VLOOKUP('Receta'!$A86,Productos[#All],3,0),"") -> Turbante
A51: TU-01 | B51: =IFERROR(VLOOKUP('Receta'!$A51,Productos[#All],2,0),"") -> Turbante Ca | C51: 1 | D51: 6 | E51: MO-02 | F51: =IFERROR(VLOOKUP(E51,Materias_Primas[#All],3,0),"") -> MO | G51: =IFERROR(VLOOKUP('Receta'!$E51,Materias_Primas[#All],2,0),"") -> Confección | H51: 8 | I51: =IFERROR(VLOOKUP('Receta'!$E51,Materias_Primas[#All],5,0),"") -> Min | J51: =IFERROR(H51*VLOOKUP('Receta'!$E51,Materias_Primas[#All],10,0),"") -> 520 | K51: =IFERROR('Receta'!$J51/'Receta'!$C51,"") -> 520 | L51: =IFERROR(VLOOKUP('Receta'!$A87,Productos[#All],3,0),"") -> Turbante
A52: TU-01 | B52: =IFERROR(VLOOKUP('Receta'!$A52,Productos[#All],2,0),"") -> Turbante Ca | C52: 1 | D52: 7 | E52: MO-03 | F52: =IFERROR(VLOOKUP(E52,Materias_Primas[#All],3,0),"") -> MO | G52: =IFERROR(VLOOKUP('Receta'!$E52,Materias_Primas[#All],2,0),"") -> Botones | H52: 3 | I52: =IFERROR(VLOOKUP('Receta'!$E52,Materias_Primas[#All],5,0),"") -> Min | J52: =IFERROR(H52*VLOOKUP('Receta'!$E52,Materias_Primas[#All],10,0),"") -> 33 | K52: =IFERROR('Receta'!$J52/'Receta'!$C52,"") -> 33 | L52: =IFERROR(VLOOKUP('Receta'!$A88,Productos[#All],3,0),"") -> Turbante
A53: TU-01 | B53: =IFERROR(VLOOKUP('Receta'!$A53,Productos[#All],2,0),"") -> Turbante Ca | C53: 1 | D53: 8 | E53: MO-04 | F53: =IFERROR(VLOOKUP(E53,Materias_Primas[#All],3,0),"") -> MO | G53: =IFERROR(VLOOKUP('Receta'!$E53,Materias_Primas[#All],2,0),"") -> Preparación | H53: 0.5 | I53: =IFERROR(VLOOKUP('Receta'!$E53,Materias_Primas[#All],5,0),"") -> Min | J53: =IFERROR(H53*VLOOKUP('Receta'!$E53,Materias_Primas[#All],10,0),"") -> 32.5 | K53: =IFERROR('Receta'!$J53/'Receta'!$C53,"") -> 32.5 | L53: =IFERROR(VLOOKUP('Receta'!$A89,Productos[#All],3,0),"") -> Turbante
A54: TU-03 | B54: =IFERROR(VLOOKUP('Receta'!$A54,Productos[#All],2,0),"") -> Turbante Vp | C54: 8 | D54: 1 | E54: TE-08 | F54: =IFERROR(VLOOKUP(E54,Materias_Primas[#All],3,0),"") -> MP | G54: =IFERROR(VLOOKUP('Receta'!$E54,Materias_Primas[#All],2,0),"") -> Microfibra Dep 160 Vp | H54: 0.13 | I54: =IFERROR(VLOOKUP('Receta'!$E54,Materias_Primas[#All],5,0),"") -> Mts | J54: =IFERROR(H54*VLOOKUP('Receta'!$E54,Materias_Primas[#All],10,0),"") -> 637 | K54: =IFERROR('Receta'!$J54/'Receta'!$C54,"") -> 79.625 | L54: =IFERROR(VLOOKUP('Receta'!$A54,Productos[#All],3,0),"") -> Turbante
A55: TU-03 | B55: =IFERROR(VLOOKUP('Receta'!$A55,Productos[#All],2,0),"") -> Turbante Vp | C55: 100 | D55: 2 | E55: HI-01 | F55: =IFERROR(VLOOKUP(E55,Materias_Primas[#All],3,0),"") -> IN | G55: =IFERROR(VLOOKUP('Receta'!$E55,Materias_Primas[#All],2,0),"") -> Hilo Overlock Verde | H55: 2 | I55: =IFERROR(VLOOKUP('Receta'!$E55,Materias_Primas[#All],5,0),"") -> Uni | J55: =IFERROR(H55*VLOOKUP('Receta'!$E55,Materias_Primas[#All],10,0),"") -> 2598 | K55: =IFERROR('Receta'!$J55/'Receta'!$C55,"") -> 25.98 | L55: =IFERROR(VLOOKUP('Receta'!$A55,Productos[#All],3,0),"") -> Turbante
A56: TU-03 | B56: =IFERROR(VLOOKUP('Receta'!$A56,Productos[#All],2,0),"") -> Turbante Vp | C56: 1 | D56: 3 | E56: HI-02 | F56: =IFERROR(VLOOKUP(E56,Materias_Primas[#All],3,0),"") -> IN | G56: =IFERROR(VLOOKUP('Receta'!$E56,Materias_Primas[#All],2,0),"") -> Hilo Recta Verde | H56: 0.008125 | I56: =IFERROR(VLOOKUP('Receta'!$E56,Materias_Primas[#All],5,0),"") -> Uni | J56: =IFERROR(H56*VLOOKUP('Receta'!$E56,Materias_Primas[#All],10,0),"") -> 7.23125 | K56: =IFERROR('Receta'!$J56/'Receta'!$C56,"") -> 7.23125 | L56: =IFERROR(VLOOKUP('Receta'!$A56,Productos[#All],3,0),"") -> Turbante
A57: TU-03 | B57: =IFERROR(VLOOKUP('Receta'!$A57,Productos[#All],2,0),"") -> Turbante Vp | C57: 1 | D57: 4 | E57: GA-01 | F57: =IFERROR(VLOOKUP(E57,Materias_Primas[#All],3,0),"") -> 0 | G57: =IFERROR(VLOOKUP('Receta'!$E57,Materias_Primas[#All],2,0),"") -> Locomoción | H57: 0.02 | I57: =IFERROR(VLOOKUP('Receta'!$E57,Materias_Primas[#All],5,0),"") -> Uni | J57: =IFERROR(H57*VLOOKUP('Receta'!$E57,Materias_Primas[#All],10,0),"") -> 20 | K57: =IFERROR('Receta'!$J57/'Receta'!$C57,"") -> 20 | L57: =IFERROR(VLOOKUP('Receta'!$A57,Productos[#All],3,0),"") -> Turbante
A58: TU-04 | B58: =IFERROR(VLOOKUP('Receta'!$A58,Productos[#All],2,0),"") -> Turbante Li | C58: 8 | D58: 1 | E58: TE-02 | F58: =IFERROR(VLOOKUP(E58,Materias_Primas[#All],3,0),"") -> MP | G58: =IFERROR(VLOOKUP('Receta'!$E58,Materias_Primas[#All],2,0),"") -> Microfibra Dep 160 Li | H58: 0.13 | I58: =IFERROR(VLOOKUP('Receta'!$E58,Materias_Primas[#All],5,0),"") -> Mts | J58: =IFERROR(H58*VLOOKUP('Receta'!$E58,Materias_Primas[#All],10,0),"") -> 637 | K58: =IFERROR('Receta'!$J58/'Receta'!$C58,"") -> 79.625 | L58: =IFERROR(VLOOKUP('Receta'!$A58,Productos[#All],3,0),"") -> Turbante
A59: TU-04 | B59: =IFERROR(VLOOKUP('Receta'!$A59,Productos[#All],2,0),"") -> Turbante Li | C59: 100 | D59: 2 | E59: HI-01 | F59: =IFERROR(VLOOKUP(E59,Materias_Primas[#All],3,0),"") -> IN | G59: =IFERROR(VLOOKUP('Receta'!$E59,Materias_Primas[#All],2,0),"") -> Hilo Overlock Verde | H59: 2 | I59: =IFERROR(VLOOKUP('Receta'!$E59,Materias_Primas[#All],5,0),"") -> Uni | J59: =IFERROR(H59*VLOOKUP('Receta'!$E59,Materias_Primas[#All],10,0),"") -> 2598 | K59: =IFERROR('Receta'!$J59/'Receta'!$C59,"") -> 25.98 | L59: =IFERROR(VLOOKUP('Receta'!$A59,Productos[#All],3,0),"") -> Turbante
A60: TU-04 | B60: =IFERROR(VLOOKUP('Receta'!$A60,Productos[#All],2,0),"") -> Turbante Li | C60: 1 | D60: 3 | E60: HI-02 | F60: =IFERROR(VLOOKUP(E60,Materias_Primas[#All],3,0),"") -> IN | G60: =IFERROR(VLOOKUP('Receta'!$E60,Materias_Primas[#All],2,0),"") -> Hilo Recta Verde | H60: 0.008125 | I60: =IFERROR(VLOOKUP('Receta'!$E60,Materias_Primas[#All],5,0),"") -> Uni | J60: =IFERROR(H60*VLOOKUP('Receta'!$E60,Materias_Primas[#All],10,0),"") -> 7.23125 | K60: =IFERROR('Receta'!$J60/'Receta'!$C60,"") -> 7.23125 | L60: =IFERROR(VLOOKUP('Receta'!$A60,Productos[#All],3,0),"") -> Turbante
A61: TU-04 | B61: =IFERROR(VLOOKUP('Receta'!$A61,Productos[#All],2,0),"") -> Turbante Li | C61: 1 | D61: 4 | E61: GA-01 | F61: =IFERROR(VLOOKUP(E61,Materias_Primas[#All],3,0),"") -> 0 | G61: =IFERROR(VLOOKUP('Receta'!$E61,Materias_Primas[#All],2,0),"") -> Locomoción | H61: 0.02 | I61: =IFERROR(VLOOKUP('Receta'!$E61,Materias_Primas[#All],5,0),"") -> Uni | J61: =IFERROR(H61*VLOOKUP('Receta'!$E61,Materias_Primas[#All],10,0),"") -> 20 | K61: =IFERROR('Receta'!$J61/'Receta'!$C61,"") -> 20 | L61: =IFERROR(VLOOKUP('Receta'!$A61,Productos[#All],3,0),"") -> Turbante
A62: TO-03 | B62: =IFERROR(VLOOKUP('Receta'!$A62,Productos[#All],2,0),"") -> Toalla 160x80 Am | C62: 1 | D62: 1 | E62: TE-06 | F62: =IFERROR(VLOOKUP(E62,Materias_Primas[#All],3,0),"") -> MP | G62: =IFERROR(VLOOKUP('Receta'!$E62,Materias_Primas[#All],2,0),"") -> Microfibra Dep 160 Am | H62: 0.8 | I62: =IFERROR(VLOOKUP('Receta'!$E62,Materias_Primas[#All],5,0),"") -> Mts | J62: =IFERROR(H62*VLOOKUP('Receta'!$E62,Materias_Primas[#All],10,0),"") -> 3920 | K62: =IFERROR('Receta'!$J62/'Receta'!$C62,"") -> 3920 | L62: =IFERROR(VLOOKUP('Receta'!$A62,Productos[#All],3,0),"") -> Toalla
A63: TO-03 | B63: =IFERROR(VLOOKUP('Receta'!$A63,Productos[#All],2,0),"") -> Toalla 160x80 Am | C63: 1 | D63: 2 | E63: HI-01 | F63: =IFERROR(VLOOKUP(E63,Materias_Primas[#All],3,0),"") -> IN | G63: =IFERROR(VLOOKUP('Receta'!$E63,Materias_Primas[#All],2,0),"") -> Hilo Overlock Verde | H63: =1/25 -> 0.04 | I63: =IFERROR(VLOOKUP('Receta'!$E63,Materias_Primas[#All],5,0),"") -> Uni | J63: =IFERROR(H63*VLOOKUP('Receta'!$E63,Materias_Primas[#All],10,0),"") -> 51.96 | K63: =IFERROR('Receta'!$J63/'Receta'!$C63,"") -> 51.96 | L63: =IFERROR(VLOOKUP('Receta'!$A63,Productos[#All],3,0),"") -> Toalla
A64: TO-03 | B64: =IFERROR(VLOOKUP('Receta'!$A64,Productos[#All],2,0),"") -> Toalla 160x80 Am | C64: 1 | D64: 3 | E64: HI-02 | F64: =IFERROR(VLOOKUP(E64,Materias_Primas[#All],3,0),"") -> IN | G64: =IFERROR(VLOOKUP('Receta'!$E64,Materias_Primas[#All],2,0),"") -> Hilo Recta Verde | H64: 0.04 | I64: =IFERROR(VLOOKUP('Receta'!$E64,Materias_Primas[#All],5,0),"") -> Uni | J64: =IFERROR(H64*VLOOKUP('Receta'!$E64,Materias_Primas[#All],10,0),"") -> 35.6 | K64: =IFERROR('Receta'!$J64/'Receta'!$C64,"") -> 35.6 | L64: =IFERROR(VLOOKUP('Receta'!$A64,Productos[#All],3,0),"") -> Toalla
A65: TO-03 | B65: =IFERROR(VLOOKUP('Receta'!$A65,Productos[#All],2,0),"") -> Toalla 160x80 Am | C65: 1 | D65: 4 | E65: GA-01 | F65: =IFERROR(VLOOKUP(E65,Materias_Primas[#All],3,0),"") -> 0 | G65: =IFERROR(VLOOKUP('Receta'!$E65,Materias_Primas[#All],2,0),"") -> Locomoción | H65: 0.1 | I65: =IFERROR(VLOOKUP('Receta'!$E65,Materias_Primas[#All],5,0),"") -> Uni | J65: =IFERROR(H65*VLOOKUP('Receta'!$E65,Materias_Primas[#All],10,0),"") -> 100 | K65: =IFERROR('Receta'!$J65/'Receta'!$C65,"") -> 100 | L65: =IFERROR(VLOOKUP('Receta'!$A65,Productos[#All],3,0),"") -> Toalla
A66: TU-05 | B66: =IFERROR(VLOOKUP('Receta'!$A66,Productos[#All],2,0),"") -> Turbante Ne | C66: 8 | D66: 1 | E66: TE-05 | F66: =IFERROR(VLOOKUP(E66,Materias_Primas[#All],3,0),"") -> MP | G66: =IFERROR(VLOOKUP('Receta'!$E66,Materias_Primas[#All],2,0),"") -> Microfibra Dep 160 Ne | H66: 0.13 | I66: =IFERROR(VLOOKUP('Receta'!$E66,Materias_Primas[#All],5,0),"") -> Mts | J66: =IFERROR(H66*VLOOKUP('Receta'!$E66,Materias_Primas[#All],10,0),"") -> 637 | K66: =IFERROR('Receta'!$J66/'Receta'!$C66,"") -> 79.625 | L66: =IFERROR(VLOOKUP('Receta'!$A66,Productos[#All],3,0),"") -> Turbante
A67: TU-05 | B67: =IFERROR(VLOOKUP('Receta'!$A67,Productos[#All],2,0),"") -> Turbante Ne | C67: 100 | D67: 2 | E67: HI-01 | F67: =IFERROR(VLOOKUP(E67,Materias_Primas[#All],3,0),"") -> IN | G67: =IFERROR(VLOOKUP('Receta'!$E67,Materias_Primas[#All],2,0),"") -> Hilo Overlock Verde | H67: 2 | I67: =IFERROR(VLOOKUP('Receta'!$E67,Materias_Primas[#All],5,0),"") -> Uni | J67: =IFERROR(H67*VLOOKUP('Receta'!$E67,Materias_Primas[#All],10,0),"") -> 2598 | K67: =IFERROR('Receta'!$J67/'Receta'!$C67,"") -> 25.98 | L67: =IFERROR(VLOOKUP('Receta'!$A67,Productos[#All],3,0),"") -> Turbante
A68: TU-05 | B68: =IFERROR(VLOOKUP('Receta'!$A68,Productos[#All],2,0),"") -> Turbante Ne | C68: 1 | D68: 3 | E68: HI-02 | F68: =IFERROR(VLOOKUP(E68,Materias_Primas[#All],3,0),"") -> IN | G68: =IFERROR(VLOOKUP('Receta'!$E68,Materias_Primas[#All],2,0),"") -> Hilo Recta Verde | H68: 0.008125 | I68: =IFERROR(VLOOKUP('Receta'!$E68,Materias_Primas[#All],5,0),"") -> Uni | J68: =IFERROR(H68*VLOOKUP('Receta'!$E68,Materias_Primas[#All],10,0),"") -> 7.23125 | K68: =IFERROR('Receta'!$J68/'Receta'!$C68,"") -> 7.23125 | L68: =IFERROR(VLOOKUP('Receta'!$A68,Productos[#All],3,0),"") -> Turbante
A69: TU-05 | B69: =IFERROR(VLOOKUP('Receta'!$A69,Productos[#All],2,0),"") -> Turbante Ne | C69: 1 | D69: 4 | E69: GA-01 | F69: =IFERROR(VLOOKUP(E69,Materias_Primas[#All],3,0),"") -> 0 | G69: =IFERROR(VLOOKUP('Receta'!$E69,Materias_Primas[#All],2,0),"") -> Locomoción | H69: 0.02 | I69: =IFERROR(VLOOKUP('Receta'!$E69,Materias_Primas[#All],5,0),"") -> Uni | J69: =IFERROR(H69*VLOOKUP('Receta'!$E69,Materias_Primas[#All],10,0),"") -> 20 | K69: =IFERROR('Receta'!$J69/'Receta'!$C69,"") -> 20 | L69: =IFERROR(VLOOKUP('Receta'!$A69,Productos[#All],3,0),"") -> Turbante
A70: TU-06 | B70: =IFERROR(VLOOKUP('Receta'!$A70,Productos[#All],2,0),"") -> Turbante Na | C70: 8 | D70: 1 | E70: TE-01 | F70: =IFERROR(VLOOKUP(E70,Materias_Primas[#All],3,0),"") -> MP | G70: =IFERROR(VLOOKUP('Receta'!$E70,Materias_Primas[#All],2,0),"") -> Microfibra Dep 160 Na | H70: 0.13 | I70: =IFERROR(VLOOKUP('Receta'!$E70,Materias_Primas[#All],5,0),"") -> Mts | J70: =IFERROR(H70*VLOOKUP('Receta'!$E70,Materias_Primas[#All],10,0),"") -> 637 | K70: =IFERROR('Receta'!$J70/'Receta'!$C70,"") -> 79.625 | L70: =IFERROR(VLOOKUP('Receta'!$A70,Productos[#All],3,0),"") -> Turbante
A71: TU-06 | B71: =IFERROR(VLOOKUP('Receta'!$A71,Productos[#All],2,0),"") -> Turbante Na | C71: 100 | D71: 2 | E71: HI-01 | F71: =IFERROR(VLOOKUP(E71,Materias_Primas[#All],3,0),"") -> IN | G71: =IFERROR(VLOOKUP('Receta'!$E71,Materias_Primas[#All],2,0),"") -> Hilo Overlock Verde | H71: 2 | I71: =IFERROR(VLOOKUP('Receta'!$E71,Materias_Primas[#All],5,0),"") -> Uni | J71: =IFERROR(H71*VLOOKUP('Receta'!$E71,Materias_Primas[#All],10,0),"") -> 2598 | K71: =IFERROR('Receta'!$J71/'Receta'!$C71,"") -> 25.98 | L71: =IFERROR(VLOOKUP('Receta'!$A71,Productos[#All],3,0),"") -> Turbante
A72: TU-06 | B72: =IFERROR(VLOOKUP('Receta'!$A72,Productos[#All],2,0),"") -> Turbante Na | C72: 1 | D72: 3 | E72: HI-02 | F72: =IFERROR(VLOOKUP(E72,Materias_Primas[#All],3,0),"") -> IN | G72: =IFERROR(VLOOKUP('Receta'!$E72,Materias_Primas[#All],2,0),"") -> Hilo Recta Verde | H72: 0.008125 | I72: =IFERROR(VLOOKUP('Receta'!$E72,Materias_Primas[#All],5,0),"") -> Uni | J72: =IFERROR(H72*VLOOKUP('Receta'!$E72,Materias_Primas[#All],10,0),"") -> 7.23125 | K72: =IFERROR('Receta'!$J72/'Receta'!$C72,"") -> 7.23125 | L72: =IFERROR(VLOOKUP('Receta'!$A72,Productos[#All],3,0),"") -> Turbante
A73: TU-06 | B73: =IFERROR(VLOOKUP('Receta'!$A73,Productos[#All],2,0),"") -> Turbante Na | C73: 1 | D73: 4 | E73: GA-01 | F73: =IFERROR(VLOOKUP(E73,Materias_Primas[#All],3,0),"") -> 0 | G73: =IFERROR(VLOOKUP('Receta'!$E73,Materias_Primas[#All],2,0),"") -> Locomoción | H73: 0.02 | I73: =IFERROR(VLOOKUP('Receta'!$E73,Materias_Primas[#All],5,0),"") -> Uni | J73: =IFERROR(H73*VLOOKUP('Receta'!$E73,Materias_Primas[#All],10,0),"") -> 20 | K73: =IFERROR('Receta'!$J73/'Receta'!$C73,"") -> 20 | L73: =IFERROR(VLOOKUP('Receta'!$A73,Productos[#All],3,0),"") -> Turbante
A74: TU-07 | B74: =IFERROR(VLOOKUP('Receta'!$A74,Productos[#All],2,0),"") -> Turbante Am | C74: 8 | D74: 1 | E74: TE-06 | F74: =IFERROR(VLOOKUP(E74,Materias_Primas[#All],3,0),"") -> MP | G74: =IFERROR(VLOOKUP('Receta'!$E74,Materias_Primas[#All],2,0),"") -> Microfibra Dep 160 Am | H74: 0.13 | I74: =IFERROR(VLOOKUP('Receta'!$E74,Materias_Primas[#All],5,0),"") -> Mts | J74: =IFERROR(H74*VLOOKUP('Receta'!$E74,Materias_Primas[#All],10,0),"") -> 637 | K74: =IFERROR('Receta'!$J74/'Receta'!$C74,"") -> 79.625 | L74: =IFERROR(VLOOKUP('Receta'!$A74,Productos[#All],3,0),"") -> Turbante
A75: TU-07 | B75: =IFERROR(VLOOKUP('Receta'!$A75,Productos[#All],2,0),"") -> Turbante Am | C75: 100 | D75: 2 | E75: HI-01 | F75: =IFERROR(VLOOKUP(E75,Materias_Primas[#All],3,0),"") -> IN | G75: =IFERROR(VLOOKUP('Receta'!$E75,Materias_Primas[#All],2,0),"") -> Hilo Overlock Verde | H75: 2 | I75: =IFERROR(VLOOKUP('Receta'!$E75,Materias_Primas[#All],5,0),"") -> Uni | J75: =IFERROR(H75*VLOOKUP('Receta'!$E75,Materias_Primas[#All],10,0),"") -> 2598 | K75: =IFERROR('Receta'!$J75/'Receta'!$C75,"") -> 25.98 | L75: =IFERROR(VLOOKUP('Receta'!$A75,Productos[#All],3,0),"") -> Turbante
... A85: TU-08 | B85: =IFERROR(VLOOKUP('Receta'!$A85,Productos[#All],2,0),"") -> Turbante Ro | C85: 1 | D85: 8 | E85: MO-04 | F85: =IFERROR(VLOOKUP(E85,Materias_Primas[#All],3,0),"") -> MO | G85: =IFERROR(VLOOKUP('Receta'!$E85,Materias_Primas[#All],2,0),"") -> Preparación | H85: 0.5 | I85: =IFERROR(VLOOKUP('Receta'!$E85,Materias_Primas[#All],5,0),"") -> Min | J85: =IFERROR(H85*VLOOKUP('Receta'!$E85,Materias_Primas[#All],10,0),"") -> 32.5 | K85: =IFERROR('Receta'!$J85/'Receta'!$C85,"") -> 32.5 | L85: =IFERROR(VLOOKUP('Receta'!$A85,Productos[#All],3,0),"") -> Turbante
A86: TU-01 | B86: =IFERROR(VLOOKUP('Receta'!$A86,Productos[#All],2,0),"") -> Turbante Ca | C86: 1 | D86: 9 | E86: SE-01 | F86: =IFERROR(VLOOKUP(E86,Materias_Primas[#All],3,0),"") -> SE | G86: =IFERROR(VLOOKUP('Receta'!$E86,Materias_Primas[#All],2,0),"") -> Estampado Logo Turb. | H86: 1 | I86: =IFERROR(VLOOKUP('Receta'!$E86,Materias_Primas[#All],5,0),"") -> Uni | J86: =IFERROR(H86*VLOOKUP('Receta'!$E86,Materias_Primas[#All],10,0),"") -> 650 | K86: =IFERROR('Receta'!$J86/'Receta'!$C86,"") -> 650 | L86: =IFERROR(VLOOKUP('Receta'!$A114,Productos[#All],3,0),"") -> Turbante
A87: TU-01 | B87: =IFERROR(VLOOKUP('Receta'!$A87,Productos[#All],2,0),"") -> Turbante Ca | C87: 8 | D87: 10 | E87: IN-02 | F87: =IFERROR(VLOOKUP(E87,Materias_Primas[#All],3,0),"") -> IN | G87: =IFERROR(VLOOKUP('Receta'!$E87,Materias_Primas[#All],2,0),"") -> Cordón Eládtico | H87: 60 | I87: =IFERROR(VLOOKUP('Receta'!$E87,Materias_Primas[#All],5,0),"") -> Mts | J87: =IFERROR(H87*VLOOKUP('Receta'!$E87,Materias_Primas[#All],10,0),"") -> 8100 | K87: =IFERROR('Receta'!$J87/'Receta'!$C87,"") -> 1012.5 | L87: =IFERROR(VLOOKUP('Receta'!$A155,Productos[#All],3,0),"") -> Turbante
A88: TU-01 | B88: =IFERROR(VLOOKUP('Receta'!$A88,Productos[#All],2,0),"") -> Turbante Ca | C88: 1 | D88: 11 | E88: IN-03 | F88: =IFERROR(VLOOKUP(E88,Materias_Primas[#All],3,0),"") -> IN | G88: =IFERROR(VLOOKUP('Receta'!$E88,Materias_Primas[#All],2,0),"") -> Sesgo | H88: 0.13 | I88: =IFERROR(VLOOKUP('Receta'!$E88,Materias_Primas[#All],5,0),"") -> Mts | J88: =IFERROR(H88*VLOOKUP('Receta'!$E88,Materias_Primas[#All],10,0),"") -> 11.7 | K88: =IFERROR('Receta'!$J88/'Receta'!$C88,"") -> 11.7 | L88: =IFERROR(VLOOKUP('Receta'!$A156,Productos[#All],3,0),"") -> Turbante
A89: TU-01 | B89: =IFERROR(VLOOKUP('Receta'!$A89,Productos[#All],2,0),"") -> Turbante Ca | C89: 1 | D89: 12 | E89: IN-04 | F89: =IFERROR(VLOOKUP(E89,Materias_Primas[#All],3,0),"") -> IN | G89: =IFERROR(VLOOKUP('Receta'!$E89,Materias_Primas[#All],2,0),"") -> Logo Estampado | H89: 1 | I89: =IFERROR(VLOOKUP('Receta'!$E89,Materias_Primas[#All],5,0),"") -> Uni | J89: =IFERROR(H89*VLOOKUP('Receta'!$E89,Materias_Primas[#All],10,0),"") -> 774 | K89: =IFERROR('Receta'!$J89/'Receta'!$C89,"") -> 774 | L89: =IFERROR(VLOOKUP('Receta'!$A157,Productos[#All],3,0),"") -> Turbante
A90: TU-02 | B90: =IFERROR(VLOOKUP('Receta'!$A90,Productos[#All],2,0),"") -> Turbante Fu | C90: 8 | D90: 1 | E90: TE-03 | F90: =IFERROR(VLOOKUP(E90,Materias_Primas[#All],3,0),"") -> MP | G90: =IFERROR(VLOOKUP('Receta'!$E90,Materias_Primas[#All],2,0),"") -> Microfibra Dep 160 Fu | H90: 0.13 | I90: =IFERROR(VLOOKUP('Receta'!$E90,Materias_Primas[#All],5,0),"") -> Mts | J90: =IFERROR(H90*VLOOKUP('Receta'!$E90,Materias_Primas[#All],10,0),"") -> 637 | K90: =IFERROR('Receta'!$J90/'Receta'!$C90,"") -> 79.625 | L90: =IFERROR(VLOOKUP('Receta'!$A158,Productos[#All],3,0),"") -> Turbante
A91: TO-01 | B91: =IFERROR(VLOOKUP('Receta'!$A91,Productos[#All],2,0),"") -> Toalla 160x80 Az | C91: 8 | D91: 1 | E91: TE-03 | F91: =IFERROR(VLOOKUP(E91,Materias_Primas[#All],3,0),"") -> MP | G91: =IFERROR(VLOOKUP('Receta'!$E91,Materias_Primas[#All],2,0),"") -> Microfibra Dep 160 Fu | H91: 0.13 | I91: =IFERROR(VLOOKUP('Receta'!$E91,Materias_Primas[#All],5,0),"") -> Mts | J91: =IFERROR(H91*VLOOKUP('Receta'!$E91,Materias_Primas[#All],10,0),"") -> 637 | K91: =IFERROR('Receta'!$J91/'Receta'!$C91,"") -> 79.625 | L91: =IFERROR(VLOOKUP('Receta'!$A50,Productos[#All],3,0),"") -> Turbante
A92: TU-02 | B92: =IFERROR(VLOOKUP('Receta'!$A92,Productos[#All],2,0),"") -> Turbante Fu | C92: 100 | D92: 2 | E92: HI-01 | F92: =IFERROR(VLOOKUP(E92,Materias_Primas[#All],3,0),"") -> IN | G92: =IFERROR(VLOOKUP('Receta'!$E92,Materias_Primas[#All],2,0),"") -> Hilo Overlock Verde | H92: 2 | I92: =IFERROR(VLOOKUP('Receta'!$E92,Materias_Primas[#All],5,0),"") -> Uni | J92: =IFERROR(H92*VLOOKUP('Receta'!$E92,Materias_Primas[#All],10,0),"") -> 2598 | K92: =IFERROR('Receta'!$J92/'Receta'!$C92,"") -> 25.98 | L92: =IFERROR(VLOOKUP('Receta'!$A51,Productos[#All],3,0),"") -> Turbante
A93: TU-02 | B93: =IFERROR(VLOOKUP('Receta'!$A93,Productos[#All],2,0),"") -> Turbante Fu | C93: 1 | D93: 3 | E93: HI-02 | F93: =IFERROR(VLOOKUP(E93,Materias_Primas[#All],3,0),"") -> IN | G93: =IFERROR(VLOOKUP('Receta'!$E93,Materias_Primas[#All],2,0),"") -> Hilo Recta Verde | H93: 0.008125 | I93: =IFERROR(VLOOKUP('Receta'!$E93,Materias_Primas[#All],5,0),"") -> Uni | J93: =IFERROR(H93*VLOOKUP('Receta'!$E93,Materias_Primas[#All],10,0),"") -> 7.23125 | K93: =IFERROR('Receta'!$J93/'Receta'!$C93,"") -> 7.23125 | L93: =IFERROR(VLOOKUP('Receta'!$A52,Productos[#All],3,0),"") -> Turbante
A94: TU-03 | B94: =IFERROR(VLOOKUP('Receta'!$A94,Productos[#All],2,0),"") -> Turbante Vp | C94: 1 | D94: 5 | E94: MO-01 | F94: =IFERROR(VLOOKUP(E94,Materias_Primas[#All],3,0),"") -> MO | G94: =IFERROR(VLOOKUP('Receta'!$E94,Materias_Primas[#All],2,0),"") -> Corte | H94: 2 | I94: =IFERROR(VLOOKUP('Receta'!$E94,Materias_Primas[#All],5,0),"") -> Min | J94: =IFERROR(H94*VLOOKUP('Receta'!$E94,Materias_Primas[#All],10,0),"") -> 130 | K94: =IFERROR('Receta'!$J94/'Receta'!$C94,"") -> 130 | L94: =IFERROR(VLOOKUP('Receta'!$A94,Productos[#All],3,0),"") -> Turbante
A95: TU-03 | B95: =IFERROR(VLOOKUP('Receta'!$A95,Productos[#All],2,0),"") -> Turbante Vp | C95: 1 | D95: 6 | E95: MO-02 | F95: =IFERROR(VLOOKUP(E95,Materias_Primas[#All],3,0),"") -> MO | G95: =IFERROR(VLOOKUP('Receta'!$E95,Materias_Primas[#All],2,0),"") -> Confección | H95: 8 | I95: =IFERROR(VLOOKUP('Receta'!$E95,Materias_Primas[#All],5,0),"") -> Min | J95: =IFERROR(H95*VLOOKUP('Receta'!$E95,Materias_Primas[#All],10,0),"") -> 520 | K95: =IFERROR('Receta'!$J95/'Receta'!$C95,"") -> 520 | L95: =IFERROR(VLOOKUP('Receta'!$A95,Productos[#All],3,0),"") -> Turbante
A96: TU-03 | B96: =IFERROR(VLOOKUP('Receta'!$A96,Productos[#All],2,0),"") -> Turbante Vp | C96: 1 | D96: 7 | E96: MO-03 | F96: =IFERROR(VLOOKUP(E96,Materias_Primas[#All],3,0),"") -> MO | G96: =IFERROR(VLOOKUP('Receta'!$E96,Materias_Primas[#All],2,0),"") -> Botones | H96: 3 | I96: =IFERROR(VLOOKUP('Receta'!$E96,Materias_Primas[#All],5,0),"") -> Min | J96: =IFERROR(H96*VLOOKUP('Receta'!$E96,Materias_Primas[#All],10,0),"") -> 33 | K96: =IFERROR('Receta'!$J96/'Receta'!$C96,"") -> 33 | L96: =IFERROR(VLOOKUP('Receta'!$A96,Productos[#All],3,0),"") -> Turbante
A97: TU-03 | B97: =IFERROR(VLOOKUP('Receta'!$A97,Productos[#All],2,0),"") -> Turbante Vp | C97: 1 | D97: 8 | E97: MO-04 | F97: =IFERROR(VLOOKUP(E97,Materias_Primas[#All],3,0),"") -> MO | G97: =IFERROR(VLOOKUP('Receta'!$E97,Materias_Primas[#All],2,0),"") -> Preparación | H97: 0.5 | I97: =IFERROR(VLOOKUP('Receta'!$E97,Materias_Primas[#All],5,0),"") -> Min | J97: =IFERROR(H97*VLOOKUP('Receta'!$E97,Materias_Primas[#All],10,0),"") -> 32.5 | K97: =IFERROR('Receta'!$J97/'Receta'!$C97,"") -> 32.5 | L97: =IFERROR(VLOOKUP('Receta'!$A97,Productos[#All],3,0),"") -> Turbante
A98: TU-04 | B98: =IFERROR(VLOOKUP('Receta'!$A98,Productos[#All],2,0),"") -> Turbante Li | C98: 1 | D98: 5 | E98: MO-01 | F98: =IFERROR(VLOOKUP(E98,Materias_Primas[#All],3,0),"") -> MO | G98: =IFERROR(VLOOKUP('Receta'!$E98,Materias_Primas[#All],2,0),"") -> Corte | H98: 2 | I98: =IFERROR(VLOOKUP('Receta'!$E98,Materias_Primas[#All],5,0),"") -> Min | J98: =IFERROR(H98*VLOOKUP('Receta'!$E98,Materias_Primas[#All],10,0),"") -> 130 | K98: =IFERROR('Receta'!$J98/'Receta'!$C98,"") -> 130 | L98: =IFERROR(VLOOKUP('Receta'!$A98,Productos[#All],3,0),"") -> Turbante
A99: TU-04 | B99: =IFERROR(VLOOKUP('Receta'!$A99,Productos[#All],2,0),"") -> Turbante Li | C99: 1 | D99: 6 | E99: MO-02 | F99: =IFERROR(VLOOKUP(E99,Materias_Primas[#All],3,0),"") -> MO | G99: =IFERROR(VLOOKUP('Receta'!$E99,Materias_Primas[#All],2,0),"") -> Confección | H99: 8 | I99: =IFERROR(VLOOKUP('Receta'!$E99,Materias_Primas[#All],5,0),"") -> Min | J99: =IFERROR(H99*VLOOKUP('Receta'!$E99,Materias_Primas[#All],10,0),"") -> 520 | K99: =IFERROR('Receta'!$J99/'Receta'!$C99,"") -> 520 | L99: =IFERROR(VLOOKUP('Receta'!$A99,Productos[#All],3,0),"") -> Turbante
A100: TU-04 | B100: =IFERROR(VLOOKUP('Receta'!$A100,Productos[#All],2,0),"") -> Turbante Li | C100: 1 | D100: 7 | E100: MO-03 | F100: =IFERROR(VLOOKUP(E100,Materias_Primas[#All],3,0),"") -> MO | G100: =IFERROR(VLOOKUP('Receta'!$E100,Materias_Primas[#All],2,0),"") -> Botones | H100: 3 | I100: =IFERROR(VLOOKUP('Receta'!$E100,Materias_Primas[#All],5,0),"") -> Min | J100: =IFERROR(H100*VLOOKUP('Receta'!$E100,Materias_Primas[#All],10,0),"") -> 33 | K100: =IFERROR('Receta'!$J100/'Receta'!$C100,"") -> 33 | L100: =IFERROR(VLOOKUP('Receta'!$A100,Productos[#All],3,0),"") -> Turbante
A101: TU-04 | B101: =IFERROR(VLOOKUP('Receta'!$A101,Productos[#All],2,0),"") -> Turbante Li | C101: 1 | D101: 8 | E101: MO-04 | F101: =IFERROR(VLOOKUP(E101,Materias_Primas[#All],3,0),"") -> MO | G101: =IFERROR(VLOOKUP('Receta'!$E101,Materias_Primas[#All],2,0),"") -> Preparación | H101: 0.5 | I101: =IFERROR(VLOOKUP('Receta'!$E101,Materias_Primas[#All],5,0),"") -> Min | J101: =IFERROR(H101*VLOOKUP('Receta'!$E101,Materias_Primas[#All],10,0),"") -> 32.5 | K101: =IFERROR('Receta'!$J101/'Receta'!$C101,"") -> 32.5 | L101: =IFERROR(VLOOKUP('Receta'!$A101,Productos[#All],3,0),"") -> Turbante
A102: TU-05 | B102: =IFERROR(VLOOKUP('Receta'!$A102,Productos[#All],2,0),"") -> Turbante Ne | C102: 1 | D102: 5 | E102: MO-01 | F102: =IFERROR(VLOOKUP(E102,Materias_Primas[#All],3,0),"") -> MO | G102: =IFERROR(VLOOKUP('Receta'!$E102,Materias_Primas[#All],2,0),"") -> Corte | H102: 2 | I102: =IFERROR(VLOOKUP('Receta'!$E102,Materias_Primas[#All],5,0),"") -> Min | J102: =IFERROR(H102*VLOOKUP('Receta'!$E102,Materias_Primas[#All],10,0),"") -> 130 | K102: =IFERROR('Receta'!$J102/'Receta'!$C102,"") -> 130 | L102: =IFERROR(VLOOKUP('Receta'!$A102,Productos[#All],3,0),"") -> Turbante
A103: TU-05 | B103: =IFERROR(VLOOKUP('Receta'!$A103,Productos[#All],2,0),"") -> Turbante Ne | C103: 1 | D103: 6 | E103: MO-02 | F103: =IFERROR(VLOOKUP(E103,Materias_Primas[#All],3,0),"") -> MO | G103: =IFERROR(VLOOKUP('Receta'!$E103,Materias_Primas[#All],2,0),"") -> Confección | H103: 8 | I103: =IFERROR(VLOOKUP('Receta'!$E103,Materias_Primas[#All],5,0),"") -> Min | J103: =IFERROR(H103*VLOOKUP('Receta'!$E103,Materias_Primas[#All],10,0),"") -> 520 | K103: =IFERROR('Receta'!$J103/'Receta'!$C103,"") -> 520 | L103: =IFERROR(VLOOKUP('Receta'!$A103,Productos[#All],3,0),"") -> Turbante
A104: TU-05 | B104: =IFERROR(VLOOKUP('Receta'!$A104,Productos[#All],2,0),"") -> Turbante Ne | C104: 1 | D104: 7 | E104: MO-03 | F104: =IFERROR(VLOOKUP(E104,Materias_Primas[#All],3,0),"") -> MO | G104: =IFERROR(VLOOKUP('Receta'!$E104,Materias_Primas[#All],2,0),"") -> Botones | H104: 3 | I104: =IFERROR(VLOOKUP('Receta'!$E104,Materias_Primas[#All],5,0),"") -> Min | J104: =IFERROR(H104*VLOOKUP('Receta'!$E104,Materias_Primas[#All],10,0),"") -> 33 | K104: =IFERROR('Receta'!$J104/'Receta'!$C104,"") -> 33 | L104: =IFERROR(VLOOKUP('Receta'!$A104,Productos[#All],3,0),"") -> Turbante
A105: TU-05 | B105: =IFERROR(VLOOKUP('Receta'!$A105,Productos[#All],2,0),"") -> Turbante Ne | C105: 1 | D105: 8 | E105: MO-04 | F105: =IFERROR(VLOOKUP(E105,Materias_Primas[#All],3,0),"") -> MO | G105: =IFERROR(VLOOKUP('Receta'!$E105,Materias_Primas[#All],2,0),"") -> Preparación | H105: 0.5 | I105: =IFERROR(VLOOKUP('Receta'!$E105,Materias_Primas[#All],5,0),"") -> Min | J105: =IFERROR(H105*VLOOKUP('Receta'!$E105,Materias_Primas[#All],10,0),"") -> 32.5 | K105: =IFERROR('Receta'!$J105/'Receta'!$C105,"") -> 32.5 | L105: =IFERROR(VLOOKUP('Receta'!$A105,Productos[#All],3,0),"") -> Turbante
... A113: TU-07 | B113: =IFERROR(VLOOKUP('Receta'!$A113,Productos[#All],2,0),"") -> Turbante Am | C113: 1 | D113: 8 | E113: MO-04 | F113: =IFERROR(VLOOKUP(E113,Materias_Primas[#All],3,0),"") -> MO | G113: =IFERROR(VLOOKUP('Receta'!$E113,Materias_Primas[#All],2,0),"") -> Preparación | H113: 0.5 | I113: =IFERROR(VLOOKUP('Receta'!$E113,Materias_Primas[#All],5,0),"") -> Min | J113: =IFERROR(H113*VLOOKUP('Receta'!$E113,Materias_Primas[#All],10,0),"") -> 32.5 | K113: =IFERROR('Receta'!$J113/'Receta'!$C113,"") -> 32.5 | L113: =IFERROR(VLOOKUP('Receta'!$A113,Productos[#All],3,0),"") -> Turbante
A114: TU-02 | B114: =IFERROR(VLOOKUP('Receta'!$A114,Productos[#All],2,0),"") -> Turbante Fu | C114: 1 | D114: 4 | E114: GA-01 | F114: =IFERROR(VLOOKUP(E114,Materias_Primas[#All],3,0),"") -> 0 | G114: =IFERROR(VLOOKUP('Receta'!$E114,Materias_Primas[#All],2,0),"") -> Locomoción | H114: 0.02 | I114: =IFERROR(VLOOKUP('Receta'!$E114,Materias_Primas[#All],5,0),"") -> Uni | J114: =IFERROR(H114*VLOOKUP('Receta'!$E114,Materias_Primas[#All],10,0),"") -> 20 | K114: =IFERROR('Receta'!$J114/'Receta'!$C114,"") -> 20 | L114: =IFERROR(VLOOKUP('Receta'!$A53,Productos[#All],3,0),"") -> Turbante
A115: TU-02 | B115: =IFERROR(VLOOKUP('Receta'!$A115,Productos[#All],2,0),"") -> Turbante Fu | C115: 1 | D115: 5 | E115: MO-01 | F115: =IFERROR(VLOOKUP(E115,Materias_Primas[#All],3,0),"") -> MO | G115: =IFERROR(VLOOKUP('Receta'!$E115,Materias_Primas[#All],2,0),"") -> Corte | H115: 2 | I115: =IFERROR(VLOOKUP('Receta'!$E115,Materias_Primas[#All],5,0),"") -> Min | J115: =IFERROR(H115*VLOOKUP('Receta'!$E115,Materias_Primas[#All],10,0),"") -> 130 | K115: =IFERROR('Receta'!$J115/'Receta'!$C115,"") -> 130 | L115: =IFERROR(VLOOKUP('Receta'!$A90,Productos[#All],3,0),"") -> Turbante
A116: TU-03 | B116: =IFERROR(VLOOKUP('Receta'!$A116,Productos[#All],2,0),"") -> Turbante Vp | C116: 1 | D116: 9 | E116: SE-01 | F116: =IFERROR(VLOOKUP(E116,Materias_Primas[#All],3,0),"") -> SE | G116: =IFERROR(VLOOKUP('Receta'!$E116,Materias_Primas[#All],2,0),"") -> Estampado Logo Turb. | H116: 1 | I116: =IFERROR(VLOOKUP('Receta'!$E116,Materias_Primas[#All],5,0),"") -> Uni | J116: =IFERROR(H116*VLOOKUP('Receta'!$E116,Materias_Primas[#All],10,0),"") -> 650 | K116: =IFERROR('Receta'!$J116/'Receta'!$C116,"") -> 650 | L116: =IFERROR(VLOOKUP('Receta'!$A116,Productos[#All],3,0),"") -> Turbante
...

Sheet Proveedores
A1: Codigo | B1: Nombre | C1: Dirección | D1: Sector | E1: Teléfono | F1: Contacto | G1: WEB | H1: Observaciones
A2: 1 | B2: Pasajito Import. Calesa | C2: Pasajito mac clure | D2: Ind | E2: 56 997381561 | H2: Unico Tela MC Dep
A3: 2 | B3: Crayling vicuña M | C3: Av. Vicuña Mackenna 1415, Santiago | E3: 56 977935292 | F3: Sucursal | H3: Telas Bistrech y otras
A4: 3 | B4: Rainbown Publicidad | C4: Antonia Lopez de Bello 220, Recoleta | E4: 56 935179292 | F4: Johan Contreras , entrega 24 hrs. | H4: Sublimacion
A5: 4 | B5: Nahuel chile ltda | C5: Vargas buston 1088, San Miguel | E5: 56 966335702 | F5: Cobran por matriz, maximo 5 dias para entrega | G5: www.nahuelchileltda.cl | H5: Bordados
A6: 5 | B6: Textil Cassis S.A. | C6: Av. Jose Pedro Alessandri 1880, ñuñoa | E6: 56 982399670 | F6: Contacto: Raul | H6: Sublimacion por metros
A7: 6 | B7: Meriggi | C7: Av. Vicuña Mackenna 4525, san Joaquin | E7: 56 232734300 | G7: www.meriggi.cl | H7: Bistrech, Manteles Spandex, Granite
A8: 7 | B8: Calas | E8: 56 935646711 | G8: www.calas.cl | H8: Manteles Spandex, Mesas
A9: 8 | B9: Michel Neime | C9: Av Independencia 285. Independencia | E9: 22 735 2128 - 569 44502001 | H9: sesgo 1,5 $1210 20 mts
A10: 8 | B10: La muñequita | C10: Av. Independencia 381-383 | E10: 56 946926244 | H10: Telas granite y otras
A11: 9 | B11: Cristaleria La Paz | C11: Av. la Paz 126 | E11: 56 983017790 - 56 956532023 | H11: Cubiertos y menaje
A12: 10 | B12: Punto Chef | C12: Antonia Lopez de Bello 966. Independencia | E12: 56 976004569 | G12: www.puntochef.cl | H12: Cubiertos y menaje
A13: 11 | B13: Telas Pacifico
A14: 12
A15: 13
A16: 14

Sheet Ofertas
A1: S | B1: Proveedor | C1: Materia Prima | D1: Nombre | E1: Precio
A2: 2 | B2: =IFERROR(VLOOKUP(A2,Proveedores[#All],2,0),"") -> Crayling vicuña M | C2: TE-10 | D2: =IFERROR(VLOOKUP(C2,Materias_Primas[#All],2,0),"") -> Bistrech 150 cm Ne | E2: 780
A3: 2 | B3: =IFERROR(VLOOKUP(A3,Proveedores[#All],2,0),"") -> Crayling vicuña M | C3: TE-11 | D3: =IFERROR(VLOOKUP(C3,Materias_Primas[#All],2,0),"") -> Bistrech 300 cm Ne
A4: 2 | B4: =IFERROR(VLOOKUP(A4,Proveedores[#All],2,0),"") -> Crayling vicuña M | D4: =IFERROR(VLOOKUP(C4,Materias_Primas[#All],2,0),"")
A5: 6 | B5: =IFERROR(VLOOKUP(A5,Proveedores[#All],2,0),"") -> Meriggi | C5: TE-10 | D5: =IFERROR(VLOOKUP(C5,Materias_Primas[#All],2,0),"") -> Bistrech 150 cm Ne | E5: 844
A6: 6 | B6: =IFERROR(VLOOKUP(A6,Proveedores[#All],2,0),"") -> Meriggi | C6: TE-11 | D6: =IFERROR(VLOOKUP(C6,Materias_Primas[#All],2,0),"") -> Bistrech 300 cm Ne
A7: 6 | B7: =IFERROR(VLOOKUP(A7,Proveedores[#All],2,0),"") -> Meriggi | C7: TE-15 | D7: =IFERROR(VLOOKUP(C7,Materias_Primas[#All],2,0),"") -> Bistrech 150 cm Ve | E7: 844
A8: 3 | B8: =IFERROR(VLOOKUP(A8,Proveedores[#All],2,0),"") -> Rainbown Publicidad | C8: SE-01 | D8: =IFERROR(VLOOKUP(C8,Materias_Primas[#All],2,0),"") -> Estampado Logo Turb. | E8: 36
B9: =IFERROR(VLOOKUP(A9,Proveedores[#All],2,0),"") | D9: =IFERROR(VLOOKUP(C9,Materias_Primas[#All],2,0),"")
B10: =IFERROR(VLOOKUP(A10,Proveedores[#All],2,0),"") | D10: =IFERROR(VLOOKUP(C10,Materias_Primas[#All],2,0),"")
B11: =IFERROR(VLOOKUP(A11,Proveedores[#All],2,0),"") | D11: =IFERROR(VLOOKUP(C11,Materias_Primas[#All],2,0),"")
B12: =IFERROR(VLOOKUP(A12,Proveedores[#All],2,0),"") | D12: =IFERROR(VLOOKUP(C12,Materias_Primas[#All],2,0),"")
B13: =IFERROR(VLOOKUP(A13,Proveedores[#All],2,0),"") | D13: =IFERROR(VLOOKUP(C13,Materias_Primas[#All],2,0),"")
B14: =IFERROR(VLOOKUP(A14,Proveedores[#All],2,0),"") | D14: =IFERROR(VLOOKUP(C14,Materias_Primas[#All],2,0),"")
B15: =IFERROR(VLOOKUP(A15,Proveedores[#All],2,0),"") | D15: =IFERROR(VLOOKUP(C15,Materias_Primas[#All],2,0),"")
B16: =IFERROR(VLOOKUP(A16,Proveedores[#All],2,0),"") | D16: =IFERROR(VLOOKUP(C16,Materias_Primas[#All],2,0),"")

Sheet Consumo
A1: Producto | B1: Nombre P | C1: Cantidad | D1: MP | E1: Nombre | F1: Cant PR | G1: Cant MP | H1: Cons Unit | I1: ID | J1: Tipo | K1: Consumo | L1: Unidad
A2: ='Receta'!A2 -> TO-07 | B2: =IFERROR(VLOOKUP(A2,Productos[#All],2,0),"") -> Toalla 160x80 Na | C2: =SUMIF(Producción[[#All],[Producto]],A2,Producción[[#All],[Cant]]) -> 2 | D2: ='Receta'!E2 -> TE-01 | E2: =IFERROR(VLOOKUP(D2,Materias_Primas[#All],2,0),"") -> Microfibra Dep 160 Na | F2: ='Receta'!C2 -> 1 | G2: ='Receta'!H2 -> 0.8 | H2: =IFERROR(G2/F2,"") -> 0.8 | I2: 1 | J2: Empanada | K2: =C2*H2 -> 1.6 | L2: =IFERROR(VLOOKUP(D2,Materias_Primas[#All],5,0),"") -> Mts
A3: ='Receta'!A3 -> TO-07 | B3: =IFERROR(VLOOKUP(A3,Productos[#All],2,0),"") -> Toalla 160x80 Na | C3: =SUMIF(Producción[[#All],[Producto]],A3,Producción[[#All],[Cant]]) -> 2 | D3: ='Receta'!E3 -> HI-01 | E3: =IFERROR(VLOOKUP(D3,Materias_Primas[#All],2,0),"") -> Hilo Overlock Verde | F3: ='Receta'!C3 -> 1 | G3: ='Receta'!H3 -> 0.04 | H3: =IFERROR(G3/F3,"") -> 0.04 | I3: 1 | J3: Empanada | K3: =C3*H3 -> 0.08 | L3: =IFERROR(VLOOKUP(D3,Materias_Primas[#All],5,0),"") -> Uni
A4: ='Receta'!A4 -> TO-07 | B4: =IFERROR(VLOOKUP(A4,Productos[#All],2,0),"") -> Toalla 160x80 Na | C4: =SUMIF(Producción[[#All],[Producto]],A4,Producción[[#All],[Cant]]) -> 2 | D4: ='Receta'!E4 -> HI-02 | E4: =IFERROR(VLOOKUP(D4,Materias_Primas[#All],2,0),"") -> Hilo Recta Verde | F4: ='Receta'!C4 -> 1 | G4: ='Receta'!H4 -> 0.04 | H4: =IFERROR(G4/F4,"") -> 0.04 | I4: 1 | J4: Empanada | K4: =C4*H4 -> 0.08 | L4: =IFERROR(VLOOKUP(D4,Materias_Primas[#All],5,0),"") -> Uni
A5: ='Receta'!A5 -> TO-07 | B5: =IFERROR(VLOOKUP(A5,Productos[#All],2,0),"") -> Toalla 160x80 Na | C5: =SUMIF(Producción[[#All],[Producto]],A5,Producción[[#All],[Cant]]) -> 2 | D5: ='Receta'!E5 -> GA-01 | E5: =IFERROR(VLOOKUP(D5,Materias_Primas[#All],2,0),"") -> Locomoción | F5: ='Receta'!C5 -> 1 | G5: ='Receta'!H5 -> 0.1 | H5: =IFERROR(G5/F5,"") -> 0.1 | I5: 1 | J5: Empanada | K5: =C5*H5 -> 0.2 | L5: =IFERROR(VLOOKUP(D5,Materias_Primas[#All],5,0),"") -> Uni
A6: ='Receta'!A6 -> TO-06 | B6: =IFERROR(VLOOKUP(A6,Productos[#All],2,0),"") -> Toalla 160x80 Fu | C6: =SUMIF(Producción[[#All],[Producto]],A6,Producción[[#All],[Cant]]) -> 2 | D6: ='Receta'!E6 -> TE-03 | E6: =IFERROR(VLOOKUP(D6,Materias_Primas[#All],2,0),"") -> Microfibra Dep 160 Fu | F6: ='Receta'!C6 -> 1 | G6: ='Receta'!H6 -> 0.8 | H6: =IFERROR(G6/F6,"") -> 0.8 | I6: 1 | J6: Empanada | K6: =C6*H6 -> 1.6 | L6: =IFERROR(VLOOKUP(D6,Materias_Primas[#All],5,0),"") -> Mts
A7: ='Receta'!A7 -> TO-06 | B7: =IFERROR(VLOOKUP(A7,Productos[#All],2,0),"") -> Toalla 160x80 Fu | C7: =SUMIF(Producción[[#All],[Producto]],A7,Producción[[#All],[Cant]]) -> 2 | D7: ='Receta'!E7 -> HI-01 | E7: =IFERROR(VLOOKUP(D7,Materias_Primas[#All],2,0),"") -> Hilo Overlock Verde | F7: ='Receta'!C7 -> 1 | G7: ='Receta'!H7 -> 0.04 | H7: =IFERROR(G7/F7,"") -> 0.04 | I7: 1 | J7: Empanada | K7: =C7*H7 -> 0.08 | L7: =IFERROR(VLOOKUP(D7,Materias_Primas[#All],5,0),"") -> Uni
A8: ='Receta'!A8 -> TO-06 | B8: =IFERROR(VLOOKUP(A8,Productos[#All],2,0),"") -> Toalla 160x80 Fu | C8: =SUMIF(Producción[[#All],[Producto]],A8,Producción[[#All],[Cant]]) -> 2 | D8: ='Receta'!E8 -> HI-02 | E8: =IFERROR(VLOOKUP(D8,Materias_Primas[#All],2,0),"") -> Hilo Recta Verde | F8: ='Receta'!C8 -> 1 | G8: ='Receta'!H8 -> 0.04 | H8: =IFERROR(G8/F8,"") -> 0.04 | I8: 1 | J8: Empanada | K8: =C8*H8 -> 0.08 | L8: =IFERROR(VLOOKUP(D8,Materias_Primas[#All],5,0),"") -> Uni
A9: ='Receta'!A9 -> TO-06 | B9: =IFERROR(VLOOKUP(A9,Productos[#All],2,0),"") -> Toalla 160x80 Fu | C9: =SUMIF(Producción[[#All],[Producto]],A9,Producción[[#All],[Cant]]) -> 2 | D9: ='Receta'!E9 -> GA-01 | E9: =IFERROR(VLOOKUP(D9,Materias_Primas[#All],2,0),"") -> Locomoción | F9: ='Receta'!C9 -> 1 | G9: ='Receta'!H9 -> 0.1 | H9: =IFERROR(G9/F9,"") -> 0.1 | I9: 1 | J9: Empanada | K9: =C9*H9 -> 0.2 | L9: =IFERROR(VLOOKUP(D9,Materias_Primas[#All],5,0),"") -> Uni
A10: ='Receta'!A10 -> TO-01 | B10: =IFERROR(VLOOKUP(A10,Productos[#All],2,0),"") -> Toalla 160x80 Az | C10: =SUMIF(Producción[[#All],[Producto]],A10,Producción[[#All],[Cant]]) -> 2 | D10: ='Receta'!E10 -> TE-09 | E10: =IFERROR(VLOOKUP(D10,Materias_Primas[#All],2,0),"") -> Microfibra Dep 160 Az | F10: ='Receta'!C10 -> 1 | G10: ='Receta'!H10 -> 0.8 | H10: =IFERROR(G10/F10,"") -> 0.8 | I10: 1 | J10: Empanada | K10: =C10*H10 -> 1.6 | L10: =IFERROR(VLOOKUP(D10,Materias_Primas[#All],5,0),"") -> Mts
A11: ='Receta'!A11 -> TO-01 | B11: =IFERROR(VLOOKUP(A11,Productos[#All],2,0),"") -> Toalla 160x80 Az | C11: =SUMIF(Producción[[#All],[Producto]],A11,Producción[[#All],[Cant]]) -> 2 | D11: ='Receta'!E11 -> HI-01 | E11: =IFERROR(VLOOKUP(D11,Materias_Primas[#All],2,0),"") -> Hilo Overlock Verde | F11: ='Receta'!C11 -> 1 | G11: ='Receta'!H11 -> 0.04 | H11: =IFERROR(G11/F11,"") -> 0.04 | I11: 1 | J11: Empanada | K11: =C11*H11 -> 0.08 | L11: =IFERROR(VLOOKUP(D11,Materias_Primas[#All],5,0),"") -> Uni
A12: ='Receta'!A12 -> TO-01 | B12: =IFERROR(VLOOKUP(A12,Productos[#All],2,0),"") -> Toalla 160x80 Az | C12: =SUMIF(Producción[[#All],[Producto]],A12,Producción[[#All],[Cant]]) -> 2 | D12: ='Receta'!E12 -> HI-02 | E12: =IFERROR(VLOOKUP(D12,Materias_Primas[#All],2,0),"") -> Hilo Recta Verde | F12: ='Receta'!C12 -> 1 | G12: ='Receta'!H12 -> 0.04 | H12: =IFERROR(G12/F12,"") -> 0.04 | I12: 1 | J12: Empanada | K12: =C12*H12 -> 0.08 | L12: =IFERROR(VLOOKUP(D12,Materias_Primas[#All],5,0),"") -> Uni
A13: ='Receta'!A13 -> TO-01 | B13: =IFERROR(VLOOKUP(A13,Productos[#All],2,0),"") -> Toalla 160x80 Az | C13: =SUMIF(Producción[[#All],[Producto]],A13,Producción[[#All],[Cant]]) -> 2 | D13: ='Receta'!E13 -> GA-01 | E13: =IFERROR(VLOOKUP(D13,Materias_Primas[#All],2,0),"") -> Locomoción | F13: ='Receta'!C13 -> 1 | G13: ='Receta'!H13 -> 0.1 | H13: =IFERROR(G13/F13,"") -> 0.1 | I13: 1 | J13: Empanada | K13: =C13*H13 -> 0.2 | L13: =IFERROR(VLOOKUP(D13,Materias_Primas[#All],5,0),"") -> Uni
... A295: ='Receta'!A295 -> 0 | B295: =IFERROR(VLOOKUP(A295,Productos[#All],2,0),"") | C295: =SUMIF(Producción[[#All],[Producto]],A295,Producción[[#All],[Cant]]) -> 0 | D295: ='Receta'!E295 -> 0 | E295: =IFERROR(VLOOKUP(D295,Materias_Primas[#All],2,0),"") | F295: ='Receta'!C295 -> TERMINACIÓN | G295: ='Receta'!H295 -> 0 | H295: =IFERROR(G295/F295,"") | I295: 7 | J295: Empanada | K295: =C295*H295 -> #VALUE! | L295: =IFERROR(VLOOKUP(D295,Materias_Primas[#All],5,0),"")
A296: ='Receta'!A297 -> 0 | B296: =IFERROR(VLOOKUP(A296,Productos[#All],2,0),"") | C296: =SUMIF(Producción[[#All],[Producto]],A296,Producción[[#All],[Cant]]) -> 0 | D296: ='Receta'!E297 -> 0 | E296: =IFERROR(VLOOKUP(D296,Materias_Primas[#All],2,0),"") | F296: ='Receta'!C297 -> PLANCHADO | G296: ='Receta'!H297 -> 0 | H296: =IFERROR(G296/F296,"") | I296: 7 | J296: Empanada | K296: =C296*H296 -> #VALUE! | L296: =IFERROR(VLOOKUP(D296,Materias_Primas[#All],5,0),"")
A297: ='Receta'!A298 -> 0 | B297: =IFERROR(VLOOKUP(A297,Productos[#All],2,0),"") | C297: =SUMIF(Producción[[#All],[Producto]],A297,Producción[[#All],[Cant]]) -> 0 | D297: ='Receta'!E298 -> 1820 | E297: =IFERROR(VLOOKUP(D297,Materias_Primas[#All],2,0),"") | F297: ='Receta'!C298 -> MO | G297: ='Receta'!H298 -> 0 | H297: =IFERROR(G297/F297,"") | I297: 7 | J297: Empanada | K297: =C297*H297 -> #VALUE! | L297: =IFERROR(VLOOKUP(D297,Materias_Primas[#All],5,0),"")
A298: ='Receta'!A299 -> 0 | B298: =IFERROR(VLOOKUP(A298,Productos[#All],2,0),"") | C298: =SUMIF(Producción[[#All],[Producto]],A298,Producción[[#All],[Cant]]) -> 0 | D298: ='Receta'!E299 -> 0 | E298: =IFERROR(VLOOKUP(D298,Materias_Primas[#All],2,0),"") | F298: ='Receta'!C299 -> 0 | G298: ='Receta'!H299 -> 0 | H298: =IFERROR(G298/F298,"") | I298: 7 | J298: Empanada | K298: =C298*H298 -> #VALUE! | L298: =IFERROR(VLOOKUP(D298,Materias_Primas[#All],5,0),"")
A299: ='Receta'!A300 -> 0 | B299: =IFERROR(VLOOKUP(A299,Productos[#All],2,0),"") | C299: =SUMIF(Producción[[#All],[Producto]],A299,Producción[[#All],[Cant]]) -> 0 | D299: ='Receta'!E300 -> 0 | E299: =IFERROR(VLOOKUP(D299,Materias_Primas[#All],2,0),"") | F299: ='Receta'!C300 -> 0 | G299: ='Receta'!H300 -> 0 | H299: =IFERROR(G299/F299,"") | I299: 7 | J299: Empanada | K299: =C299*H299 -> #VALUE! | L299: =IFERROR(VLOOKUP(D299,Materias_Primas[#All],5,0),"")
A300: ='Receta'!A301 -> 0 | B300: =IFERROR(VLOOKUP(A300,Productos[#All],2,0),"") | C300: =SUMIF(Producción[[#All],[Producto]],A300,Producción[[#All],[Cant]]) -> 0 | D300: ='Receta'!E301 -> 0 | E300: =IFERROR(VLOOKUP(D300,Materias_Primas[#All],2,0),"") | F300: ='Receta'!C301 -> 0 | G300: ='Receta'!H301 -> 0 | H300: =IFERROR(G300/F300,"") | I300: 7 | J300: Empanada | K300: =C300*H300 -> #VALUE! | L300: =IFERROR(VLOOKUP(D300,Materias_Primas[#All],5,0),"")
A301: ='Receta'!A302 -> 0 | B301: =IFERROR(VLOOKUP(A301,Productos[#All],2,0),"") | C301: =SUMIF(Producción[[#All],[Producto]],A301,Producción[[#All],[Cant]]) -> 0 | D301: ='Receta'!E302 -> 3200 | E301: =IFERROR(VLOOKUP(D301,Materias_Primas[#All],2,0),"") | F301: ='Receta'!C302 -> 0 | G301: ='Receta'!H302 -> 0 | H301: =IFERROR(G301/F301,"") | I301: 7 | J301: Empanada | K301: =C301*H301 -> #VALUE! | L301: =IFERROR(VLOOKUP(D301,Materias_Primas[#All],5,0),"")
A302: ='Receta'!A303 -> 0 | B302: =IFERROR(VLOOKUP(A302,Productos[#All],2,0),"") | C302: =SUMIF(Producción[[#All],[Producto]],A302,Producción[[#All],[Cant]]) -> 0 | D302: ='Receta'!E303 -> 0 | E302: =IFERROR(VLOOKUP(D302,Materias_Primas[#All],2,0),"") | F302: ='Receta'!C303 -> CORTE | G302: ='Receta'!H303 -> 8 | H302: =IFERROR(G302/F302,"") | I302: 7 | J302: Empanada | K302: =C302*H302 -> #VALUE! | L302: =IFERROR(VLOOKUP(D302,Materias_Primas[#All],5,0),"")
A303: ='Receta'!A304 -> 0 | B303: =IFERROR(VLOOKUP(A303,Productos[#All],2,0),"") | C303: =SUMIF(Producción[[#All],[Producto]],A303,Producción[[#All],[Cant]]) -> 0 | D303: ='Receta'!E304 -> 0 | E303: =IFERROR(VLOOKUP(D303,Materias_Primas[#All],2,0),"") | F303: ='Receta'!C304 -> CONFECCIÓN | G303: ='Receta'!H304 -> 3 | H303: =IFERROR(G303/F303,"") | I303: 7 | J303: Empanada | K303: =C303*H303 -> #VALUE! | L303: =IFERROR(VLOOKUP(D303,Materias_Primas[#All],5,0),"")
A304: ='Receta'!A305 -> 0 | B304: =IFERROR(VLOOKUP(A304,Productos[#All],2,0),"") | C304: =SUMIF(Producción[[#All],[Producto]],A304,Producción[[#All],[Cant]]) -> 0 | D304: ='Receta'!E305 -> 0 | E304: =IFERROR(VLOOKUP(D304,Materias_Primas[#All],2,0),"") | F304: ='Receta'!C305 -> TERMINACIÓN | G304: ='Receta'!H305 -> 0 | H304: =IFERROR(G304/F304,"") | I304: 7 | J304: Empanada | K304: =C304*H304 -> #VALUE! | L304: =IFERROR(VLOOKUP(D304,Materias_Primas[#All],5,0),"")
A305: ='Receta'!A306 -> 0 | B305: =IFERROR(VLOOKUP(A305,Productos[#All],2,0),"") | C305: =SUMIF(Producción[[#All],[Producto]],A305,Producción[[#All],[Cant]]) -> 0 | D305: ='Receta'!E306 -> 0 | E305: =IFERROR(VLOOKUP(D305,Materias_Primas[#All],2,0),"") | F305: ='Receta'!C306 -> PREPARADO | G305: ='Receta'!H306 -> 2 | H305: =IFERROR(G305/F305,"") | I305: 7 | J305: Empanada | K305: =C305*H305 -> #VALUE! | L305: =IFERROR(VLOOKUP(D305,Materias_Primas[#All],5,0),"")
A306: ='Receta'!A307 -> 0 | B306: =IFERROR(VLOOKUP(A306,Productos[#All],2,0),"") | C306: =SUMIF(Producción[[#All],[Producto]],A306,Producción[[#All],[Cant]]) -> 0 | D306: ='Receta'!E307 -> 0 | E306: =IFERROR(VLOOKUP(D306,Materias_Primas[#All],2,0),"") | F306: ='Receta'!C307 -> PLANCHADO | G306: ='Receta'!H307 -> 0 | H306: =IFERROR(G306/F306,"") | I306: 7 | J306: Empanada | K306: =C306*H306 -> #VALUE! | L306: =IFERROR(VLOOKUP(D306,Materias_Primas[#All],5,0),"")
A307: ='Receta'!A308 -> 0 | B307: =IFERROR(VLOOKUP(A307,Productos[#All],2,0),"") | C307: =SUMIF(Producción[[#All],[Producto]],A307,Producción[[#All],[Cant]]) -> 0 | D307: ='Receta'!E308 -> 0 | E307: =IFERROR(VLOOKUP(D307,Materias_Primas[#All],2,0),"") | F307: ='Receta'!C308 -> 0 | G307: ='Receta'!H308 -> 0 | H307: =IFERROR(G307/F307,"") | I307: 7 | J307: Empanada | K307: =C307*H307 -> #VALUE! | L307: =IFERROR(VLOOKUP(D307,Materias_Primas[#All],5,0),"")
... A2746: ='Receta'!A2747 -> 0 | B2746: =IFERROR(VLOOKUP(A2746,Productos[#All],2,0),"") | C2746: =SUMIF(Producción[[#All],[Producto]],A2746,Producción[[#All],[Cant]]) -> 0 | D2746: ='Receta'!E2747 -> 0 | E2746: =IFERROR(VLOOKUP(D2746,Materias_Primas[#All],2,0),"") | F2746: ='Receta'!C2747 -> 0 | G2746: ='Receta'!H2747 -> 0 | H2746: =IFERROR(G2746/F2746,"") | I2746: 92 | J2746: Empanada | K2746: =C2746*H2746 -> #VALUE! | L2746: =IFERROR(VLOOKUP(D2746,Materias_Primas[#All],5,0),"")
A2747: Total | B2747: =IFERROR(VLOOKUP(A2747,Productos[#All],2,0),"") | C2747: =SUMIF(Producción[[#All],[Producto]],A2747,Producción[[#All],[Cant]]) -> 0 | D2747: ='Receta'!E2748 -> 0 | H2747: =IFERROR(G2747/F2747,"") | K2747: =SUBTOTAL(109,Consumo!$K$2:$K$2746) -> #VALUE! | L2747: =IFERROR(VLOOKUP(D2747,Materias_Primas[#All],5,0),"")

Sheet Stock
A1: Código | B1: Materia Prima | C1: Cant Cons | D1: Cant Rbjd | E1: Cant Comp | F1: Stock | G1: Unidad | H1: Costo | I1: Pron Com
A2: ='Materias Primas'!$A2 -> TE-01 | B2: =IFERROR(VLOOKUP(Stock!$A2,Materias_Primas[#All],2,0),"") -> Microfibra Dep 160 Na | C2: =IFERROR(SUMIF(Consumo!$E$2:$E$2746,Stock!$B2,Consumo!$K$2:$K$2746),"") -> 3.265 | D2: =SUMIFS(Compras!$H$11:$H$155,Compras!$G$11:$G$155,Stock!$B2,Compras!$C$11:$C$155,"Ajust Inv") -> 0 | E2: =SUMIFS(Compras!$H$2:$H$155,Compras!$G$2:$G$155,Stock!$B2,Compras!$C$2:$C$155,"Compra") -> 5.85 | F2: =Stock!$E2-Stock!$C2-Stock!$D2 -> 2.585 | G2: =IFERROR(VLOOKUP(Stock!$A2,Materias_Primas[#All],5,0),"") -> Mts | H2: =IFERROR(ROUND(VLOOKUP(Stock!$A2,Materias_Primas[#All],7,0)*Stock!$F2,0),"") -> 2021 | I2: =IFERROR(ROUND(Stock!$F2/(Stock!$C2/(TODAY()-MIN(Producción!$C$2:$C$204))),1),"") -> 107.7
A3: ='Materias Primas'!$A3 -> TE-02 | B3: =IFERROR(VLOOKUP(Stock!$A3,Materias_Primas[#All],2,0),"") -> Microfibra Dep 160 Li | C3: =IFERROR(SUMIF(Consumo!$E$2:$E$2746,Stock!$B3,Consumo!$K$2:$K$2746),"") -> 1.33 | D3: =SUMIFS(Compras!$H$11:$H$155,Compras!$G$11:$G$155,Stock!$B3,Compras!$C$11:$C$155,"Ajust Inv") -> 0 | E3: =SUMIFS(Compras!$H$2:$H$155,Compras!$G$2:$G$155,Stock!$B3,Compras!$C$2:$C$155,"Compra") -> 2.5 | F3: =Stock!$E3-Stock!$C3-Stock!$D3 -> 1.17 | G3: =IFERROR(VLOOKUP(Stock!$A3,Materias_Primas[#All],5,0),"") -> Mts | H3: =IFERROR(ROUND(VLOOKUP(Stock!$A3,Materias_Primas[#All],7,0)*Stock!$F3,0),"") -> 915 | I3: =IFERROR(ROUND(Stock!$F3/(Stock!$C3/(TODAY()-MIN(Producción!$C$2:$C$204))),1),"") -> 119.6
A4: ='Materias Primas'!$A4 -> TE-03 | B4: =IFERROR(VLOOKUP(Stock!$A4,Materias_Primas[#All],2,0),"") -> Microfibra Dep 160 Fu | C4: =IFERROR(SUMIF(Consumo!$E$2:$E$2746,Stock!$B4,Consumo!$K$2:$K$2746),"") -> 1.8925 | D4: =SUMIFS(Compras!$H$11:$H$155,Compras!$G$11:$G$155,Stock!$B4,Compras!$C$11:$C$155,"Ajust Inv") -> 0 | E4: =SUMIFS(Compras!$H$2:$H$155,Compras!$G$2:$G$155,Stock!$B4,Compras!$C$2:$C$155,"Compra") -> 4.2 | F4: =Stock!$E4-Stock!$C4-Stock!$D4 -> 2.3075 | G4: =IFERROR(VLOOKUP(Stock!$A4,Materias_Primas[#All],5,0),"") -> Mts | H4: =IFERROR(ROUND(VLOOKUP(Stock!$A4,Materias_Primas[#All],7,0)*Stock!$F4,0),"") -> 1804 | I4: =IFERROR(ROUND(Stock!$F4/(Stock!$C4/(TODAY()-MIN(Producción!$C$2:$C$204))),1),"") -> 165.8
A5: ='Materias Primas'!$A5 -> TE-04 | B5: =IFERROR(VLOOKUP(Stock!$A5,Materias_Primas[#All],2,0),"") -> Microfibra Dep 160 Ca | C5: =IFERROR(SUMIF(Consumo!$E$2:$E$2746,Stock!$B5,Consumo!$K$2:$K$2746),"") -> 1.86 | D5: =SUMIFS(Compras!$H$11:$H$155,Compras!$G$11:$G$155,Stock!$B5,Compras!$C$11:$C$155,"Ajust Inv") -> 0 | E5: =SUMIFS(Compras!$H$2:$H$155,Compras!$G$2:$G$155,Stock!$B5,Compras!$C$2:$C$155,"Compra") -> 4.2 | F5: =Stock!$E5-Stock!$C5-Stock!$D5 -> 2.34 | G5: =IFERROR(VLOOKUP(Stock!$A5,Materias_Primas[#All],5,0),"") -> Mts | H5: =IFERROR(ROUND(VLOOKUP(Stock!$A5,Materias_Primas[#All],7,0)*Stock!$F5,0),"") -> 1830 | I5: =IFERROR(ROUND(Stock!$F5/(Stock!$C5/(TODAY()-MIN(Producción!$C$2:$C$204))),1),"") -> 171.1
A6: ='Materias Primas'!$A6 -> TE-05 | B6: =IFERROR(VLOOKUP(Stock!$A6,Materias_Primas[#All],2,0),"") -> Microfibra Dep 160 Ne | C6: =IFERROR(SUMIF(Consumo!$E$2:$E$2746,Stock!$B6,Consumo!$K$2:$K$2746),"") -> 0.93 | D6: =SUMIFS(Compras!$H$11:$H$155,Compras!$G$11:$G$155,Stock!$B6,Compras!$C$11:$C$155,"Ajust Inv") -> 0 | E6: =SUMIFS(Compras!$H$2:$H$155,Compras!$G$2:$G$155,Stock!$B6,Compras!$C$2:$C$155,"Compra") -> 2.1 | F6: =Stock!$E6-Stock!$C6-Stock!$D6 -> 1.17 | G6: =IFERROR(VLOOKUP(Stock!$A6,Materias_Primas[#All],5,0),"") -> Mts | H6: =IFERROR(ROUND(VLOOKUP(Stock!$A6,Materias_Primas[#All],7,0)*Stock!$F6,0),"") -> 915 | I6: =IFERROR(ROUND(Stock!$F6/(Stock!$C6/(TODAY()-MIN(Producción!$C$2:$C$204))),1),"") -> 171.1
A7: ='Materias Primas'!$A7 -> TE-06 | B7: =IFERROR(VLOOKUP(Stock!$A7,Materias_Primas[#All],2,0),"") -> Microfibra Dep 160 Am | C7: =IFERROR(SUMIF(Consumo!$E$2:$E$2746,Stock!$B7,Consumo!$K$2:$K$2746),"") -> 1.665 | D7: =SUMIFS(Compras!$H$11:$H$155,Compras!$G$11:$G$155,Stock!$B7,Compras!$C$11:$C$155,"Ajust Inv") -> 0 | E7: =SUMIFS(Compras!$H$2:$H$155,Compras!$G$2:$G$155,Stock!$B7,Compras!$C$2:$C$155,"Compra") -> 2.25 | F7: =Stock!$E7-Stock!$C7-Stock!$D7 -> 0.585 | G7: =IFERROR(VLOOKUP(Stock!$A7,Materias_Primas[#All],5,0),"") -> Mts | H7: =IFERROR(ROUND(VLOOKUP(Stock!$A7,Materias_Primas[#All],7,0)*Stock!$F7,0),"") -> 457 | I7: =IFERROR(ROUND(Stock!$F7/(Stock!$C7/(TODAY()-MIN(Producción!$C$2:$C$204))),1),"") -> 47.8
A8: ='Materias Primas'!$A8 -> TE-07 | B8: =IFERROR(VLOOKUP(Stock!$A8,Materias_Primas[#All],2,0),"") -> Microfibra Dep 160 Ro | C8: =IFERROR(SUMIF(Consumo!$E$2:$E$2746,Stock!$B8,Consumo!$K$2:$K$2746),"") -> 1.665 | D8: =SUMIFS(Compras!$H$11:$H$155,Compras!$G$11:$G$155,Stock!$B8,Compras!$C$11:$C$155,"Ajust Inv") -> 0 | E8: =SUMIFS(Compras!$H$2:$H$155,Compras!$G$2:$G$155,Stock!$B8,Compras!$C$2:$C$155,"Compra") -> 2.25 | F8: =Stock!$E8-Stock!$C8-Stock!$D8 -> 0.585 | G8: =IFERROR(VLOOKUP(Stock!$A8,Materias_Primas[#All],5,0),"") -> Mts | H8: =IFERROR(ROUND(VLOOKUP(Stock!$A8,Materias_Primas[#All],7,0)*Stock!$F8,0),"") -> 457 | I8: =IFERROR(ROUND(Stock!$F8/(Stock!$C8/(TODAY()-MIN(Producción!$C$2:$C$204))),1),"") -> 47.8
A9: ='Materias Primas'!$A9 -> TE-08 | B9: =IFERROR(VLOOKUP(Stock!$A9,Materias_Primas[#All],2,0),"") -> Microfibra Dep 160 Vp | C9: =IFERROR(SUMIF(Consumo!$E$2:$E$2746,Stock!$B9,Consumo!$K$2:$K$2746),"") -> 0.93 | D9: =SUMIFS(Compras!$H$11:$H$155,Compras!$G$11:$G$155,Stock!$B9,Compras!$C$11:$C$155,"Ajust Inv") -> 0 | E9: =SUMIFS(Compras!$H$2:$H$155,Compras!$G$2:$G$155,Stock!$B9,Compras!$C$2:$C$155,"Compra") -> 2.1 | F9: =Stock!$E9-Stock!$C9-Stock!$D9 -> 1.17 | G9: =IFERROR(VLOOKUP(Stock!$A9,Materias_Primas[#All],5,0),"") -> Mts | H9: =IFERROR(ROUND(VLOOKUP(Stock!$A9,Materias_Primas[#All],7,0)*Stock!$F9,0),"") -> 915 | I9: =IFERROR(ROUND(Stock!$F9/(Stock!$C9/(TODAY()-MIN(Producción!$C$2:$C$204))),1),"") -> 171.1
A10: ='Materias Primas'!$A10 -> TE-09 | B10: =IFERROR(VLOOKUP(Stock!$A10,Materias_Primas[#All],2,0),"") -> Microfibra Dep 160 Az | C10: =IFERROR(SUMIF(Consumo!$E$2:$E$2746,Stock!$B10,Consumo!$K$2:$K$2746),"") -> 1.6 | D10: =SUMIFS(Compras!$H$11:$H$155,Compras!$G$11:$G$155,Stock!$B10,Compras!$C$11:$C$155,"Ajust Inv") -> 0 | E10: =SUMIFS(Compras!$H$2:$H$155,Compras!$G$2:$G$155,Stock!$B10,Compras!$C$2:$C$155,"Compra") -> 1.6 | F10: =Stock!$E10-Stock!$C10-Stock!$D10 -> 0 | G10: =IFERROR(VLOOKUP(Stock!$A10,Materias_Primas[#All],5,0),"") -> Mts | H10: =IFERROR(ROUND(VLOOKUP(Stock!$A10,Materias_Primas[#All],7,0)*Stock!$F10,0),"") -> 0 | I10: =IFERROR(ROUND(Stock!$F10/(Stock!$C10/(TODAY()-MIN(Producción!$C$2:$C$204))),1),"") -> 0
A11: ='Materias Primas'!$A11 -> TE-10 | B11: =IFERROR(VLOOKUP(Stock!$A11,Materias_Primas[#All],2,0),"") -> Bistrech 150 cm Ne | C11: =IFERROR(SUMIF(Consumo!$E$2:$E$2746,Stock!$B11,Consumo!$K$2:$K$2746),"") -> 0 | D11: =SUMIFS(Compras!$H$11:$H$155,Compras!$G$11:$G$155,Stock!$B11,Compras!$C$11:$C$155,"Ajust Inv") -> 0 | E11: =SUMIFS(Compras!$H$2:$H$155,Compras!$G$2:$G$155,Stock!$B11,Compras!$C$2:$C$155,"Compra") -> 0 | F11: =Stock!$E11-Stock!$C11-Stock!$D11 -> 0 | G11: =IFERROR(VLOOKUP(Stock!$A11,Materias_Primas[#All],5,0),"") -> Mts | H11: =IFERROR(ROUND(VLOOKUP(Stock!$A11,Materias_Primas[#All],7,0)*Stock!$F11,0),"") -> 0 | I11: =IFERROR(ROUND(Stock!$F11/(Stock!$C11/(TODAY()-MIN(Producción!$C$2:$C$204))),1),"")
A12: ='Materias Primas'!$A12 -> TE-11 | B12: =IFERROR(VLOOKUP(Stock!$A12,Materias_Primas[#All],2,0),"") -> Bistrech 300 cm Ne | C12: =IFERROR(SUMIF(Consumo!$E$2:$E$2746,Stock!$B12,Consumo!$K$2:$K$2746),"") -> 0 | D12: =SUMIFS(Compras!$H$11:$H$155,Compras!$G$11:$G$155,Stock!$B12,Compras!$C$11:$C$155,"Ajust Inv") -> 0 | E12: =SUMIFS(Compras!$H$2:$H$155,Compras!$G$2:$G$155,Stock!$B12,Compras!$C$2:$C$155,"Compra") -> 0 | F12: =Stock!$E12-Stock!$C12-Stock!$D12 -> 0 | G12: =IFERROR(VLOOKUP(Stock!$A12,Materias_Primas[#All],5,0),"") -> Mts | H12: =IFERROR(ROUND(VLOOKUP(Stock!$A12,Materias_Primas[#All],7,0)*Stock!$F12,0),"") -> 0 | I12: =IFERROR(ROUND(Stock!$F12/(Stock!$C12/(TODAY()-MIN(Producción!$C$2:$C$204))),1),"")
A13: ='Materias Primas'!$A13 -> TE-12 | B13: =IFERROR(VLOOKUP(Stock!$A13,Materias_Primas[#All],2,0),"") -> Mantel Spandex 180 Ne | C13: =IFERROR(SUMIF(Consumo!$E$2:$E$2746,Stock!$B13,Consumo!$K$2:$K$2746),"") -> 0 | D13: =SUMIFS(Compras!$H$11:$H$155,Compras!$G$11:$G$155,Stock!$B13,Compras!$C$11:$C$155,"Ajust Inv") -> 0 | E13: =SUMIFS(Compras!$H$2:$H$155,Compras!$G$2:$G$155,Stock!$B13,Compras!$C$2:$C$155,"Compra") -> 0 | F13: =Stock!$E13-Stock!$C13-Stock!$D13 -> 0 | G13: =IFERROR(VLOOKUP(Stock!$A13,Materias_Primas[#All],5,0),"") -> Uni | H13: =IFERROR(ROUND(VLOOKUP(Stock!$A13,Materias_Primas[#All],7,0)*Stock!$F13,0),"") -> 0 | I13: =IFERROR(ROUND(Stock!$F13/(Stock!$C13/(TODAY()-MIN(Producción!$C$2:$C$204))),1),"")
A14: ='Materias Primas'!$A15 -> TE-14 | B14: =IFERROR(VLOOKUP(Stock!$A14,Materias_Primas[#All],2,0),"") -> Granite | C14: =IFERROR(SUMIF(Consumo!$E$2:$E$2746,Stock!$B14,Consumo!$K$2:$K$2746),"") -> 0 | D14: =SUMIFS(Compras!$H$11:$H$155,Compras!$G$11:$G$155,Stock!$B14,Compras!$C$11:$C$155,"Ajust Inv") -> 0 | E14: =SUMIFS(Compras!$H$2:$H$155,Compras!$G$2:$G$155,Stock!$B14,Compras!$C$2:$C$155,"Compra") -> 0 | F14: =Stock!$E14-Stock!$C14-Stock!$D14 -> 0 | G14: =IFERROR(VLOOKUP(Stock!$A14,Materias_Primas[#All],5,0),"") -> Mts | H14: =IFERROR(ROUND(VLOOKUP(Stock!$A14,Materias_Primas[#All],7,0)*Stock!$F14,0),"") -> 0 | I14: =IFERROR(ROUND(Stock!$F14/(Stock!$C14/(TODAY()-MIN(Producción!$C$2:$C$204))),1),"")
A15: ='Materias Primas'!$A16 -> TE-15 | B15: =IFERROR(VLOOKUP(Stock!$A15,Materias_Primas[#All],2,0),"") -> Bistrech 150 cm Ve | C15: =IFERROR(SUMIF(Consumo!$E$2:$E$2746,Stock!$B15,Consumo!$K$2:$K$2746),"") -> 0 | D15: =SUMIFS(Compras!$H$11:$H$155,Compras!$G$11:$G$155,Stock!$B15,Compras!$C$11:$C$155,"Ajust Inv") -> 0 | E15: =SUMIFS(Compras!$H$2:$H$155,Compras!$G$2:$G$155,Stock!$B15,Compras!$C$2:$C$155,"Compra") -> 0 | F15: =Stock!$E15-Stock!$C15-Stock!$D15 -> 0 | G15: =IFERROR(VLOOKUP(Stock!$A15,Materias_Primas[#All],5,0),"") -> Mts | H15: =IFERROR(ROUND(VLOOKUP(Stock!$A15,Materias_Primas[#All],7,0)*Stock!$F15,0),"") -> 0 | I15: =IFERROR(ROUND(Stock!$F15/(Stock!$C15/(TODAY()-MIN(Producción!$C$2:$C$204))),1),"")
A16: ='Materias Primas'!$A17 -> TE-16 | B16: =IFERROR(VLOOKUP(Stock!$A16,Materias_Primas[#All],2,0),"") -> Gabardina 150 cm Ne | C16: =IFERROR(SUMIF(Consumo!$E$2:$E$2746,Stock!$B16,Consumo!$K$2:$K$2746),"") -> 0 | D16: =SUMIFS(Compras!$H$11:$H$155,Compras!$G$11:$G$155,Stock!$B16,Compras!$C$11:$C$155,"Ajust Inv") -> 0 | E16: =SUMIFS(Compras!$H$2:$H$155,Compras!$G$2:$G$155,Stock!$B16,Compras!$C$2:$C$155,"Compra") -> 0 | F16: =Stock!$E16-Stock!$C16-Stock!$D16 -> 0 | G16: =IFERROR(VLOOKUP(Stock!$A16,Materias_Primas[#All],5,0),"") -> Mts | H16: =IFERROR(ROUND(VLOOKUP(Stock!$A16,Materias_Primas[#All],7,0)*Stock!$F16,0),"") -> 0 | I16: =IFERROR(ROUND(Stock!$F16/(Stock!$C16/(TODAY()-MIN(Producción!$C$2:$C$204))),1),"")
A17: ='Materias Primas'!$A18 -> MO-01 | B17: =IFERROR(VLOOKUP(Stock!$A17,Materias_Primas[#All],2,0),"") -> Corte | C17: =IFERROR(SUMIF(Consumo!$E$2:$E$2746,Stock!$B17,Consumo!$K$2:$K$2746),"") -> 250 | D17: =SUMIFS(Compras!$H$11:$H$155,Compras!$G$11:$G$155,Stock!$B17,Compras!$C$11:$C$155,"Ajust Inv") -> 0 | E17: =SUMIFS(Compras!$H$2:$H$155,Compras!$G$2:$G$155,Stock!$B17,Compras!$C$2:$C$155,"Compra") -> 0 | F17: =Stock!$E17-Stock!$C17-Stock!$D17 -> -250 | G17: =IFERROR(VLOOKUP(Stock!$A17,Materias_Primas[#All],5,0),"") -> Min | H17: =IFERROR(ROUND(VLOOKUP(Stock!$A17,Materias_Primas[#All],7,0)*Stock!$F17,0),"") -> -2500 | I17: =IFERROR(ROUND(Stock!$F17/(Stock!$C17/(TODAY()-MIN(Producción!$C$2:$C$204))),1),"") -> -136
A18: ='Materias Primas'!$A19 -> MO-02 | B18: =IFERROR(VLOOKUP(Stock!$A18,Materias_Primas[#All],2,0),"") -> Confección | C18: =IFERROR(SUMIF(Consumo!$E$2:$E$2746,Stock!$B18,Consumo!$K$2:$K$2746),"") -> 866 | D18: =SUMIFS(Compras!$H$11:$H$155,Compras!$G$11:$G$155,Stock!$B18,Compras!$C$11:$C$155,"Ajust Inv") -> 0 | E18: =SUMIFS(Compras!$H$2:$H$155,Compras!$G$2:$G$155,Stock!$B18,Compras!$C$2:$C$155,"Compra") -> 0 | F18: =Stock!$E18-Stock!$C18-Stock!$D18 -> -866 | G18: =IFERROR(VLOOKUP(Stock!$A18,Materias_Primas[#All],5,0),"") -> Min | H18: =IFERROR(ROUND(VLOOKUP(Stock!$A18,Materias_Primas[#All],7,0)*Stock!$F18,0),"") -> -8660 | I18: =IFERROR(ROUND(Stock!$F18/(Stock!$C18/(TODAY()-MIN(Producción!$C$2:$C$204))),1),"") -> -136
A19: ='Materias Primas'!$A20 -> MO-03 | B19: =IFERROR(VLOOKUP(Stock!$A19,Materias_Primas[#All],2,0),"") -> Botones | C19: =IFERROR(SUMIF(Consumo!$E$2:$E$2746,Stock!$B19,Consumo!$K$2:$K$2746),"") -> 204 | D19: =SUMIFS(Compras!$H$11:$H$155,Compras!$G$11:$G$155,Stock!$B19,Compras!$C$11:$C$155,"Ajust Inv") -> 0 | E19: =SUMIFS(Compras!$H$2:$H$155,Compras!$G$2:$G$155,Stock!$B19,Compras!$C$2:$C$155,"Compra") -> 0 | F19: =Stock!$E19-Stock!$C19-Stock!$D19 -> -204 | G19: =IFERROR(VLOOKUP(Stock!$A19,Materias_Primas[#All],5,0),"") -> Min | H19: =IFERROR(ROUND(VLOOKUP(Stock!$A19,Materias_Primas[#All],7,0)*Stock!$F19,0),"") -> -371280 | I19: =IFERROR(ROUND(Stock!$F19/(Stock!$C19/(TODAY()-MIN(Producción!$C$2:$C$204))),1),"") -> -136
A20: ='Materias Primas'!$A21 -> HI-01 | B20: =IFERROR(VLOOKUP(Stock!$A20,Materias_Primas[#All],2,0),"") -> Hilo Overlock Verde | C20: =IFERROR(SUMIF(Consumo!$E$2:$E$2746,Stock!$B20,Consumo!$K$2:$K$2746),"") -> 2.06 | D20: =SUMIFS(Compras!$H$11:$H$155,Compras!$G$11:$G$155,Stock!$B20,Compras!$C$11:$C$155,"Ajust Inv") -> 0 | E20: =SUMIFS(Compras!$H$2:$H$155,Compras!$G$2:$G$155,Stock!$B20,Compras!$C$2:$C$155,"Compra") -> 0 | F20: =Stock!$E20-Stock!$C20-Stock!$D20 -> -2.06 | G20: =IFERROR(VLOOKUP(Stock!$A20,Materias_Primas[#All],5,0),"") -> Uni | H20: =IFERROR(ROUND(VLOOKUP(Stock!$A20,Materias_Primas[#All],7,0)*Stock!$F20,0),"") -> -426 | I20: =IFERROR(ROUND(Stock!$F20/(Stock!$C20/(TODAY()-MIN(Producción!$C$2:$C$204))),1),"") -> -136
A21: ='Materias Primas'!$A22 -> HI-02 | B21: =IFERROR(VLOOKUP(Stock!$A21,Materias_Primas[#All],2,0),"") -> Hilo Recta Verde | C21: =IFERROR(SUMIF(Consumo!$E$2:$E$2746,Stock!$B21,Consumo!$K$2:$K$2746),"") -> 1.1225 | D21: =SUMIFS(Compras!$H$11:$H$155,Compras!$G$11:$G$155,Stock!$B21,Compras!$C$11:$C$155,"Ajust Inv") -> 0 | E21: =SUMIFS(Compras!$H$2:$H$155,Compras!$G$2:$G$155,Stock!$B21,Compras!$C$2:$C$155,"Compra") -> 0 | F21: =Stock!$E21-Stock!$C21-Stock!$D21 -> -1.1225 | G21: =IFERROR(VLOOKUP(Stock!$A21,Materias_Primas[#All],5,0),"") -> Uni | H21: =IFERROR(ROUND(VLOOKUP(Stock!$A21,Materias_Primas[#All],7,0)*Stock!$F21,0),"") -> -159 | I21: =IFERROR(ROUND(Stock!$F21/(Stock!$C21/(TODAY()-MIN(Producción!$C$2:$C$204))),1),"") -> -136
A22: ='Materias Primas'!$A23 -> MO-04 | B22: =IFERROR(VLOOKUP(Stock!$A22,Materias_Primas[#All],2,0),"") -> Preparación | C22: =IFERROR(SUMIF(Consumo!$E$2:$E$2746,Stock!$B22,Consumo!$K$2:$K$2746),"") -> 70 | D22: =SUMIFS(Compras!$H$11:$H$155,Compras!$G$11:$G$155,Stock!$B22,Compras!$C$11:$C$155,"Ajust Inv") -> 0 | E22: =SUMIFS(Compras!$H$2:$H$155,Compras!$G$2:$G$155,Stock!$B22,Compras!$C$2:$C$155,"Compra") -> 0 | F22: =Stock!$E22-Stock!$C22-Stock!$D22 -> -70 | G22: =IFERROR(VLOOKUP(Stock!$A22,Materias_Primas[#All],5,0),"") -> Min | H22: =IFERROR(ROUND(VLOOKUP(Stock!$A22,Materias_Primas[#All],7,0)*Stock!$F22,0),"") -> -700 | I22: =IFERROR(ROUND(Stock!$F22/(Stock!$C22/(TODAY()-MIN(Producción!$C$2:$C$204))),1),"") -> -136
A23: ='Materias Primas'!$A24 -> SE-01 | B23: =IFERROR(VLOOKUP(Stock!$A23,Materias_Primas[#All],2,0),"") -> Estampado Logo Turb. | C23: =IFERROR(SUMIF(Consumo!$E$2:$E$2746,Stock!$B23,Consumo!$K$2:$K$2746),"") -> 68 | D23: =SUMIFS(Compras!$H$11:$H$155,Compras!$G$11:$G$155,Stock!$B23,Compras!$C$11:$C$155,"Ajust Inv") -> 0 | E23: =SUMIFS(Compras!$H$2:$H$155,Compras!$G$2:$G$155,Stock!$B23,Compras!$C$2:$C$155,"Compra") -> 1333 | F23: =Stock!$E23-Stock!$C23-Stock!$D23 -> 1265 | G23: =IFERROR(VLOOKUP(Stock!$A23,Materias_Primas[#All],5,0),"") -> Uni | H23: =IFERROR(ROUND(VLOOKUP(Stock!$A23,Materias_Primas[#All],7,0)*Stock!$F23,0),"") -> 131560 | I23: =IFERROR(ROUND(Stock!$F23/(Stock!$C23/(TODAY()-MIN(Producción!$C$2:$C$204))),1),"") -> 2530
A24: ='Materias Primas'!$A25 -> MO-05 | B24: =IFERROR(VLOOKUP(Stock!$A24,Materias_Primas[#All],2,0),"") -> Planchado | C24: =IFERROR(SUMIF(Consumo!$E$2:$E$2746,Stock!$B24,Consumo!$K$2:$K$2746),"") -> 0 | D24: =SUMIFS(Compras!$H$11:$H$155,Compras!$G$11:$G$155,Stock!$B24,Compras!$C$11:$C$155,"Ajust Inv") -> 0 | E24: =SUMIFS(Compras!$H$2:$H$155,Compras!$G$2:$G$155,Stock!$B24,Compras!$C$2:$C$155,"Compra") -> 0 | F24: =Stock!$E24-Stock!$C24-Stock!$D24 -> 0 | G24: =IFERROR(VLOOKUP(Stock!$A24,Materias_Primas[#All],5,0),"") -> Min | H24: =IFERROR(ROUND(VLOOKUP(Stock!$A24,Materias_Primas[#All],7,0)*Stock!$F24,0),"") -> 0 | I24: =IFERROR(ROUND(Stock!$F24/(Stock!$C24/(TODAY()-MIN(Producción!$C$2:$C$204))),1),"")
A25: ='Materias Primas'!$A26 -> IN-03 | B25: =IFERROR(VLOOKUP(Stock!$A25,Materias_Primas[#All],2,0),"") -> Sesgo | C25: =IFERROR(SUMIF(Consumo!$E$2:$E$2746,Stock!$B25,Consumo!$K$2:$K$2746),"") -> 2.08 | D25: =SUMIFS(Compras!$H$11:$H$155,Compras!$G$11:$G$155,Stock!$B25,Compras!$C$11:$C$155,"Ajust Inv") -> 0 | E25: =SUMIFS(Compras!$H$2:$H$155,Compras!$G$2:$G$155,Stock!$B25,Compras!$C$2:$C$155,"Compra") -> 0 | F25: =Stock!$E25-Stock!$C25-Stock!$D25 -> -2.08 | G25: =IFERROR(VLOOKUP(Stock!$A25,Materias_Primas[#All],5,0),"") -> Mts | H25: =IFERROR(ROUND(VLOOKUP(Stock!$A25,Materias_Primas[#All],7,0)*Stock!$F25,0),"") -> -597 | I25: =IFERROR(ROUND(Stock!$F25/(Stock!$C25/(TODAY()-MIN(Producción!$C$2:$C$204))),1),"") -> -136
... A57: ='Materias Primas'!$A58 -> 0 | B57: =IFERROR(VLOOKUP(Stock!$A57,Materias_Primas[#All],2,0),"") | C57: =IFERROR(SUMIF(Consumo!$E$2:$E$2746,Stock!$B57,Consumo!$K$2:$K$2746),"") | D57: =SUMIFS(Compras!$H$11:$H$155,Compras!$G$11:$G$155,Stock!$B57,Compras!$C$11:$C$155,"Ajust Inv") -> 0 | E57: =SUMIFS(Compras!$H$2:$H$155,Compras!$G$2:$G$155,Stock!$B57,Compras!$C$2:$C$155,"Compra") -> 0 | F57: =Stock!$E57-Stock!$C57-Stock!$D57 -> #VALUE! | G57: =IFERROR(VLOOKUP(Stock!$A57,Materias_Primas[#All],5,0),"") | H57: =IFERROR(ROUND(VLOOKUP(Stock!$A57,Materias_Primas[#All],7,0)*Stock!$F57,0),"") | I57: =IFERROR(ROUND(Stock!$F57/(Stock!$C57/(TODAY()-MIN(Producción!$C$2:$C$204))),1),"")
A58: Total | F58: =SUM(Stock[Stock]) -> #VALUE! | H58: =SUM(Stock[Costo]) -> -373228 | I58: =SUM(Stock[Pron Com]) -> 4566

Sheet Compras
A1: ID | B1: Fecha | C1: Tipo | D1: Proveedor | E1: Ítem | F1: MP | G1: Nombre | H1: Cantidad | I1: Unidad | J1: Cant Ref | K1: CU Base | L1: CU Ref | M1: Costo Ref | N1: Total | O1: IVA | P1: Neto | Q1: Forma de Pgo
A2: 0 | C2: Compra | D2: Pasajito Import. Calesa | E2: 1 | F2: TE-01 | G2: =IFERROR(VLOOKUP(Compras!$F2,'Materias Primas'!$A$1:$J$59,2,0),"") -> Microfibra Dep 160 Na | H2: 5.2 | I2: =IFERROR(VLOOKUP(Compras!$F2,'Materias Primas'!$A$1:$J$59,5,0),"") -> Mts | J2: =VLOOKUP(Compras!$F2,'Materias Primas'!$A$1:$J$59,3,0) -> MP | K2: =IFERROR(VLOOKUP(Compras!$F2,'Materias Primas'!$A$1:$J$59,7,0),"") -> 782 | L2: =IFERROR(Compras!$M2/Compras!$J2,"") | M2: =IFERROR(Compras!$J2*Compras!$N2/Compras!$H2,"") | N2: =4900*H2 -> 25480 | O2: =ROUND(N2*19/119,0) -> 4068 | P2: =N2-O2 -> 21412
A3: 0 | C3: Compra | D3: Pasajito Import. Calesa | E3: 2 | F3: TE-02 | G3: =IFERROR(VLOOKUP(Compras!$F3,'Materias Primas'!$A$1:$J$59,2,0),"") -> Microfibra Dep 160 Li | H3: 0.1 | I3: =IFERROR(VLOOKUP(Compras!$F3,'Materias Primas'!$A$1:$J$59,5,0),"") -> Mts | J3: =VLOOKUP(Compras!$F3,'Materias Primas'!$A$1:$J$59,3,0) -> MP | K3: =IFERROR(VLOOKUP(Compras!$F3,'Materias Primas'!$A$1:$J$59,7,0),"") -> 782 | L3: =IFERROR(Compras!$M3/Compras!$J3,"") | M3: =IFERROR(Compras!$J3*Compras!$N3/Compras!$H3,"") | N3: =4900*H3 -> 490 | O3: =ROUND(N3*19/119,0) -> 78 | P3: =N3-O3 -> 412
A4: 0 | C4: Compra | D4: Pasajito Import. Calesa | E4: 3 | F4: TE-03 | G4: =IFERROR(VLOOKUP(Compras!$F4,'Materias Primas'!$A$1:$J$59,2,0),"") -> Microfibra Dep 160 Fu | H4: 2.9 | I4: =IFERROR(VLOOKUP(Compras!$F4,'Materias Primas'!$A$1:$J$59,5,0),"") -> Mts | J4: =VLOOKUP(Compras!$F4,'Materias Primas'!$A$1:$J$59,3,0) -> MP | K4: =IFERROR(VLOOKUP(Compras!$F4,'Materias Primas'!$A$1:$J$59,7,0),"") -> 782 | L4: =IFERROR(Compras!$M4/Compras!$J4,"") | M4: =IFERROR(Compras!$J4*Compras!$N4/Compras!$H4,"") | N4: =4900*H4 -> 14210 | O4: =ROUND(N4*19/119,0) -> 2269 | P4: =N4-O4 -> 11941
A5: 0 | C5: Compra | D5: Pasajito Import. Calesa | E5: 4 | F5: TE-04 | G5: =IFERROR(VLOOKUP(Compras!$F5,'Materias Primas'!$A$1:$J$59,2,0),"") -> Microfibra Dep 160 Ca | H5: 2.9 | I5: =IFERROR(VLOOKUP(Compras!$F5,'Materias Primas'!$A$1:$J$59,5,0),"") -> Mts | J5: =VLOOKUP(Compras!$F5,'Materias Primas'!$A$1:$J$59,3,0) -> MP | K5: =IFERROR(VLOOKUP(Compras!$F5,'Materias Primas'!$A$1:$J$59,7,0),"") -> 782 | L5: =IFERROR(Compras!$M5/Compras!$J5,"") | M5: =IFERROR(Compras!$J5*Compras!$N5/Compras!$H5,"") | N5: =4900*H5 -> 14210 | O5: =ROUND(N5*19/119,0) -> 2269 | P5: =N5-O5 -> 11941
A6: 0 | C6: Compra | D6: Pasajito Import. Calesa | E6: 5 | F6: TE-05 | G6: =IFERROR(VLOOKUP(Compras!$F6,'Materias Primas'!$A$1:$J$59,2,0),"") -> Microfibra Dep 160 Ne | H6: 0.8 | I6: =IFERROR(VLOOKUP(Compras!$F6,'Materias Primas'!$A$1:$J$59,5,0),"") -> Mts | J6: =VLOOKUP(Compras!$F6,'Materias Primas'!$A$1:$J$59,3,0) -> MP | K6: =IFERROR(VLOOKUP(Compras!$F6,'Materias Primas'!$A$1:$J$59,7,0),"") -> 782 | L6: =IFERROR(Compras!$M6/Compras!$J6,"") | M6: =IFERROR(Compras!$J6*Compras!$N6/Compras!$H6,"") | N6: =4900*H6 -> 3920 | O6: =ROUND(N6*19/119,0) -> 626 | P6: =N6-O6 -> 3294
A7: 0 | C7: Compra | D7: Pasajito Import. Calesa | E7: 6 | F7: TE-06 | G7: =IFERROR(VLOOKUP(Compras!$F7,'Materias Primas'!$A$1:$J$59,2,0),"") -> Microfibra Dep 160 Am | H7: 1.6 | I7: =IFERROR(VLOOKUP(Compras!$F7,'Materias Primas'!$A$1:$J$59,5,0),"") -> Mts | J7: =VLOOKUP(Compras!$F7,'Materias Primas'!$A$1:$J$59,3,0) -> MP | K7: =IFERROR(VLOOKUP(Compras!$F7,'Materias Primas'!$A$1:$J$59,7,0),"") -> 782 | L7: =IFERROR(Compras!$M7/Compras!$J7,"") | M7: =IFERROR(Compras!$J7*Compras!$N7/Compras!$H7,"") | N7: =4900*H7 -> 7840 | O7: =ROUND(N7*19/119,0) -> 1252 | P7: =N7-O7 -> 6588
A8: 0 | C8: Compra | D8: Pasajito Import. Calesa | E8: 7 | F8: TE-07 | G8: =IFERROR(VLOOKUP(Compras!$F8,'Materias Primas'!$A$1:$J$59,2,0),"") -> Microfibra Dep 160 Ro | H8: 1.6 | I8: =IFERROR(VLOOKUP(Compras!$F8,'Materias Primas'!$A$1:$J$59,5,0),"") -> Mts | J8: =VLOOKUP(Compras!$F8,'Materias Primas'!$A$1:$J$59,3,0) -> MP | K8: =IFERROR(VLOOKUP(Compras!$F8,'Materias Primas'!$A$1:$J$59,7,0),"") -> 782 | L8: =IFERROR(Compras!$M8/Compras!$J8,"") | M8: =IFERROR(Compras!$J8*Compras!$N8/Compras!$H8,"") | N8: =4900*H8 -> 7840 | O8: =ROUND(N8*19/119,0) -> 1252 | P8: =N8-O8 -> 6588
A9: 0 | C9: Compra | D9: Pasajito Import. Calesa | E9: 8 | F9: TE-08 | G9: =IFERROR(VLOOKUP(Compras!$F9,'Materias Primas'!$A$1:$J$59,2,0),"") -> Microfibra Dep 160 Vp | H9: 0.8 | I9: =IFERROR(VLOOKUP(Compras!$F9,'Materias Primas'!$A$1:$J$59,5,0),"") -> Mts | J9: =VLOOKUP(Compras!$F9,'Materias Primas'!$A$1:$J$59,3,0) -> MP | K9: =IFERROR(VLOOKUP(Compras!$F9,'Materias Primas'!$A$1:$J$59,7,0),"") -> 782 | L9: =IFERROR(Compras!$M9/Compras!$J9,"") | M9: =IFERROR(Compras!$J9*Compras!$N9/Compras!$H9,"") | N9: =4900*H9 -> 3920 | O9: =ROUND(N9*19/119,0) -> 626 | P9: =N9-O9 -> 3294
A10: 0 | C10: Compra | D10: Pasajito Import. Calesa | E10: 9 | F10: TE-09 | G10: =IFERROR(VLOOKUP(Compras!$F10,'Materias Primas'!$A$1:$J$59,2,0),"") -> Microfibra Dep 160 Az | H10: 1.6 | I10: =IFERROR(VLOOKUP(Compras!$F10,'Materias Primas'!$A$1:$J$59,5,0),"") -> Mts | J10: =VLOOKUP(Compras!$F10,'Materias Primas'!$A$1:$J$59,3,0) -> MP | K10: =IFERROR(VLOOKUP(Compras!$F10,'Materias Primas'!$A$1:$J$59,7,0),"") -> 782 | L10: =IFERROR(Compras!$M10/Compras!$J10,"") | M10: =IFERROR(Compras!$J10*Compras!$N10/Compras!$H10,"") | N10: =4900*H10 -> 7840 | O10: =ROUND(N10*19/119,0) -> 1252 | P10: =N10-O10 -> 6588
A11: 1 | B11: 45923 | C11: Compra | D11: Pasajito Import. Calesa | E11: 1 | F11: TE-02 | G11: =IFERROR(VLOOKUP(Compras!$F11,'Materias Primas'!$A$1:$J$59,2,0),"") -> Microfibra Dep 160 Li | H11: 2.4 | I11: =IFERROR(VLOOKUP(Compras!$F11,'Materias Primas'!$A$1:$J$59,5,0),"") -> Mts | J11: =VLOOKUP(Compras!$F11,'Materias Primas'!$A$1:$J$59,3,0) -> MP | K11: =IFERROR(VLOOKUP(Compras!$F11,'Materias Primas'!$A$1:$J$59,7,0),"") -> 782 | L11: =IFERROR(Compras!$M11/Compras!$J11,"") | M11: =IFERROR(Compras!$J11*Compras!$N11/Compras!$H11,"") | N11: 11767 | O11: =ROUND(N11*19/119,0) -> 1879 | P11: =N11-O11 -> 9888
A12: 1 | B12: 45923 | C12: Compra | D12: Pasajito Import. Calesa | E12: 2 | F12: TE-08 | G12: =IFERROR(VLOOKUP(Compras!$F12,'Materias Primas'!$A$1:$J$59,2,0),"") -> Microfibra Dep 160 Vp | H12: 1.3 | I12: =IFERROR(VLOOKUP(Compras!$F12,'Materias Primas'!$A$1:$J$59,5,0),"") -> Mts | J12: =VLOOKUP(Compras!$F12,'Materias Primas'!$A$1:$J$59,3,0) -> MP | K12: =IFERROR(VLOOKUP(Compras!$F12,'Materias Primas'!$A$1:$J$59,7,0),"") -> 782 | L12: =IFERROR(Compras!$M12/Compras!$J12,"") | M12: =IFERROR(Compras!$J12*Compras!$N12/Compras!$H12,"") | N12: 6374 | O12: =ROUND(N12*19/119,0) -> 1018 | P12: =N12-O12 -> 5356
A13: 2 | C13: Compra | D13: Pasajito Import. Calesa | E13: 1 | F13: TE-04 | G13: =IFERROR(VLOOKUP(Compras!$F13,'Materias Primas'!$A$1:$J$59,2,0),"") -> Microfibra Dep 160 Ca | H13: 1.3 | I13: =IFERROR(VLOOKUP(Compras!$F13,'Materias Primas'!$A$1:$J$59,5,0),"") -> Mts | J13: =VLOOKUP(Compras!$F13,'Materias Primas'!$A$1:$J$59,3,0) -> MP | K13: =IFERROR(VLOOKUP(Compras!$F13,'Materias Primas'!$A$1:$J$59,7,0),"") -> 782 | L13: =IFERROR(Compras!$M13/Compras!$J13,"") | M13: =IFERROR(Compras!$J13*Compras!$N13/Compras!$H13,"") | N13: 6374 | O13: =ROUND(N13*19/119,0) -> 1018 | P13: =N13-O13 -> 5356
A14: 2 | C14: Compra | D14: Pasajito Import. Calesa | E14: 2 | F14: TE-03 | G14: =IFERROR(VLOOKUP(Compras!$F14,'Materias Primas'!$A$1:$J$59,2,0),"") -> Microfibra Dep 160 Fu | H14: 1.3 | I14: =IFERROR(VLOOKUP(Compras!$F14,'Materias Primas'!$A$1:$J$59,5,0),"") -> Mts | J14: =VLOOKUP(Compras!$F14,'Materias Primas'!$A$1:$J$59,3,0) -> MP | K14: =IFERROR(VLOOKUP(Compras!$F14,'Materias Primas'!$A$1:$J$59,7,0),"") -> 782 | L14: =IFERROR(Compras!$M14/Compras!$J14,"") | M14: =IFERROR(Compras!$J14*Compras!$N14/Compras!$H14,"") | N14: 6374 | O14: =ROUND(N14*19/119,0) -> 1018 | P14: =N14-O14 -> 5356
A15: 2 | C15: Compra | D15: Pasajito Import. Calesa | E15: 3 | F15: TE-05 | G15: =IFERROR(VLOOKUP(Compras!$F15,'Materias Primas'!$A$1:$J$59,2,0),"") -> Microfibra Dep 160 Ne | H15: 1.3 | I15: =IFERROR(VLOOKUP(Compras!$F15,'Materias Primas'!$A$1:$J$59,5,0),"") -> Mts | J15: =VLOOKUP(Compras!$F15,'Materias Primas'!$A$1:$J$59,3,0) -> MP | K15: =IFERROR(VLOOKUP(Compras!$F15,'Materias Primas'!$A$1:$J$59,7,0),"") -> 782 | L15: =IFERROR(Compras!$M15/Compras!$J15,"") | M15: =IFERROR(Compras!$J15*Compras!$N15/Compras!$H15,"") | N15: 6374 | O15: =ROUND(N15*19/119,0) -> 1018 | P15: =N15-O15 -> 5356
A16: 2 | C16: Compra | D16: Pasajito Import. Calesa | E16: 4 | F16: TE-01 | G16: =IFERROR(VLOOKUP(Compras!$F16,'Materias Primas'!$A$1:$J$59,2,0),"") -> Microfibra Dep 160 Na | H16: 0.65 | I16: =IFERROR(VLOOKUP(Compras!$F16,'Materias Primas'!$A$1:$J$59,5,0),"") -> Mts | J16: =VLOOKUP(Compras!$F16,'Materias Primas'!$A$1:$J$59,3,0) -> MP | K16: =IFERROR(VLOOKUP(Compras!$F16,'Materias Primas'!$A$1:$J$59,7,0),"") -> 782 | L16: =IFERROR(Compras!$M16/Compras!$J16,"") | M16: =IFERROR(Compras!$J16*Compras!$N16/Compras!$H16,"") | N16: 3187 | O16: =ROUND(N16*19/119,0) -> 509 | P16: =N16-O16 -> 2678
A17: 2 | C17: Compra | D17: Pasajito Import. Calesa | E17: 5 | F17: TE-06 | G17: =IFERROR(VLOOKUP(Compras!$F17,'Materias Primas'!$A$1:$J$59,2,0),"") -> Microfibra Dep 160 Am | H17: 0.65 | I17: =IFERROR(VLOOKUP(Compras!$F17,'Materias Primas'!$A$1:$J$59,5,0),"") -> Mts | J17: =VLOOKUP(Compras!$F17,'Materias Primas'!$A$1:$J$59,3,0) -> MP | K17: =IFERROR(VLOOKUP(Compras!$F17,'Materias Primas'!$A$1:$J$59,7,0),"") -> 782 | L17: =IFERROR(Compras!$M17/Compras!$J17,"") | M17: =IFERROR(Compras!$J17*Compras!$N17/Compras!$H17,"") | N17: 3187 | O17: =ROUND(N17*19/119,0) -> 509 | P17: =N17-O17 -> 2678
A18: 2 | C18: Compra | D18: Pasajito Import. Calesa | E18: 6 | F18: TE-07 | G18: =IFERROR(VLOOKUP(Compras!$F18,'Materias Primas'!$A$1:$J$59,2,0),"") -> Microfibra Dep 160 Ro | H18: 0.65 | I18: =IFERROR(VLOOKUP(Compras!$F18,'Materias Primas'!$A$1:$J$59,5,0),"") -> Mts | J18: =VLOOKUP(Compras!$F18,'Materias Primas'!$A$1:$J$59,3,0) -> MP | K18: =IFERROR(VLOOKUP(Compras!$F18,'Materias Primas'!$A$1:$J$59,7,0),"") -> 782 | L18: =IFERROR(Compras!$M18/Compras!$J18,"") | M18: =IFERROR(Compras!$J18*Compras!$N18/Compras!$H18,"") | N18: 3187 | O18: =ROUND(N18*19/119,0) -> 509 | P18: =N18-O18 -> 2678
A19: 4 | B19: 45966 | C19: Compra | D19: Rainbown Publicidad | E19: 1 | F19: SE-01 | G19: =IFERROR(VLOOKUP(Compras!$F19,'Materias Primas'!$A$1:$J$59,2,0),"") -> Estampado Logo Turb. | H19: =21.5*36 -> 774 | I19: =IFERROR(VLOOKUP(Compras!$F19,'Materias Primas'!$A$1:$J$59,5,0),"") -> Uni | J19: =VLOOKUP(Compras!$F19,'Materias Primas'!$A$1:$J$59,3,0) -> SE | K19: =IFERROR(VLOOKUP(Compras!$F19,'Materias Primas'!$A$1:$J$59,7,0),"") -> 104 | L19: =IFERROR(Compras!$M19/Compras!$J19,"") | M19: =IFERROR(Compras!$J19*Compras!$N19/Compras!$H19,"") | N19: 27846 | O19: =ROUND(N19*19/119,0) -> 4446 | P19: =N19-O19 -> 23400 | Q19: T
A20: 3 | B20: 45926 | C20: Compra | D20: Rainbown Publicidad | E20: 1 | F20: SE-01 | G20: =IFERROR(VLOOKUP(Compras!$F20,'Materias Primas'!$A$1:$J$59,2,0),"") -> Estampado Logo Turb. | H20: =21.5*26 -> 559 | I20: =IFERROR(VLOOKUP(Compras!$F20,'Materias Primas'!$A$1:$J$59,5,0),"") -> Uni | J20: =VLOOKUP(Compras!$F20,'Materias Primas'!$A$1:$J$59,3,0) -> SE | K20: =IFERROR(VLOOKUP(Compras!$F20,'Materias Primas'!$A$1:$J$59,7,0),"") -> 104 | L20: =IFERROR(Compras!$M20/Compras!$J20,"") | M20: =IFERROR(Compras!$J20*Compras!$N20/Compras!$H20,"") | N20: 16900 | O20: =ROUND(N20*19/119,0) -> 2698 | P20: =N20-O20 -> 14202 | Q20: T
G21: =IFERROR(VLOOKUP(Compras!$F21,'Materias Primas'!$A$1:$J$59,2,0),"") | I21: =IFERROR(VLOOKUP(Compras!$F21,'Materias Primas'!$A$1:$J$59,5,0),"") | J21: =VLOOKUP(Compras!$F21,'Materias Primas'!$A$1:$J$59,3,0) -> #N/A | K21: =IFERROR(VLOOKUP(Compras!$F21,'Materias Primas'!$A$1:$J$59,7,0),"") | L21: =IFERROR(Compras!$M21/Compras!$J21,"") | M21: =IFERROR(Compras!$J21*Compras!$N21/Compras!$H21,"") | O21: =ROUND(N21*19/119,0) -> 0 | P21: =N21-O21 -> 0
G22: =IFERROR(VLOOKUP(Compras!$F22,'Materias Primas'!$A$1:$J$59,2,0),"") | I22: =IFERROR(VLOOKUP(Compras!$F22,'Materias Primas'!$A$1:$J$59,5,0),"") | J22: =VLOOKUP(Compras!$F22,'Materias Primas'!$A$1:$J$59,3,0) -> #N/A | K22: =IFERROR(VLOOKUP(Compras!$F22,'Materias Primas'!$A$1:$J$59,7,0),"") | L22: =IFERROR(Compras!$M22/Compras!$J22,"") | M22: =IFERROR(Compras!$J22*Compras!$N22/Compras!$H22,"") | O22: =ROUND(N22*19/119,0) -> 0 | P22: =N22-O22 -> 0
G23: =IFERROR(VLOOKUP(Compras!$F23,'Materias Primas'!$A$1:$J$59,2,0),"") | I23: =IFERROR(VLOOKUP(Compras!$F23,'Materias Primas'!$A$1:$J$59,5,0),"") | J23: =VLOOKUP(Compras!$F23,'Materias Primas'!$A$1:$J$59,3,0) -> #N/A | K23: =IFERROR(VLOOKUP(Compras!$F23,'Materias Primas'!$A$1:$J$59,7,0),"") | L23: =IFERROR(Compras!$M23/Compras!$J23,"") | M23: =IFERROR(Compras!$J23*Compras!$N23/Compras!$H23,"") | O23: =ROUND(N23*19/119,0) -> 0 | P23: =N23-O23 -> 0
G24: =IFERROR(VLOOKUP(Compras!$F24,'Materias Primas'!$A$1:$J$59,2,0),"") | I24: =IFERROR(VLOOKUP(Compras!$F24,'Materias Primas'!$A$1:$J$59,5,0),"") | J24: =VLOOKUP(Compras!$F24,'Materias Primas'!$A$1:$J$59,3,0) -> #N/A | K24: =IFERROR(VLOOKUP(Compras!$F24,'Materias Primas'!$A$1:$J$59,7,0),"") | L24: =IFERROR(Compras!$M24/Compras!$J24,"") | M24: =IFERROR(Compras!$J24*Compras!$N24/Compras!$H24,"") | O24: =ROUND(N24*19/119,0) -> 0 | P24: =N24-O24 -> 0
G25: =IFERROR(VLOOKUP(Compras!$F25,'Materias Primas'!$A$1:$J$59,2,0),"") | I25: =IFERROR(VLOOKUP(Compras!$F25,'Materias Primas'!$A$1:$J$59,5,0),"") | J25: =VLOOKUP(Compras!$F25,'Materias Primas'!$A$1:$J$59,3,0) -> #N/A | K25: =IFERROR(VLOOKUP(Compras!$F25,'Materias Primas'!$A$1:$J$59,7,0),"") | L25: =IFERROR(Compras!$M25/Compras!$J25,"") | M25: =IFERROR(Compras!$J25*Compras!$N25/Compras!$H25,"") | O25: =ROUND(N25*19/119,0) -> 0 | P25: =N25-O25 -> 0
G26: =IFERROR(VLOOKUP(Compras!$F26,'Materias Primas'!$A$1:$J$59,2,0),"") | I26: =IFERROR(VLOOKUP(Compras!$F26,'Materias Primas'!$A$1:$J$59,5,0),"") | J26: =VLOOKUP(Compras!$F26,'Materias Primas'!$A$1:$J$59,3,0) -> #N/A | K26: =IFERROR(VLOOKUP(Compras!$F26,'Materias Primas'!$A$1:$J$59,7,0),"") | L26: =IFERROR(Compras!$M26/Compras!$J26,"") | M26: =IFERROR(Compras!$J26*Compras!$N26/Compras!$H26,"") | O26: =ROUND(N26*19/119,0) -> 0 | P26: =N26-O26 -> 0
G27: =IFERROR(VLOOKUP(Compras!$F27,'Materias Primas'!$A$1:$J$59,2,0),"") | I27: =IFERROR(VLOOKUP(Compras!$F27,'Materias Primas'!$A$1:$J$59,5,0),"") | J27: =VLOOKUP(Compras!$F27,'Materias Primas'!$A$1:$J$59,3,0) -> #N/A | K27: =IFERROR(VLOOKUP(Compras!$F27,'Materias Primas'!$A$1:$J$59,7,0),"") | L27: =IFERROR(Compras!$M27/Compras!$J27,"") | M27: =IFERROR(Compras!$J27*Compras!$N27/Compras!$H27,"") | O27: =ROUND(N27*19/119,0) -> 0 | P27: =N27-O27 -> 0
G28: =IFERROR(VLOOKUP(Compras!$F28,'Materias Primas'!$A$1:$J$59,2,0),"") | I28: =IFERROR(VLOOKUP(Compras!$F28,'Materias Primas'!$A$1:$J$59,5,0),"") | J28: =VLOOKUP(Compras!$F28,'Materias Primas'!$A$1:$J$59,3,0) -> #N/A | K28: =IFERROR(VLOOKUP(Compras!$F28,'Materias Primas'!$A$1:$J$59,7,0),"") | L28: =IFERROR(Compras!$M28/Compras!$J28,"") | M28: =IFERROR(Compras!$J28*Compras!$N28/Compras!$H28,"") | O28: =ROUND(N28*19/119,0) -> 0 | P28: =N28-O28 -> 0
G29: =IFERROR(VLOOKUP(Compras!$F29,'Materias Primas'!$A$1:$J$59,2,0),"") | I29: =IFERROR(VLOOKUP(Compras!$F29,'Materias Primas'!$A$1:$J$59,5,0),"") | J29: =VLOOKUP(Compras!$F29,'Materias Primas'!$A$1:$J$59,3,0) -> #N/A | K29: =IFERROR(VLOOKUP(Compras!$F29,'Materias Primas'!$A$1:$J$59,7,0),"") | L29: =IFERROR(Compras!$M29/Compras!$J29,"") | M29: =IFERROR(Compras!$J29*Compras!$N29/Compras!$H29,"") | O29: =ROUND(N29*19/119,0) -> 0 | P29: =N29-O29 -> 0
G30: =IFERROR(VLOOKUP(Compras!$F30,'Materias Primas'!$A$1:$J$59,2,0),"") | I30: =IFERROR(VLOOKUP(Compras!$F30,'Materias Primas'!$A$1:$J$59,5,0),"") | J30: =VLOOKUP(Compras!$F30,'Materias Primas'!$A$1:$J$59,3,0) -> #N/A | K30: =IFERROR(VLOOKUP(Compras!$F30,'Materias Primas'!$A$1:$J$59,7,0),"") | L30: =IFERROR(Compras!$M30/Compras!$J30,"") | M30: =IFERROR(Compras!$J30*Compras!$N30/Compras!$H30,"") | O30: =ROUND(N30*19/119,0) -> 0 | P30: =N30-O30 -> 0
G31: =IFERROR(VLOOKUP(Compras!$F31,'Materias Primas'!$A$1:$J$59,2,0),"") | I31: =IFERROR(VLOOKUP(Compras!$F31,'Materias Primas'!$A$1:$J$59,5,0),"") | J31: =VLOOKUP(Compras!$F31,'Materias Primas'!$A$1:$J$59,3,0) -> #N/A | K31: =IFERROR(VLOOKUP(Compras!$F31,'Materias Primas'!$A$1:$J$59,7,0),"") | L31: =IFERROR(Compras!$M31/Compras!$J31,"") | M31: =IFERROR(Compras!$J31*Compras!$N31/Compras!$H31,"") | O31: =ROUND(N31*19/119,0) -> 0 | P31: =N31-O31 -> 0
G32: =IFERROR(VLOOKUP(Compras!$F32,'Materias Primas'!$A$1:$J$59,2,0),"") | I32: =IFERROR(VLOOKUP(Compras!$F32,'Materias Primas'!$A$1:$J$59,5,0),"") | J32: =VLOOKUP(Compras!$F32,'Materias Primas'!$A$1:$J$59,3,0) -> #N/A | K32: =IFERROR(VLOOKUP(Compras!$F32,'Materias Primas'!$A$1:$J$59,7,0),"") | L32: =IFERROR(Compras!$M32/Compras!$J32,"") | M32: =IFERROR(Compras!$J32*Compras!$N32/Compras!$H32,"") | O32: =ROUND(N32*19/119,0) -> 0 | P32: =N32-O32 -> 0
... G155: =IFERROR(VLOOKUP(Compras!$F155,'Materias Primas'!$A$1:$J$59,2,0),"") | I155: =IFERROR(VLOOKUP(Compras!$F155,'Materias Primas'!$A$1:$J$59,5,0),"") | J155: =VLOOKUP(Compras!$F155,'Materias Primas'!$A$1:$J$59,3,0) -> #N/A | K155: =IFERROR(VLOOKUP(Compras!$F155,'Materias Primas'!$A$1:$J$59,7,0),"") | L155: =IFERROR(Compras!$M155/Compras!$J155,"") | M155: =IFERROR(Compras!$J155*Compras!$N155/Compras!$H155,"") | O155: =ROUND(N155*19/119,0) -> 0 | P155: =N155-O155 -> 0
N156: =SUBTOTAL(109,Compras!$N$11:$N$155) -> 91570 | O156: =SUBTOTAL(109,Compras!$O$11:$O$155) -> 14622 | P156: =SUBTOTAL(109,Compras!$P$11:$P$155) -> 76948

Sheet Hoja1
C5: ID | D5: 13 | E5: Feha | F5: 46125
C8: Ítem | D8: Producto | E8: Precio Unit | F8: Cantidad | G8: Sub Tot
C9: 1 | D9: Producto 1 | E9: 5000 | F9: 3 | G9: =E9*F9 -> 15000
C10: 2 | D10: Producto 3 | E10: 3500 | F10: 2 | G10: =E10*F10 -> 7000
C11: 3 | D11: Producto 5 | E11: 8700 | F11: 2 | G11: =E11*F11 -> 17400
C12: 4 | D12: Producto 8 | E12: 12500 | F12: 1 | G12: =E12*F12 -> 12500
C13: 5
C14: 6
C15: 7
C16: 8
C17: 9
C18: 10
F19: Neto | G19: =SUM(G9:G18) -> 51900
F20: IVA | G20: =G19*0.19 -> 9861
F21: Total | G21: =G19+G20 -> 61761

Sheet Producción
A1: ID | B1: Ítem | C1: Fecha | D1: Producto | E1: Nombre P | F1: Cant | G1: Costo M O | H1: C T M O | I1: PAG
A2: 1 | B2: 0 | C2: 45901 | D2: TO-01 | E2: =IFERROR(VLOOKUP(D2,Productos[#All],2,0),"") -> Toalla 160x80 Az | F2: 2 | G2: =SUMIFS(Receta[[#All],[CU]],Receta[[#All],[Código]],D2,Receta[[#All],[M P]],"MO*") -> 1820 | H2: =F2*G2 -> 3640 | I2: S
A3: 1 | B3: 0 | C3: 45901 | D3: TO-02 | E3: =IFERROR(VLOOKUP(D3,Productos[#All],2,0),"") -> Toalla 160x80 Ro | F3: 2 | G3: =SUMIFS(Receta[[#All],[CU]],Receta[[#All],[Código]],D3,Receta[[#All],[M P]],"MO*") -> 1820 | H3: =F3*G3 -> 3640 | I3: S
A4: 1 | B4: 0 | C4: 45901 | D4: TO-03 | E4: =IFERROR(VLOOKUP(D4,Productos[#All],2,0),"") -> Toalla 160x80 Am | F4: 2 | G4: =SUMIFS(Receta[[#All],[CU]],Receta[[#All],[Código]],D4,Receta[[#All],[M P]],"MO*") -> 1820 | H4: =F4*G4 -> 3640 | I4: S
A5: 1 | B5: 0 | C5: 45901 | D5: TO-04 | E5: =IFERROR(VLOOKUP(D5,Productos[#All],2,0),"") -> Toalla 160x80 Vp | F5: 1 | G5: =SUMIFS(Receta[[#All],[CU]],Receta[[#All],[Código]],D5,Receta[[#All],[M P]],"MO*") -> 1820 | H5: =F5*G5 -> 1820 | I5: S
A6: 1 | B6: 0 | C6: 45901 | D6: TO-05 | E6: =IFERROR(VLOOKUP(D6,Productos[#All],2,0),"") -> Toalla 160x80 Ca | F6: 2 | G6: =SUMIFS(Receta[[#All],[CU]],Receta[[#All],[Código]],D6,Receta[[#All],[M P]],"MO*") -> 1820 | H6: =F6*G6 -> 3640 | I6: S
A7: 1 | B7: 0 | C7: 45901 | D7: TO-06 | E7: =IFERROR(VLOOKUP(D7,Productos[#All],2,0),"") -> Toalla 160x80 Fu | F7: 2 | G7: =SUMIFS(Receta[[#All],[CU]],Receta[[#All],[Código]],D7,Receta[[#All],[M P]],"MO*") -> 1820 | H7: =F7*G7 -> 3640 | I7: S
A8: 1 | B8: 0 | C8: 45901 | D8: TO-07 | E8: =IFERROR(VLOOKUP(D8,Productos[#All],2,0),"") -> Toalla 160x80 Na | F8: 2 | G8: =SUMIFS(Receta[[#All],[CU]],Receta[[#All],[Código]],D8,Receta[[#All],[M P]],"MO*") -> 1820 | H8: =F8*G8 -> 3640 | I8: S
A9: 1 | B9: 0 | C9: 45901 | D9: TO-08 | E9: =IFERROR(VLOOKUP(D9,Productos[#All],2,0),"") -> Toalla 160x80 Ne | F9: 1 | G9: =SUMIFS(Receta[[#All],[CU]],Receta[[#All],[Código]],D9,Receta[[#All],[M P]],"MO*") -> 1820 | H9: =F9*G9 -> 1820 | I9: S
A10: 1 | B10: 0 | C10: 45901 | D10: TO-09 | E10: =IFERROR(VLOOKUP(D10,Productos[#All],2,0),"") -> Toalla 80x40 Na | F10: 1 | G10: =SUMIFS(Receta[[#All],[CU]],Receta[[#All],[Código]],D10,Receta[[#All],[M P]],"MO*") -> 975 | H10: =F10*G10 -> 975 | I10: S
A11: 1 | B11: 0 | C11: 45901 | D11: TO-10 | E11: =IFERROR(VLOOKUP(D11,Productos[#All],2,0),"") -> Toalla 40x40 Na | F11: 2 | G11: =SUMIFS(Receta[[#All],[CU]],Receta[[#All],[Código]],D11,Receta[[#All],[M P]],"MO*") -> 845 | H11: =F11*G11 -> 1690 | I11: S
A12: 1 | B12: 0 | C12: 45901 | D12: TO-11 | E12: =IFERROR(VLOOKUP(D12,Productos[#All],2,0),"") -> Toalla 160x110 Na | F12: 1 | G12: =SUMIFS(Receta[[#All],[CU]],Receta[[#All],[Código]],D12,Receta[[#All],[M P]],"MO*") -> 2535 | H12: =F12*G12 -> 2535 | I12: S
A13: 1 | B13: 0 | C13: 45901 | D13: TO-12 | E13: =IFERROR(VLOOKUP(D13,Productos[#All],2,0),"") -> Toalla 160x110 Li | F13: 1 | G13: =SUMIFS(Receta[[#All],[CU]],Receta[[#All],[Código]],D13,Receta[[#All],[M P]],"MO*") -> 0 | H13: =F13*G13 -> 0 | I13: S
... A24: 0 | B24: 2 | C24: 45958 | D24: TU-02 | E24: =IFERROR(VLOOKUP(D24,Productos[#All],2,0),"") -> Turbante Fu | F24: 8 | G24: =SUMIFS(Receta[[#All],[CU]],Receta[[#All],[Código]],D24,Receta[[#All],[M P]],"MO*") -> 715.5 | H24: =F24*G24 -> 5724 | I24: S
A25: 2 | E25: =IFERROR(VLOOKUP(D25,Productos[#All],2,0),"") | G25: =SUMIFS(Receta[[#All],[CU]],Receta[[#All],[Código]],D25,Receta[[#All],[M P]],"MO*") -> 0 | H25: =F25*G25 -> 0
A26: 2 | E26: =IFERROR(VLOOKUP(D26,Productos[#All],2,0),"") | G26: =SUMIFS(Receta[[#All],[CU]],Receta[[#All],[Código]],D26,Receta[[#All],[M P]],"MO*") -> 0 | H26: =F26*G26 -> 0
A27: 2 | E27: =IFERROR(VLOOKUP(D27,Productos[#All],2,0),"") | G27: =SUMIFS(Receta[[#All],[CU]],Receta[[#All],[Código]],D27,Receta[[#All],[M P]],"MO*") -> 0 | H27: =F27*G27 -> 0
A28: 2 | E28: =IFERROR(VLOOKUP(D28,Productos[#All],2,0),"") | G28: =SUMIFS(Receta[[#All],[CU]],Receta[[#All],[Código]],D28,Receta[[#All],[M P]],"MO*") -> 0 | H28: =F28*G28 -> 0
A29: 2 | E29: =IFERROR(VLOOKUP(D29,Productos[#All],2,0),"") | G29: =SUMIFS(Receta[[#All],[CU]],Receta[[#All],[Código]],D29,Receta[[#All],[M P]],"MO*") -> 0 | H29: =F29*G29 -> 0
A30: 2 | E30: =IFERROR(VLOOKUP(D30,Productos[#All],2,0),"") | G30: =SUMIFS(Receta[[#All],[CU]],Receta[[#All],[Código]],D30,Receta[[#All],[M P]],"MO*") -> 0 | H30: =F30*G30 -> 0
A31: 2 | E31: =IFERROR(VLOOKUP(D31,Productos[#All],2,0),"") | G31: =SUMIFS(Receta[[#All],[CU]],Receta[[#All],[Código]],D31,Receta[[#All],[M P]],"MO*") -> 0 | H31: =F31*G31 -> 0
A32: 2 | E32: =IFERROR(VLOOKUP(D32,Productos[#All],2,0),"") | G32: =SUMIFS(Receta[[#All],[CU]],Receta[[#All],[Código]],D32,Receta[[#All],[M P]],"MO*") -> 0 | H32: =F32*G32 -> 0
A33: 2 | E33: =IFERROR(VLOOKUP(D33,Productos[#All],2,0),"") | G33: =SUMIFS(Receta[[#All],[CU]],Receta[[#All],[Código]],D33,Receta[[#All],[M P]],"MO*") -> 0 | H33: =F33*G33 -> 0
A34: 2 | E34: =IFERROR(VLOOKUP(D34,Productos[#All],2,0),"") | G34: =SUMIFS(Receta[[#All],[CU]],Receta[[#All],[Código]],D34,Receta[[#All],[M P]],"MO*") -> 0 | H34: =F34*G34 -> 0
A35: 2 | E35: =IFERROR(VLOOKUP(D35,Productos[#All],2,0),"") | G35: =SUMIFS(Receta[[#All],[CU]],Receta[[#All],[Código]],D35,Receta[[#All],[M P]],"MO*") -> 0 | H35: =F35*G35 -> 0
A36: 2 | E36: =IFERROR(VLOOKUP(D36,Productos[#All],2,0),"") | G36: =SUMIFS(Receta[[#All],[CU]],Receta[[#All],[Código]],D36,Receta[[#All],[M P]],"MO*") -> 0 | H36: =F36*G36 -> 0
... A54: 4 | E54: =IFERROR(VLOOKUP(D54,Productos[#All],2,0),"") | G54: =SUMIFS(Receta[[#All],[CU]],Receta[[#All],[Código]],D54,Receta[[#All],[M P]],"MO*") -> 0 | H54: =F54*G54 -> 0
A55: 4 | E55: =IFERROR(VLOOKUP(D55,Productos[#All],2,0),"") | G55: =SUMIFS(Receta[[#All],[CU]],Receta[[#All],[Código]],D55,Receta[[#All],[M P]],"MO*") -> 0 | H55: =F55*G55 -> 0 | I55: S
A56: 4 | E56: =IFERROR(VLOOKUP(D56,Productos[#All],2,0),"") | G56: =SUMIFS(Receta[[#All],[CU]],Receta[[#All],[Código]],D56,Receta[[#All],[M P]],"MO*") -> 0 | H56: =F56*G56 -> 0
A57: 4 | E57: =IFERROR(VLOOKUP(D57,Productos[#All],2,0),"") | G57: =SUMIFS(Receta[[#All],[CU]],Receta[[#All],[Código]],D57,Receta[[#All],[M P]],"MO*") -> 0 | H57: =F57*G57 -> 0
A58: 4 | E58: =IFERROR(VLOOKUP(D58,Productos[#All],2,0),"") | G58: =SUMIFS(Receta[[#All],[CU]],Receta[[#All],[Código]],D58,Receta[[#All],[M P]],"MO*") -> 0 | H58: =F58*G58 -> 0
A59: 4 | E59: =IFERROR(VLOOKUP(D59,Productos[#All],2,0),"") | G59: =SUMIFS(Receta[[#All],[CU]],Receta[[#All],[Código]],D59,Receta[[#All],[M P]],"MO*") -> 0 | H59: =F59*G59 -> 0
A60: 4 | E60: =IFERROR(VLOOKUP(D60,Productos[#All],2,0),"") | G60: =SUMIFS(Receta[[#All],[CU]],Receta[[#All],[Código]],D60,Receta[[#All],[M P]],"MO*") -> 0 | H60: =F60*G60 -> 0
A61: 4 | E61: =IFERROR(VLOOKUP(D61,Productos[#All],2,0),"") | G61: =SUMIFS(Receta[[#All],[CU]],Receta[[#All],[Código]],D61,Receta[[#All],[M P]],"MO*") -> 0 | H61: =F61*G61 -> 0
A62: 4 | E62: =IFERROR(VLOOKUP(D62,Productos[#All],2,0),"") | G62: =SUMIFS(Receta[[#All],[CU]],Receta[[#All],[Código]],D62,Receta[[#All],[M P]],"MO*") -> 0 | H62: =F62*G62 -> 0
A63: 4 | E63: =IFERROR(VLOOKUP(D63,Productos[#All],2,0),"") | G63: =SUMIFS(Receta[[#All],[CU]],Receta[[#All],[Código]],D63,Receta[[#All],[M P]],"MO*") -> 0 | H63: =F63*G63 -> 0
A64: 4 | E64: =IFERROR(VLOOKUP(D64,Productos[#All],2,0),"") | G64: =SUMIFS(Receta[[#All],[CU]],Receta[[#All],[Código]],D64,Receta[[#All],[M P]],"MO*") -> 0 | H64: =F64*G64 -> 0
A65: 4 | E65: =IFERROR(VLOOKUP(D65,Productos[#All],2,0),"") | G65: =SUMIFS(Receta[[#All],[CU]],Receta[[#All],[Código]],D65,Receta[[#All],[M P]],"MO*") -> 0 | H65: =F65*G65 -> 0
A66: 4 | E66: =IFERROR(VLOOKUP(D66,Productos[#All],2,0),"") | G66: =SUMIFS(Receta[[#All],[CU]],Receta[[#All],[Código]],D66,Receta[[#All],[M P]],"MO*") -> 0 | H66: =F66*G66 -> 0
A67: 4 | E67: =IFERROR(VLOOKUP(D67,Productos[#All],2,0),"") | G67: =SUMIFS(Receta[[#All],[CU]],Receta[[#All],[Código]],D67,Receta[[#All],[M P]],"MO*") -> 0 | H67: =F67*G67 -> 0
... A204: 13 | E204: =IFERROR(VLOOKUP(D204,Productos[#All],2,0),"") | G204: =SUMIFS(Receta[[#All],[CU]],Receta[[#All],[Código]],D204,Receta[[#All],[M P]],"MO*") -> 0 | H204: =F204*G204 -> 0
H205: =SUBTOTAL(9,Producción[C T M O]) -> 79334

Sheet Inventario
A1: MP | B1: Nombre | C1: Producidos | D1: Vendidos | E1: Stock
A2: =Productos!A7 -> TO-06 | B2: =IFERROR(VLOOKUP(A2,Productos[#All],2,0),"") -> Toalla 160x80 Fu | C2: =SUMIF(Producción!$D$2:$D$204,A2,Producción!$F$2:$F$204) -> 2 | D2: =SUMIF(Ventas[Producto],A2,Ventas[Cantidad]) -> 2 | E2: =C2-D2 -> 0
A3: =Productos!A8 -> TO-07 | B3: =IFERROR(VLOOKUP(A3,Productos[#All],2,0),"") -> Toalla 160x80 Na | C3: =SUMIF(Producción!$D$2:$D$204,A3,Producción!$F$2:$F$204) -> 2 | D3: =SUMIF(Ventas[Producto],A3,Ventas[Cantidad]) -> 2 | E3: =C3-D3 -> 0
A4: =Productos!A9 -> TO-08 | B4: =IFERROR(VLOOKUP(A4,Productos[#All],2,0),"") -> Toalla 160x80 Ne | C4: =SUMIF(Producción!$D$2:$D$204,A4,Producción!$F$2:$F$204) -> 1 | D4: =SUMIF(Ventas[Producto],A4,Ventas[Cantidad]) -> 1 | E4: =C4-D4 -> 0
A5: =Productos!A10 -> TO-09 | B5: =IFERROR(VLOOKUP(A5,Productos[#All],2,0),"") -> Toalla 80x40 Na | C5: =SUMIF(Producción!$D$2:$D$204,A5,Producción!$F$2:$F$204) -> 1 | D5: =SUMIF(Ventas[Producto],A5,Ventas[Cantidad]) -> 1 | E5: =C5-D5 -> 0
A6: =Productos!A11 -> TO-10 | B6: =IFERROR(VLOOKUP(A6,Productos[#All],2,0),"") -> Toalla 40x40 Na | C6: =SUMIF(Producción!$D$2:$D$204,A6,Producción!$F$2:$F$204) -> 2 | D6: =SUMIF(Ventas[Producto],A6,Ventas[Cantidad]) -> 2 | E6: =C6-D6 -> 0
A7: =Productos!A12 -> TO-11 | B7: =IFERROR(VLOOKUP(A7,Productos[#All],2,0),"") -> Toalla 160x110 Na | C7: =SUMIF(Producción!$D$2:$D$204,A7,Producción!$F$2:$F$204) -> 1 | D7: =SUMIF(Ventas[Producto],A7,Ventas[Cantidad]) -> 1 | E7: =C7-D7 -> 0
A8: =Productos!A13 -> TO-12 | B8: =IFERROR(VLOOKUP(A8,Productos[#All],2,0),"") -> Toalla 160x110 Li | C8: =SUMIF(Producción!$D$2:$D$204,A8,Producción!$F$2:$F$204) -> 1 | D8: =SUMIF(Ventas[Producto],A8,Ventas[Cantidad]) -> 1 | E8: =C8-D8 -> 0
A9: =Productos!A14 -> TU-01 | B9: =IFERROR(VLOOKUP(A9,Productos[#All],2,0),"") -> Turbante Ca | C9: =SUMIF(Producción!$D$2:$D$204,A9,Producción!$F$2:$F$204) -> 16 | D9: =SUMIF(Ventas[Producto],A9,Ventas[Cantidad]) -> 13 | E9: =C9-D9 -> 3
A10: =Productos!A15 -> TU-02 | B10: =IFERROR(VLOOKUP(A10,Productos[#All],2,0),"") -> Turbante Fu | C10: =SUMIF(Producción!$D$2:$D$204,A10,Producción!$F$2:$F$204) -> 16 | D10: =SUMIF(Ventas[Producto],A10,Ventas[Cantidad]) -> 15 | E10: =C10-D10 -> 1
A11: =Productos!A16 -> TU-03 | B11: =IFERROR(VLOOKUP(A11,Productos[#All],2,0),"") -> Turbante Vp | C11: =SUMIF(Producción!$D$2:$D$204,A11,Producción!$F$2:$F$204) -> 8 | D11: =SUMIF(Ventas[Producto],A11,Ventas[Cantidad]) -> 5 | E11: =C11-D11 -> 3
A12: =Productos!A17 -> TU-04 | B12: =IFERROR(VLOOKUP(A12,Productos[#All],2,0),"") -> Turbante Li | C12: =SUMIF(Producción!$D$2:$D$204,A12,Producción!$F$2:$F$204) -> 8 | D12: =SUMIF(Ventas[Producto],A12,Ventas[Cantidad]) -> 6 | E12: =C12-D12 -> 2
A13: =Productos!A18 -> Go-01 | B13: =IFERROR(VLOOKUP(A13,Productos[#All],2,0),"") -> Gorra Natacion Lycra | C13: =SUMIF(Producción!$D$2:$D$204,A13,Producción!$F$2:$F$204) -> 5 | D13: =SUMIF(Ventas[Producto],A13,Ventas[Cantidad]) -> 4 | E13: =C13-D13 -> 1
... A57: =Productos!A62 -> 0 | B57: =IFERROR(VLOOKUP(A57,Productos[#All],2,0),"") | C57: =SUMIF(Producción!$D$2:$D$204,A57,Producción!$F$2:$F$204) -> 0 | D57: =SUMIF(Ventas[Producto],A57,Ventas[Cantidad]) -> 0 | E57: =C57-D57 -> 0

Sheet Clientes
A1: ID | B1: Nombre | C1: Dirección | D1: Referencia | E1: Zona
A2: 1
A3: 2
A4: 3
A5: 4
A6: 5
A7: 6
A8: 7
A9: 8
A10: 9
A11: 10
A12: 11
A13: 12
... A48: 47

Sheet Ventas
A1: ID | B1: Fecha | C1: Item | D1: Idet | E1: Cliente | F1: Nombre C | G1: Producto | H1: Nombre P | I1: Cantidad | J1: Observación | K1: Precio | L1: Dcto | M1: Total | N1: Tipo Pago | O1: IVA | P1: Máquina | Q1: Neto | R1: Costo | S1: Utilidad | T1: F Entrega | U1: H Entrega | V1: Transfer
A2: 1 | B2: 45913 | C2: 1 | D2: =CONCATENATE(Ventas!$A2,Ventas!$C2) -> 11 | F2: =IFERROR(VLOOKUP(Ventas!$E2,Clientes!$A$1:$E$48,2,0),"") | G2: TO-06 | H2: =IFERROR(VLOOKUP(Ventas!$G2,Productos!$A$1:$I$24,2,0),"") -> Toalla 160x80 Fu | I2: 1 | K2: =IFERROR(IF(Ventas!$E2<>13,VLOOKUP(Ventas!$G2,Productos!$A$1:$I$24,4,0),0),0) -> 8992 | M2: =Ventas!$I2*Ventas!$K2*(1-L2) -> 8992 | N2: M | O2: =IFERROR(IF(OR(N2="M",N2="T"),ROUND(M2*19/119,0),0),"") -> 1436 | P2: =ROUND(M2*0.033333,0) -> 300 | Q2: =M2-O2-P2 -> 7256 | R2: =IFERROR(ROUND(VLOOKUP(Ventas!$G2,Productos!$A$1:$I$24,5,0),0)*Ventas!$I2,"") -> 1708 | S2: =IFERROR(IF(Ventas!$E2<>13,ROUND(VLOOKUP(Ventas!$G2,Productos!$A$1:$I$24,6,0)*Ventas!$I2,0),0),"") -> 10700 | V2: S
A3: 1 | B3: 45913 | C3: 2 | D3: =CONCATENATE(Ventas!$A3,Ventas!$C3) -> 12 | F3: =IFERROR(VLOOKUP(Ventas!$E3,Clientes!$A$1:$E$48,2,0),"") | G3: TU-02 | H3: =IFERROR(VLOOKUP(Ventas!$G3,Productos!$A$1:$I$24,2,0),"") -> Turbante Fu | I3: 1 | K3: =IFERROR(IF(Ventas!$E3<>13,VLOOKUP(Ventas!$G3,Productos!$A$1:$I$24,4,0),0),0) -> 4706 | M3: =Ventas!$I3*Ventas!$K3 -> 4706 | N3: M | O3: =IFERROR(IF(OR(N3="M",N3="T"),ROUND(M3*19/119,0),0),"") -> 751 | P3: =ROUND(M3*0.033333,0) -> 157 | Q3: =M3-O3-P3 -> 3798 | R3: =IFERROR(ROUND(VLOOKUP(Ventas!$G3,Productos!$A$1:$I$24,5,0),0)*Ventas!$I3,"") -> 894 | S3: =IFERROR(IF(Ventas!$E3<>13,ROUND(VLOOKUP(Ventas!$G3,Productos!$A$1:$I$24,6,0)*Ventas!$I3,0),0),"") -> 5600 | V3: S
A4: 1 | B4: 45913 | C4: 3 | D4: =CONCATENATE(Ventas!$A4,Ventas!$C4) -> 13 | F4: =IFERROR(VLOOKUP(Ventas!$E4,Clientes!$A$1:$E$48,2,0),"") | G4: TU-01 | H4: =IFERROR(VLOOKUP(Ventas!$G4,Productos!$A$1:$I$24,2,0),"") -> Turbante Ca | I4: 1 | K4: =IFERROR(IF(Ventas!$E4<>13,VLOOKUP(Ventas!$G4,Productos!$A$1:$I$24,4,0),0),0) -> 4706 | M4: =Ventas!$I4*Ventas!$K4 -> 4706 | N4: E | O4: =IFERROR(IF(OR(N4="M",N4="T"),ROUND(M4*19/119,0),0),"") -> 0 | P4: =ROUND(M4*0.033333,0) -> 157 | Q4: =M4-O4-P4 -> 4549 | R4: =IFERROR(ROUND(VLOOKUP(Ventas!$G4,Productos!$A$1:$I$24,5,0),0)*Ventas!$I4,"") -> 894 | S4: =IFERROR(IF(Ventas!$E4<>13,ROUND(VLOOKUP(Ventas!$G4,Productos!$A$1:$I$24,6,0)*Ventas!$I4,0),0),"") -> 5600 | V4: S
A5: 1 | B5: 45913 | C5: 4 | D5: =CONCATENATE(Ventas!$A5,Ventas!$C5) -> 14 | F5: =IFERROR(VLOOKUP(Ventas!$E5,Clientes!$A$1:$E$48,2,0),"") | G5: TU-01 | H5: =IFERROR(VLOOKUP(Ventas!$G5,Productos!$A$1:$I$24,2,0),"") -> Turbante Ca | I5: 1 | K5: =IFERROR(IF(Ventas!$E5<>13,VLOOKUP(Ventas!$G5,Productos!$A$1:$I$24,4,0),0),0) -> 4706 | M5: =Ventas!$I5*Ventas!$K5 -> 4706 | N5: E | O5: =IFERROR(IF(OR(N5="M",N5="T"),ROUND(M5*19/119,0),0),"") -> 0 | P5: =ROUND(M5*0.033333,0) -> 157 | Q5: =M5-O5-P5 -> 4549 | R5: =IFERROR(ROUND(VLOOKUP(Ventas!$G5,Productos!$A$1:$I$24,5,0),0)*Ventas!$I5,"") -> 894 | S5: =IFERROR(IF(Ventas!$E5<>13,ROUND(VLOOKUP(Ventas!$G5,Productos!$A$1:$I$24,6,0)*Ventas!$I5,0),0),"") -> 5600 | V5: S
A6: 2 | B6: 45914 | C6: 1 | D6: =CONCATENATE(Ventas!$A6,Ventas!$C6) -> 21 | F6: =IFERROR(VLOOKUP(Ventas!$E6,Clientes!$A$1:$E$48,2,0),"") | G6: TU-04 | H6: =IFERROR(VLOOKUP(Ventas!$G6,Productos!$A$1:$I$24,2,0),"") -> Turbante Li | I6: 1 | K6: =IFERROR(IF(Ventas!$E6<>13,VLOOKUP(Ventas!$G6,Productos!$A$1:$I$24,4,0),0),0) -> 4706 | M6: =Ventas!$I6*Ventas!$K6 -> 4706 | N6: E | O6: =IFERROR(IF(OR(N6="M",N6="T"),ROUND(M6*19/119,0),0),"") -> 0 | P6: =ROUND(M6*0.033333,0) -> 157 | Q6: =M6-O6-P6 -> 4549 | R6: =IFERROR(ROUND(VLOOKUP(Ventas!$G6,Productos!$A$1:$I$24,5,0),0)*Ventas!$I6,"") -> 894 | S6: =IFERROR(IF(Ventas!$E6<>13,ROUND(VLOOKUP(Ventas!$G6,Productos!$A$1:$I$24,6,0)*Ventas!$I6,0),0),"") -> 5600 | V6: S
A7: 2 | B7: 45914 | C7: 2 | D7: =CONCATENATE(Ventas!$A7,Ventas!$C7) -> 22 | F7: =IFERROR(VLOOKUP(Ventas!$E7,Clientes!$A$1:$E$48,2,0),"") | G7: TU-02 | H7: =IFERROR(VLOOKUP(Ventas!$G7,Productos!$A$1:$I$24,2,0),"") -> Turbante Fu | I7: 1 | K7: =IFERROR(IF(Ventas!$E7<>13,VLOOKUP(Ventas!$G7,Productos!$A$1:$I$24,4,0),0),0) -> 4706 | M7: =Ventas!$I7*Ventas!$K7 -> 4706 | N7: E | O7: =IFERROR(IF(OR(N7="M",N7="T"),ROUND(M7*19/119,0),0),"") -> 0 | P7: =ROUND(M7*0.033333,0) -> 157 | Q7: =M7-O7-P7 -> 4549 | R7: =IFERROR(ROUND(VLOOKUP(Ventas!$G7,Productos!$A$1:$I$24,5,0),0)*Ventas!$I7,"") -> 894 | S7: =IFERROR(IF(Ventas!$E7<>13,ROUND(VLOOKUP(Ventas!$G7,Productos!$A$1:$I$24,6,0)*Ventas!$I7,0),0),"") -> 5600 | V7: S
A8: 2 | B8: 45914 | C8: 3 | D8: =CONCATENATE(Ventas!$A8,Ventas!$C8) -> 23 | F8: =IFERROR(VLOOKUP(Ventas!$E8,Clientes!$A$1:$E$48,2,0),"") | G8: TU-02 | H8: =IFERROR(VLOOKUP(Ventas!$G8,Productos!$A$1:$I$24,2,0),"") -> Turbante Fu | I8: 1 | K8: =IFERROR(IF(Ventas!$E8<>13,VLOOKUP(Ventas!$G8,Productos!$A$1:$I$24,4,0),0),0) -> 4706 | M8: =Ventas!$I8*Ventas!$K8 -> 4706 | N8: M | O8: =IFERROR(IF(OR(N8="M",N8="T"),ROUND(M8*19/119,0),0),"") -> 751 | P8: =ROUND(M8*0.033333,0) -> 157 | Q8: =M8-O8-P8 -> 3798 | R8: =IFERROR(ROUND(VLOOKUP(Ventas!$G8,Productos!$A$1:$I$24,5,0),0)*Ventas!$I8,"") -> 894 | S8: =IFERROR(IF(Ventas!$E8<>13,ROUND(VLOOKUP(Ventas!$G8,Productos!$A$1:$I$24,6,0)*Ventas!$I8,0),0),"") -> 5600 | V8: S
A9: 3 | B9: 45924 | C9: 1 | D9: =CONCATENATE(Ventas!$A9,Ventas!$C9) -> 31 | F9: =IFERROR(VLOOKUP(Ventas!$E9,Clientes!$A$1:$E$48,2,0),"") | G9: TO-12 | H9: =IFERROR(VLOOKUP(Ventas!$G9,Productos!$A$1:$I$24,2,0),"") -> Toalla 160x110 Li | I9: 1 | K9: =IFERROR(IF(Ventas!$E9<>13,VLOOKUP(Ventas!$G9,Productos!$A$1:$I$24,4,0),0),0) -> 11092 | M9: =Ventas!$I9*Ventas!$K9 -> 11092 | N9: E | O9: =IFERROR(IF(OR(N9="M",N9="T"),ROUND(M9*19/119,0),0),"") -> 0 | P9: =ROUND(M9*0.033333,0) -> 370 | Q9: =M9-O9-P9 -> 10722 | R9: =IFERROR(ROUND(VLOOKUP(Ventas!$G9,Productos!$A$1:$I$24,5,0),0)*Ventas!$I9,"") -> 2107 | S9: =IFERROR(IF(Ventas!$E9<>13,ROUND(VLOOKUP(Ventas!$G9,Productos!$A$1:$I$24,6,0)*Ventas!$I9,0),0),"") -> 13199 | V9: S
A10: 4 | B10: 45929 | C10: 1 | D10: =CONCATENATE(Ventas!$A10,Ventas!$C10) -> 41 | F10: =IFERROR(VLOOKUP(Ventas!$E10,Clientes!$A$1:$E$48,2,0),"") | G10: TU-02 | H10: =IFERROR(VLOOKUP(Ventas!$G10,Productos!$A$1:$I$24,2,0),"") -> Turbante Fu | I10: 1 | K10: =IFERROR(IF(Ventas!$E10<>13,VLOOKUP(Ventas!$G10,Productos!$A$1:$I$24,4,0),0),0) -> 4706 | M10: =Ventas!$I10*Ventas!$K10 -> 4706 | N10: M | O10: =IFERROR(IF(OR(N10="M",N10="T"),ROUND(M10*19/119,0),0),"") -> 751 | P10: =ROUND(M10*0.033333,0) -> 157 | Q10: =M10-O10-P10 -> 3798 | R10: =IFERROR(ROUND(VLOOKUP(Ventas!$G10,Productos!$A$1:$I$24,5,0),0)*Ventas!$I10,"") -> 894 | S10: =IFERROR(IF(Ventas!$E10<>13,ROUND(VLOOKUP(Ventas!$G10,Productos!$A$1:$I$24,6,0)*Ventas!$I10,0),0),"") -> 5600 | V10: S
A11: 4 | B11: 45929 | C11: 2 | D11: =CONCATENATE(Ventas!$A11,Ventas!$C11) -> 42 | F11: =IFERROR(VLOOKUP(Ventas!$E11,Clientes!$A$1:$E$48,2,0),"") | G11: TO-06 | H11: =IFERROR(VLOOKUP(Ventas!$G11,Productos!$A$1:$I$24,2,0),"") -> Toalla 160x80 Fu | I11: 1 | K11: =IFERROR(IF(Ventas!$E11<>13,VLOOKUP(Ventas!$G11,Productos!$A$1:$I$24,4,0),0),0) -> 8992 | M11: =Ventas!$I11*Ventas!$K11 -> 8992 | N11: M | O11: =IFERROR(IF(OR(N11="M",N11="T"),ROUND(M11*19/119,0),0),"") -> 1436 | P11: =ROUND(M11*0.033333,0) -> 300 | Q11: =M11-O11-P11 -> 7256 | R11: =IFERROR(ROUND(VLOOKUP(Ventas!$G11,Productos!$A$1:$I$24,5,0),0)*Ventas!$I11,"") -> 1708 | S11: =IFERROR(IF(Ventas!$E11<>13,ROUND(VLOOKUP(Ventas!$G11,Productos!$A$1:$I$24,6,0)*Ventas!$I11,0),0),"") -> 10700 | V11: S
A12: 4 | B12: 45929 | C12: 3 | D12: =CONCATENATE(Ventas!$A12,Ventas!$C12) -> 43 | F12: =IFERROR(VLOOKUP(Ventas!$E12,Clientes!$A$1:$E$48,2,0),"") | G12: Go-01 | H12: =IFERROR(VLOOKUP(Ventas!$G12,Productos!$A$1:$I$24,2,0),"") -> Gorra Natacion Lycra | I12: 1 | K12: =IFERROR(IF(Ventas!$E12<>13,VLOOKUP(Ventas!$G12,Productos!$A$1:$I$24,4,0),0),0) -> 4454 | M12: =Ventas!$I12*Ventas!$K12 -> 4454 | N12: M | O12: =IFERROR(IF(OR(N12="M",N12="T"),ROUND(M12*19/119,0),0),"") -> 711 | P12: =ROUND(M12*0.033333,0) -> 148 | Q12: =M12-O12-P12 -> 3595 | R12: =IFERROR(ROUND(VLOOKUP(Ventas!$G12,Productos!$A$1:$I$24,5,0),0)*Ventas!$I12,"") -> 846 | S12: =IFERROR(IF(Ventas!$E12<>13,ROUND(VLOOKUP(Ventas!$G12,Productos!$A$1:$I$24,6,0)*Ventas!$I12,0),0),"") -> 5300 | V12: S
A13: 4 | B13: 45929 | C13: 4 | D13: =CONCATENATE(Ventas!$A13,Ventas!$C13) -> 44 | F13: =IFERROR(VLOOKUP(Ventas!$E13,Clientes!$A$1:$E$48,2,0),"") | G13: TU-02 | H13: =IFERROR(VLOOKUP(Ventas!$G13,Productos!$A$1:$I$24,2,0),"") -> Turbante Fu | I13: 1 | K13: =IFERROR(IF(Ventas!$E13<>13,VLOOKUP(Ventas!$G13,Productos!$A$1:$I$24,4,0),0),0) -> 4706 | M13: =Ventas!$I13*Ventas!$K13 -> 4706 | N13: M | O13: =IFERROR(IF(OR(N13="M",N13="T"),ROUND(M13*19/119,0),0),"") -> 751 | P13: =ROUND(M13*0.033333,0) -> 157 | Q13: =M13-O13-P13 -> 3798 | R13: =IFERROR(ROUND(VLOOKUP(Ventas!$G13,Productos!$A$1:$I$24,5,0),0)*Ventas!$I13,"") -> 894 | S13: =IFERROR(IF(Ventas!$E13<>13,ROUND(VLOOKUP(Ventas!$G13,Productos!$A$1:$I$24,6,0)*Ventas!$I13,0),0),"") -> 5600 | V13: S
A14: 4 | B14: 45929 | C14: 5 | D14: =CONCATENATE(Ventas!$A14,Ventas!$C14) -> 45 | F14: =IFERROR(VLOOKUP(Ventas!$E14,Clientes!$A$1:$E$48,2,0),"") | G14: TU-03 | H14: =IFERROR(VLOOKUP(Ventas!$G14,Productos!$A$1:$I$24,2,0),"") -> Turbante Vp | I14: 1 | K14: =IFERROR(IF(Ventas!$E14<>13,VLOOKUP(Ventas!$G14,Productos!$A$1:$I$24,4,0),0),0) -> 4706 | M14: =Ventas!$I14*Ventas!$K14 -> 4706 | N14: M | O14: =IFERROR(IF(OR(N14="M",N14="T"),ROUND(M14*19/119,0),0),"") -> 751 | P14: =ROUND(M14*0.033333,0) -> 157 | Q14: =M14-O14-P14 -> 3798 | R14: =IFERROR(ROUND(VLOOKUP(Ventas!$G14,Productos!$A$1:$I$24,5,0),0)*Ventas!$I14,"") -> 894 | S14: =IFERROR(IF(Ventas!$E14<>13,ROUND(VLOOKUP(Ventas!$G14,Productos!$A$1:$I$24,6,0)*Ventas!$I14,0),0),"") -> 5600 | V14: S
... A28: 10 | B28: 45949 | C28: 3 | D28: =CONCATENATE(Ventas!$A28,Ventas!$C28) -> 103 | F28: =IFERROR(VLOOKUP(Ventas!$E28,Clientes!$A$1:$E$48,2,0),"") | G28: TU-03 | H28: =IFERROR(VLOOKUP(Ventas!$G28,Productos!$A$1:$I$24,2,0),"") -> Turbante Vp | I28: 1 | K28: =IFERROR(IF(Ventas!$E28<>13,VLOOKUP(Ventas!$G28,Productos!$A$1:$I$24,4,0),0),0) -> 4706 | M28: =Ventas!$I28*Ventas!$K28 -> 4706 | N28: M | O28: =IFERROR(IF(OR(N28="M",N28="T"),ROUND(M28*19/119,0),0),"") -> 751 | P28: =ROUND(M28*0.033333,0) -> 157 | Q28: =M28-O28-P28 -> 3798 | R28: =IFERROR(ROUND(VLOOKUP(Ventas!$G28,Productos!$A$1:$I$24,5,0),0)*Ventas!$I28,"") -> 894 | S28: =IFERROR(IF(Ventas!$E28<>13,ROUND(VLOOKUP(Ventas!$G28,Productos!$A$1:$I$24,6,0)*Ventas!$I28,0),0),"") -> 5600 | V28: S
A29: 11 | B29: 45969 | C29: 1 | D29: =CONCATENATE(Ventas!$A29,Ventas!$C29) -> 111 | F29: =IFERROR(VLOOKUP(Ventas!$E29,Clientes!$A$1:$E$48,2,0),"") | G29: TO-09 | H29: =IFERROR(VLOOKUP(Ventas!$G29,Productos!$A$1:$I$24,2,0),"") -> Toalla 80x40 Na | I29: 1 | K29: =IFERROR(IF(Ventas!$E29<>13,VLOOKUP(Ventas!$G29,Productos!$A$1:$I$24,4,0),0),0) -> 7983 | L29: 0.021 | M29: =Ventas!$I29*Ventas!$K29*(1-L29) -> 7815.357 | N29: M | O29: =IFERROR(IF(OR(N29="M",N29="T"),ROUND(M29*19/119,0),0),"") -> 1248 | P29: =ROUND(M29*0.033333,0) -> 261 | Q29: =M29-O29-P29 -> 6306.357 | R29: =IFERROR(ROUND(VLOOKUP(Ventas!$G29,Productos!$A$1:$I$24,5,0),0)*Ventas!$I29,"") -> 1517 | S29: =IFERROR(IF(Ventas!$E29<>13,ROUND(VLOOKUP(Ventas!$G29,Productos!$A$1:$I$24,6,0)*Ventas!$I29,0),0),"") -> 9500 | V29: S
A30: 11 | B30: 45969 | C30: 2 | D30: =CONCATENATE(Ventas!$A30,Ventas!$C30) -> 112 | F30: =IFERROR(VLOOKUP(Ventas!$E30,Clientes!$A$1:$E$48,2,0),"") | G30: TO-04 | H30: =IFERROR(VLOOKUP(Ventas!$G30,Productos!$A$1:$I$24,2,0),"") -> Toalla 160x80 Vp | I30: 1 | K30: =IFERROR(IF(Ventas!$E30<>13,VLOOKUP(Ventas!$G30,Productos!$A$1:$I$24,4,0),0),0) -> 8992 | M30: =Ventas!$I30*Ventas!$K30 -> 8992 | N30: E | O30: =IFERROR(IF(OR(N30="M",N30="T"),ROUND(M30*19/119,0),0),"") -> 0 | P30: =ROUND(M30*0.033333,0) -> 300 | Q30: =M30-O30-P30 -> 8692 | R30: =IFERROR(ROUND(VLOOKUP(Ventas!$G30,Productos!$A$1:$I$24,5,0),0)*Ventas!$I30,"") -> 1708 | S30: =IFERROR(IF(Ventas!$E30<>13,ROUND(VLOOKUP(Ventas!$G30,Productos!$A$1:$I$24,6,0)*Ventas!$I30,0),0),"") -> 10700 | V30: S
A31: 12 | B31: 45970 | C31: 1 | D31: =CONCATENATE(Ventas!$A31,Ventas!$C31) -> 121 | F31: =IFERROR(VLOOKUP(Ventas!$E31,Clientes!$A$1:$E$48,2,0),"") | G31: TU-05 | H31: =IFERROR(VLOOKUP(Ventas!$G31,Productos!$A$1:$I$24,2,0),"") -> Turbante Ne | I31: 2 | K31: =IFERROR(IF(Ventas!$E31<>13,VLOOKUP(Ventas!$G31,Productos!$A$1:$I$24,4,0),0),0) -> 4706 | M31: =Ventas!$I31*Ventas!$K31 -> 9412 | N31: M | O31: =IFERROR(IF(OR(N31="M",N31="T"),ROUND(M31*19/119,0),0),"") -> 1503 | P31: =ROUND(M31*0.033333,0) -> 314 | Q31: =M31-O31-P31 -> 7595 | R31: =IFERROR(ROUND(VLOOKUP(Ventas!$G31,Productos!$A$1:$I$24,5,0),0)*Ventas!$I31,"") -> 1788 | S31: =IFERROR(IF(Ventas!$E31<>13,ROUND(VLOOKUP(Ventas!$G31,Productos!$A$1:$I$24,6,0)*Ventas!$I31,0),0),"") -> 11200 | V31: S
A32: 12 | B32: 45970 | C32: 2 | D32: =CONCATENATE(Ventas!$A32,Ventas!$C32) -> 122 | F32: =IFERROR(VLOOKUP(Ventas!$E32,Clientes!$A$1:$E$48,2,0),"") | G32: TU-02 | H32: =IFERROR(VLOOKUP(Ventas!$G32,Productos!$A$1:$I$24,2,0),"") -> Turbante Fu | I32: 1 | K32: =IFERROR(IF(Ventas!$E32<>13,VLOOKUP(Ventas!$G32,Productos!$A$1:$I$24,4,0),0),0) -> 4706 | M32: =Ventas!$I32*Ventas!$K32 -> 4706 | N32: M | O32: =IFERROR(IF(OR(N32="M",N32="T"),ROUND(M32*19/119,0),0),"") -> 751 | P32: =ROUND(M32*0.033333,0) -> 157 | Q32: =M32-O32-P32 -> 3798 | R32: =IFERROR(ROUND(VLOOKUP(Ventas!$G32,Productos!$A$1:$I$24,5,0),0)*Ventas!$I32,"") -> 894 | S32: =IFERROR(IF(Ventas!$E32<>13,ROUND(VLOOKUP(Ventas!$G32,Productos!$A$1:$I$24,6,0)*Ventas!$I32,0),0),"") -> 5600 | V32: S
A33: 12 | B33: 45970 | C33: 3 | D33: =CONCATENATE(Ventas!$A33,Ventas!$C33) -> 123 | F33: =IFERROR(VLOOKUP(Ventas!$E33,Clientes!$A$1:$E$48,2,0),"") | G33: TU-04 | H33: =IFERROR(VLOOKUP(Ventas!$G33,Productos!$A$1:$I$24,2,0),"") -> Turbante Li | I33: 1 | K33: =IFERROR(IF(Ventas!$E33<>13,VLOOKUP(Ventas!$G33,Productos!$A$1:$I$24,4,0),0),0) -> 4706 | M33: =Ventas!$I33*Ventas!$K33 -> 4706 | N33: M | O33: =IFERROR(IF(OR(N33="M",N33="T"),ROUND(M33*19/119,0),0),"") -> 751 | P33: =ROUND(M33*0.033333,0) -> 157 | Q33: =M33-O33-P33 -> 3798 | R33: =IFERROR(ROUND(VLOOKUP(Ventas!$G33,Productos!$A$1:$I$24,5,0),0)*Ventas!$I33,"") -> 894 | S33: =IFERROR(IF(Ventas!$E33<>13,ROUND(VLOOKUP(Ventas!$G33,Productos!$A$1:$I$24,6,0)*Ventas!$I33,0),0),"") -> 5600 | V33: S
A34: 13 | B34: 45992 | C34: 1 | D34: =CONCATENATE(Ventas!$A34,Ventas!$C34) -> 131 | F34: =IFERROR(VLOOKUP(Ventas!$E34,Clientes!$A$1:$E$48,2,0),"") | G34: TU-02 | H34: =IFERROR(VLOOKUP(Ventas!$G34,Productos!$A$1:$I$24,2,0),"") -> Turbante Fu | I34: 1 | K34: =IFERROR(IF(Ventas!$E34<>13,VLOOKUP(Ventas!$G34,Productos!$A$1:$I$24,4,0),0),0) -> 4706 | M34: =Ventas!$I34*Ventas!$K34 -> 4706 | N34: M | O34: =IFERROR(IF(OR(N34="M",N34="T"),ROUND(M34*19/119,0),0),"") -> 751 | P34: =ROUND(M34*0.033333,0) -> 157 | Q34: =M34-O34-P34 -> 3798 | R34: =IFERROR(ROUND(VLOOKUP(Ventas!$G34,Productos!$A$1:$I$24,5,0),0)*Ventas!$I34,"") -> 894 | S34: =IFERROR(IF(Ventas!$E34<>13,ROUND(VLOOKUP(Ventas!$G34,Productos!$A$1:$I$24,6,0)*Ventas!$I34,0),0),"") -> 5600 | V34: S
A35: 13 | B35: 45992 | C35: 2 | D35: =CONCATENATE(Ventas!$A35,Ventas!$C35) -> 132 | F35: =IFERROR(VLOOKUP(Ventas!$E35,Clientes!$A$1:$E$48,2,0),"") | G35: TU-04 | H35: =IFERROR(VLOOKUP(Ventas!$G35,Productos!$A$1:$I$24,2,0),"") -> Turbante Li | I35: 1 | K35: =IFERROR(IF(Ventas!$E35<>13,VLOOKUP(Ventas!$G35,Productos!$A$1:$I$24,4,0),0),0) -> 4706 | M35: =Ventas!$I35*Ventas!$K35 -> 4706 | N35: M | O35: =IFERROR(IF(OR(N35="M",N35="T"),ROUND(M35*19/119,0),0),"") -> 751 | P35: =ROUND(M35*0.033333,0) -> 157 | Q35: =M35-O35-P35 -> 3798 | R35: =IFERROR(ROUND(VLOOKUP(Ventas!$G35,Productos!$A$1:$I$24,5,0),0)*Ventas!$I35,"") -> 894 | S35: =IFERROR(IF(Ventas!$E35<>13,ROUND(VLOOKUP(Ventas!$G35,Productos!$A$1:$I$24,6,0)*Ventas!$I35,0),0),"") -> 5600 | V35: S
A36: 14 | B36: 45993 | C36: 1 | D36: =CONCATENATE(Ventas!$A36,Ventas!$C36) -> 141 | F36: =IFERROR(VLOOKUP(Ventas!$E36,Clientes!$A$1:$E$48,2,0),"") | G36: TO-07 | H36: =IFERROR(VLOOKUP(Ventas!$G36,Productos!$A$1:$I$24,2,0),"") -> Toalla 160x80 Na | I36: 1 | K36: =IFERROR(IF(Ventas!$E36<>13,VLOOKUP(Ventas!$G36,Productos!$A$1:$I$24,4,0),0),0) -> 8992 | L36: 0.0654 | M36: =Ventas!$I36*Ventas!$K36*(1-L36) -> 8403.9232 | N36: E | O36: =IFERROR(IF(OR(N36="M",N36="T"),ROUND(M36*19/119,0),0),"") -> 0 | P36: =ROUND(M36*0.033333,0) -> 280 | Q36: =M36-O36-P36 -> 8123.9232 | R36: =IFERROR(ROUND(VLOOKUP(Ventas!$G36,Productos!$A$1:$I$24,5,0),0)*Ventas!$I36,"") -> 1708 | S36: =IFERROR(IF(Ventas!$E36<>13,ROUND(VLOOKUP(Ventas!$G36,Productos!$A$1:$I$24,6,0)*Ventas!$I36,0),0),"") -> 10700 | V36: S
A37: 14 | B37: 45993 | C37: 2 | D37: =CONCATENATE(Ventas!$A37,Ventas!$C37) -> 142 | F37: =IFERROR(VLOOKUP(Ventas!$E37,Clientes!$A$1:$E$48,2,0),"") | G37: TU-04 | H37: =IFERROR(VLOOKUP(Ventas!$G37,Productos!$A$1:$I$24,2,0),"") -> Turbante Li | I37: 1 | K37: =IFERROR(IF(Ventas!$E37<>13,VLOOKUP(Ventas!$G37,Productos!$A$1:$I$24,4,0),0),0) -> 4706 | M37: =Ventas!$I37*Ventas!$K37 -> 4706 | N37: E | O37: =IFERROR(IF(OR(N37="M",N37="T"),ROUND(M37*19/119,0),0),"") -> 0 | P37: =ROUND(M37*0.033333,0) -> 157 | Q37: =M37-O37-P37 -> 4549 | R37: =IFERROR(ROUND(VLOOKUP(Ventas!$G37,Productos!$A$1:$I$24,5,0),0)*Ventas!$I37,"") -> 894 | S37: =IFERROR(IF(Ventas!$E37<>13,ROUND(VLOOKUP(Ventas!$G37,Productos!$A$1:$I$24,6,0)*Ventas!$I37,0),0),"") -> 5600 | V37: S
A38: 15 | B38: 45995 | C38: 1 | D38: =CONCATENATE(Ventas!$A38,Ventas!$C38) -> 151 | F38: =IFERROR(VLOOKUP(Ventas!$E38,Clientes!$A$1:$E$48,2,0),"") | G38: TU-08 | H38: =IFERROR(VLOOKUP(Ventas!$G38,Productos!$A$1:$I$24,2,0),"") -> Turbante Ro | I38: 1 | K38: =IFERROR(IF(Ventas!$E38<>13,VLOOKUP(Ventas!$G38,Productos!$A$1:$I$24,4,0),0),0) -> 4706 | M38: =Ventas!$I38*Ventas!$K38 -> 4706 | N38: M | O38: =IFERROR(IF(OR(N38="M",N38="T"),ROUND(M38*19/119,0),0),"") -> 751 | P38: =ROUND(M38*0.033333,0) -> 157 | Q38: =M38-O38-P38 -> 3798 | R38: =IFERROR(ROUND(VLOOKUP(Ventas!$G38,Productos!$A$1:$I$24,5,0),0)*Ventas!$I38,"") -> 894 | S38: =IFERROR(IF(Ventas!$E38<>13,ROUND(VLOOKUP(Ventas!$G38,Productos!$A$1:$I$24,6,0)*Ventas!$I38,0),0),"") -> 5600 | V38: S
A39: 15 | B39: 45995 | C39: 2 | D39: =CONCATENATE(Ventas!$A39,Ventas!$C39) -> 152 | F39: =IFERROR(VLOOKUP(Ventas!$E39,Clientes!$A$1:$E$48,2,0),"") | G39: TO-01 | H39: =IFERROR(VLOOKUP(Ventas!$G39,Productos!$A$1:$I$24,2,0),"") -> Toalla 160x80 Az | I39: 1 | K39: =IFERROR(IF(Ventas!$E39<>13,VLOOKUP(Ventas!$G39,Productos!$A$1:$I$24,4,0),0),0) -> 8992 | M39: =Ventas!$I39*Ventas!$K39 -> 8992 | N39: M | O39: =IFERROR(IF(OR(N39="M",N39="T"),ROUND(M39*19/119,0),0),"") -> 1436 | P39: =ROUND(M39*0.033333,0) -> 300 | Q39: =M39-O39-P39 -> 7256 | R39: =IFERROR(ROUND(VLOOKUP(Ventas!$G39,Productos!$A$1:$I$24,5,0),0)*Ventas!$I39,"") -> 1708 | S39: =IFERROR(IF(Ventas!$E39<>13,ROUND(VLOOKUP(Ventas!$G39,Productos!$A$1:$I$24,6,0)*Ventas!$I39,0),0),"") -> 10700 | V39: S
A40: 15 | B40: 45995 | C40: 3 | D40: =CONCATENATE(Ventas!$A40,Ventas!$C40) -> 153 | F40: =IFERROR(VLOOKUP(Ventas!$E40,Clientes!$A$1:$E$48,2,0),"") | G40: TO-08 | H40: =IFERROR(VLOOKUP(Ventas!$G40,Productos!$A$1:$I$24,2,0),"") -> Toalla 160x80 Ne | I40: 1 | K40: =IFERROR(IF(Ventas!$E40<>13,VLOOKUP(Ventas!$G40,Productos!$A$1:$I$24,4,0),0),0) -> 8992 | M40: =Ventas!$I40*Ventas!$K40 -> 8992 | N40: M | O40: =IFERROR(IF(OR(N40="M",N40="T"),ROUND(M40*19/119,0),0),"") -> 1436 | P40: =ROUND(M40*0.033333,0) -> 300 | Q40: =M40-O40-P40 -> 7256 | R40: =IFERROR(ROUND(VLOOKUP(Ventas!$G40,Productos!$A$1:$I$24,5,0),0)*Ventas!$I40,"") -> 1708 | S40: =IFERROR(IF(Ventas!$E40<>13,ROUND(VLOOKUP(Ventas!$G40,Productos!$A$1:$I$24,6,0)*Ventas!$I40,0),0),"") -> 10700 | V40: S
A41: 15 | B41: 45995 | C41: 4 | D41: =CONCATENATE(Ventas!$A41,Ventas!$C41) -> 154 | F41: =IFERROR(VLOOKUP(Ventas!$E41,Clientes!$A$1:$E$48,2,0),"") | G41: TO-11 | H41: =IFERROR(VLOOKUP(Ventas!$G41,Productos!$A$1:$I$24,2,0),"") -> Toalla 160x110 Na | I41: 1 | K41: =IFERROR(IF(Ventas!$E41<>13,VLOOKUP(Ventas!$G41,Productos!$A$1:$I$24,4,0),0),0) -> 11092 | M41: =Ventas!$I41*Ventas!$K41 -> 11092 | N41: M | O41: =IFERROR(IF(OR(N41="M",N41="T"),ROUND(M41*19/119,0),0),"") -> 1771 | P41: =ROUND(M41*0.033333,0) -> 370 | Q41: =M41-O41-P41 -> 8951 | R41: =IFERROR(ROUND(VLOOKUP(Ventas!$G41,Productos!$A$1:$I$24,5,0),0)*Ventas!$I41,"") -> 2107 | S41: =IFERROR(IF(Ventas!$E41<>13,ROUND(VLOOKUP(Ventas!$G41,Productos!$A$1:$I$24,6,0)*Ventas!$I41,0),0),"") -> 13199 | V41: S
A42: 15 | B42: 45995 | C42: 5 | D42: =CONCATENATE(Ventas!$A42,Ventas!$C42) -> 155 | F42: =IFERROR(VLOOKUP(Ventas!$E42,Clientes!$A$1:$E$48,2,0),"") | G42: TO-10 | H42: =IFERROR(VLOOKUP(Ventas!$G42,Productos!$A$1:$I$24,2,0),"") -> Toalla 40x40 Na | I42: 1 | K42: =IFERROR(IF(Ventas!$E42<>13,VLOOKUP(Ventas!$G42,Productos!$A$1:$I$24,4,0),0),0) -> 3782 | M42: =Ventas!$I42*Ventas!$K42 -> 3782 | N42: E | O42: =IFERROR(IF(OR(N42="M",N42="T"),ROUND(M42*19/119,0),0),"") -> 0 | P42: =ROUND(M42*0.033333,0) -> 126 | Q42: =M42-O42-P42 -> 3656 | R42: =IFERROR(ROUND(VLOOKUP(Ventas!$G42,Productos!$A$1:$I$24,5,0),0)*Ventas!$I42,"") -> 719 | S42: =IFERROR(IF(Ventas!$E42<>13,ROUND(VLOOKUP(Ventas!$G42,Productos!$A$1:$I$24,6,0)*Ventas!$I42,0),0),"") -> 4501 | V42: S
A43: 16 | B43: 46004 | C43: 1 | D43: =CONCATENATE(Ventas!$A43,Ventas!$C43) -> 161 | F43: =IFERROR(VLOOKUP(Ventas!$E43,Clientes!$A$1:$E$48,2,0),"") | G43: TU-06 | H43: =IFERROR(VLOOKUP(Ventas!$G43,Productos!$A$1:$I$24,2,0),"") -> Turbante Na | I43: 1 | K43: =IFERROR(IF(Ventas!$E43<>13,VLOOKUP(Ventas!$G43,Productos!$A$1:$I$24,4,0),0),0) -> 4706 | M43: =Ventas!$I43*Ventas!$K43 -> 4706 | N43: E | O43: =IFERROR(IF(OR(N43="M",N43="T"),ROUND(M43*19/119,0),0),"") -> 0 | P43: =ROUND(M43*0.033333,0) -> 157 | Q43: =M43-O43-P43 -> 4549 | R43: =IFERROR(ROUND(VLOOKUP(Ventas!$G43,Productos!$A$1:$I$24,5,0),0)*Ventas!$I43,"") -> 894 | S43: =IFERROR(IF(Ventas!$E43<>13,ROUND(VLOOKUP(Ventas!$G43,Productos!$A$1:$I$24,6,0)*Ventas!$I43,0),0),"") -> 5600
A44: 16 | B44: 46004 | C44: 2 | D44: =CONCATENATE(Ventas!$A44,Ventas!$C44) -> 162 | F44: =IFERROR(VLOOKUP(Ventas!$E44,Clientes!$A$1:$E$48,2,0),"") | G44: TU-01 | H44: =IFERROR(VLOOKUP(Ventas!$G44,Productos!$A$1:$I$24,2,0),"") -> Turbante Ca | I44: 1 | K44: =IFERROR(IF(Ventas!$E44<>13,VLOOKUP(Ventas!$G44,Productos!$A$1:$I$24,4,0),0),0) -> 4706 | M44: =Ventas!$I44*Ventas!$K44 -> 4706 | N44: E | O44: =IFERROR(IF(OR(N44="M",N44="T"),ROUND(M44*19/119,0),0),"") -> 0 | P44: =ROUND(M44*0.033333,0) -> 157 | Q44: =M44-O44-P44 -> 4549 | R44: =IFERROR(ROUND(VLOOKUP(Ventas!$G44,Productos!$A$1:$I$24,5,0),0)*Ventas!$I44,"") -> 894 | S44: =IFERROR(IF(Ventas!$E44<>13,ROUND(VLOOKUP(Ventas!$G44,Productos!$A$1:$I$24,6,0)*Ventas!$I44,0),0),"") -> 5600
A45: 16 | B45: 46004 | C45: 3 | D45: =CONCATENATE(Ventas!$A45,Ventas!$C45) -> 163 | F45: =IFERROR(VLOOKUP(Ventas!$E45,Clientes!$A$1:$E$48,2,0),"") | G45: TU-01 | H45: =IFERROR(VLOOKUP(Ventas!$G45,Productos!$A$1:$I$24,2,0),"") -> Turbante Ca | I45: 1 | K45: =IFERROR(IF(Ventas!$E45<>13,VLOOKUP(Ventas!$G45,Productos!$A$1:$I$24,4,0),0),0) -> 4706 | M45: =Ventas!$I45*Ventas!$K45 -> 4706 | N45: M | O45: =IFERROR(IF(OR(N45="M",N45="T"),ROUND(M45*19/119,0),0),"") -> 751 | P45: =ROUND(M45*0.033333,0) -> 157 | Q45: =M45-O45-P45 -> 3798 | R45: =IFERROR(ROUND(VLOOKUP(Ventas!$G45,Productos!$A$1:$I$24,5,0),0)*Ventas!$I45,"") -> 894 | S45: =IFERROR(IF(Ventas!$E45<>13,ROUND(VLOOKUP(Ventas!$G45,Productos!$A$1:$I$24,6,0)*Ventas!$I45,0),0),"") -> 5600
A46: 16 | B46: 46004 | C46: 4 | D46: =CONCATENATE(Ventas!$A46,Ventas!$C46) -> 164 | F46: =IFERROR(VLOOKUP(Ventas!$E46,Clientes!$A$1:$E$48,2,0),"") | G46: TU-03 | H46: =IFERROR(VLOOKUP(Ventas!$G46,Productos!$A$1:$I$24,2,0),"") -> Turbante Vp | I46: 1 | K46: =IFERROR(IF(Ventas!$E46<>13,VLOOKUP(Ventas!$G46,Productos!$A$1:$I$24,4,0),0),0) -> 4706 | M46: =Ventas!$I46*Ventas!$K46 -> 4706 | N46: M | O46: =IFERROR(IF(OR(N46="M",N46="T"),ROUND(M46*19/119,0),0),"") -> 751 | P46: =ROUND(M46*0.033333,0) -> 157 | Q46: =M46-O46-P46 -> 3798 | R46: =IFERROR(ROUND(VLOOKUP(Ventas!$G46,Productos!$A$1:$I$24,5,0),0)*Ventas!$I46,"") -> 894 | S46: =IFERROR(IF(Ventas!$E46<>13,ROUND(VLOOKUP(Ventas!$G46,Productos!$A$1:$I$24,6,0)*Ventas!$I46,0),0),"") -> 5600
A47: 16 | B47: 46004 | C47: 5 | D47: =CONCATENATE(Ventas!$A47,Ventas!$C47) -> 165 | F47: =IFERROR(VLOOKUP(Ventas!$E47,Clientes!$A$1:$E$48,2,0),"") | G47: TU-02 | H47: =IFERROR(VLOOKUP(Ventas!$G47,Productos!$A$1:$I$24,2,0),"") -> Turbante Fu | I47: 1 | K47: =IFERROR(IF(Ventas!$E47<>13,VLOOKUP(Ventas!$G47,Productos!$A$1:$I$24,4,0),0),0) -> 4706 | M47: =Ventas!$I47*Ventas!$K47 -> 4706 | N47: M | O47: =IFERROR(IF(OR(N47="M",N47="T"),ROUND(M47*19/119,0),0),"") -> 751 | P47: =ROUND(M47*0.033333,0) -> 157 | Q47: =M47-O47-P47 -> 3798 | R47: =IFERROR(ROUND(VLOOKUP(Ventas!$G47,Productos!$A$1:$I$24,5,0),0)*Ventas!$I47,"") -> 894 | S47: =IFERROR(IF(Ventas!$E47<>13,ROUND(VLOOKUP(Ventas!$G47,Productos!$A$1:$I$24,6,0)*Ventas!$I47,0),0),"") -> 5600
A48: 17 | B48: 46005 | C48: 1 | D48: =CONCATENATE(Ventas!$A48,Ventas!$C48) -> 171 | F48: =IFERROR(VLOOKUP(Ventas!$E48,Clientes!$A$1:$E$48,2,0),"") | G48: TU-05 | H48: =IFERROR(VLOOKUP(Ventas!$G48,Productos!$A$1:$I$24,2,0),"") -> Turbante Ne | I48: 1 | K48: =IFERROR(IF(Ventas!$E48<>13,VLOOKUP(Ventas!$G48,Productos!$A$1:$I$24,4,0),0),0) -> 4706 | M48: =Ventas!$I48*Ventas!$K48 -> 4706 | N48: M | O48: =IFERROR(IF(OR(N48="M",N48="T"),ROUND(M48*19/119,0),0),"") -> 751 | P48: =ROUND(M48*0.033333,0) -> 157 | Q48: =M48-O48-P48 -> 3798 | R48: =IFERROR(ROUND(VLOOKUP(Ventas!$G48,Productos!$A$1:$I$24,5,0),0)*Ventas!$I48,"") -> 894 | S48: =IFERROR(IF(Ventas!$E48<>13,ROUND(VLOOKUP(Ventas!$G48,Productos!$A$1:$I$24,6,0)*Ventas!$I48,0),0),"") -> 5600
A49: 17 | B49: 46005 | C49: 2 | D49: =CONCATENATE(Ventas!$A49,Ventas!$C49) -> 172 | F49: =IFERROR(VLOOKUP(Ventas!$E49,Clientes!$A$1:$E$48,2,0),"") | G49: TU-07 | H49: =IFERROR(VLOOKUP(Ventas!$G49,Productos!$A$1:$I$24,2,0),"") -> Turbante Am | I49: 1 | K49: =IFERROR(IF(Ventas!$E49<>13,VLOOKUP(Ventas!$G49,Productos!$A$1:$I$24,4,0),0),0) -> 4706 | M49: =Ventas!$I49*Ventas!$K49 -> 4706 | N49: M | O49: =IFERROR(IF(OR(N49="M",N49="T"),ROUND(M49*19/119,0),0),"") -> 751 | P49: =ROUND(M49*0.033333,0) -> 157 | Q49: =M49-O49-P49 -> 3798 | R49: =IFERROR(ROUND(VLOOKUP(Ventas!$G49,Productos!$A$1:$I$24,5,0),0)*Ventas!$I49,"") -> 894 | S49: =IFERROR(IF(Ventas!$E49<>13,ROUND(VLOOKUP(Ventas!$G49,Productos!$A$1:$I$24,6,0)*Ventas!$I49,0),0),"") -> 5600
A50: 17 | B50: 46005 | C50: 3 | D50: =CONCATENATE(Ventas!$A50,Ventas!$C50) -> 173 | F50: =IFERROR(VLOOKUP(Ventas!$E50,Clientes!$A$1:$E$48,2,0),"") | G50: TO-04 | H50: =IFERROR(VLOOKUP(Ventas!$G50,Productos!$A$1:$I$24,2,0),"") -> Toalla 160x80 Vp | I50: 1 | K50: =IFERROR(IF(Ventas!$E50<>13,VLOOKUP(Ventas!$G50,Productos!$A$1:$I$24,4,0),0),0) -> 8992 | M50: =Ventas!$I50*Ventas!$K50 -> 8992 | N50: M | O50: =IFERROR(IF(OR(N50="M",N50="T"),ROUND(M50*19/119,0),0),"") -> 1436 | P50: =ROUND(M50*0.033333,0) -> 300 | Q50: =M50-O50-P50 -> 7256 | R50: =IFERROR(ROUND(VLOOKUP(Ventas!$G50,Productos!$A$1:$I$24,5,0),0)*Ventas!$I50,"") -> 1708 | S50: =IFERROR(IF(Ventas!$E50<>13,ROUND(VLOOKUP(Ventas!$G50,Productos!$A$1:$I$24,6,0)*Ventas!$I50,0),0),"") -> 10700
A51: 17 | B51: 46005 | C51: 4 | D51: =CONCATENATE(Ventas!$A51,Ventas!$C51) -> 174 | F51: =IFERROR(VLOOKUP(Ventas!$E51,Clientes!$A$1:$E$48,2,0),"") | G51: TU-03 | H51: =IFERROR(VLOOKUP(Ventas!$G51,Productos!$A$1:$I$24,2,0),"") -> Turbante Vp | I51: 1 | K51: =IFERROR(IF(Ventas!$E51<>13,VLOOKUP(Ventas!$G51,Productos!$A$1:$I$24,4,0),0),0) -> 4706 | M51: =Ventas!$I51*Ventas!$K51 -> 4706 | N51: M | O51: =IFERROR(IF(OR(N51="M",N51="T"),ROUND(M51*19/119,0),0),"") -> 751 | P51: =ROUND(M51*0.033333,0) -> 157 | Q51: =M51-O51-P51 -> 3798 | R51: =IFERROR(ROUND(VLOOKUP(Ventas!$G51,Productos!$A$1:$I$24,5,0),0)*Ventas!$I51,"") -> 894 | S51: =IFERROR(IF(Ventas!$E51<>13,ROUND(VLOOKUP(Ventas!$G51,Productos!$A$1:$I$24,6,0)*Ventas!$I51,0),0),"") -> 5600
A52: 17 | B52: 46005 | C52: 5 | D52: =CONCATENATE(Ventas!$A52,Ventas!$C52) -> 175 | F52: =IFERROR(VLOOKUP(Ventas!$E52,Clientes!$A$1:$E$48,2,0),"") | G52: Go-01 | H52: =IFERROR(VLOOKUP(Ventas!$G52,Productos!$A$1:$I$24,2,0),"") -> Gorra Natacion Lycra | I52: 1 | K52: =IFERROR(IF(Ventas!$E52<>13,VLOOKUP(Ventas!$G52,Productos!$A$1:$I$24,4,0),0),0) -> 4454 | M52: =Ventas!$I52*Ventas!$K52 -> 4454 | N52: M | O52: =IFERROR(IF(OR(N52="M",N52="T"),ROUND(M52*19/119,0),0),"") -> 711 | P52: =ROUND(M52*0.033333,0) -> 148 | Q52: =M52-O52-P52 -> 3595 | R52: =IFERROR(ROUND(VLOOKUP(Ventas!$G52,Productos!$A$1:$I$24,5,0),0)*Ventas!$I52,"") -> 846 | S52: =IFERROR(IF(Ventas!$E52<>13,ROUND(VLOOKUP(Ventas!$G52,Productos!$A$1:$I$24,6,0)*Ventas!$I52,0),0),"") -> 5300
A53: 17 | B53: 46005 | C53: 6 | D53: =CONCATENATE(Ventas!$A53,Ventas!$C53) -> 176 | F53: =IFERROR(VLOOKUP(Ventas!$E53,Clientes!$A$1:$E$48,2,0),"") | G53: Go-01 | H53: =IFERROR(VLOOKUP(Ventas!$G53,Productos!$A$1:$I$24,2,0),"") -> Gorra Natacion Lycra | I53: 1 | K53: =IFERROR(IF(Ventas!$E53<>13,VLOOKUP(Ventas!$G53,Productos!$A$1:$I$24,4,0),0),0) -> 4454 | M53: =Ventas!$I53*Ventas!$K53 -> 4454 | N53: M | O53: =IFERROR(IF(OR(N53="M",N53="T"),ROUND(M53*19/119,0),0),"") -> 711 | P53: =ROUND(M53*0.033333,0) -> 148 | Q53: =M53-O53-P53 -> 3595 | R53: =IFERROR(ROUND(VLOOKUP(Ventas!$G53,Productos!$A$1:$I$24,5,0),0)*Ventas!$I53,"") -> 846 | S53: =IFERROR(IF(Ventas!$E53<>13,ROUND(VLOOKUP(Ventas!$G53,Productos!$A$1:$I$24,6,0)*Ventas!$I53,0),0),"") -> 5300
A54: 17 | B54: 46005 | C54: 7 | D54: =CONCATENATE(Ventas!$A54,Ventas!$C54) -> 177 | F54: =IFERROR(VLOOKUP(Ventas!$E54,Clientes!$A$1:$E$48,2,0),"") | G54: TO-02 | H54: =IFERROR(VLOOKUP(Ventas!$G54,Productos!$A$1:$I$24,2,0),"") -> Toalla 160x80 Ro | I54: 1 | K54: =IFERROR(IF(Ventas!$E54<>13,VLOOKUP(Ventas!$G54,Productos!$A$1:$I$24,4,0),0),0) -> 8992 | M54: =Ventas!$I54*Ventas!$K54 -> 8992 | N54: M | O54: =IFERROR(IF(OR(N54="M",N54="T"),ROUND(M54*19/119,0),0),"") -> 1436 | P54: =ROUND(M54*0.033333,0) -> 300 | Q54: =M54-O54-P54 -> 7256 | R54: =IFERROR(ROUND(VLOOKUP(Ventas!$G54,Productos!$A$1:$I$24,5,0),0)*Ventas!$I54,"") -> 1708 | S54: =IFERROR(IF(Ventas!$E54<>13,ROUND(VLOOKUP(Ventas!$G54,Productos!$A$1:$I$24,6,0)*Ventas!$I54,0),0),"") -> 10700
... A70: 21 | B70: 46011 | C70: 8 | D70: =CONCATENATE(Ventas!$A70,Ventas!$C70) -> 218 | F70: =IFERROR(VLOOKUP(Ventas!$E70,Clientes!$A$1:$E$48,2,0),"") | G70: TO-07 | H70: =IFERROR(VLOOKUP(Ventas!$G70,Productos!$A$1:$I$24,2,0),"") -> Toalla 160x80 Na | I70: 1 | K70: =IFERROR(IF(Ventas!$E70<>13,VLOOKUP(Ventas!$G70,Productos!$A$1:$I$24,4,0),0),0) -> 8992 | M70: =Ventas!$I70*Ventas!$K70 -> 8992 | N70: E | O70: =IFERROR(IF(OR(N70="M",N70="T"),ROUND(M70*19/119,0),0),"") -> 0 | P70: =ROUND(M70*0.033333,0) -> 300 | Q70: =M70-O70-P70 -> 8692 | R70: =IFERROR(ROUND(VLOOKUP(Ventas!$G70,Productos!$A$1:$I$24,5,0),0)*Ventas!$I70,"") -> 1708 | S70: =IFERROR(IF(Ventas!$E70<>13,ROUND(VLOOKUP(Ventas!$G70,Productos!$A$1:$I$24,6,0)*Ventas!$I70,0),0),"") -> 10700
A71: 22 | B71: 46012 | C71: 1 | D71: =CONCATENATE(Ventas!$A71,Ventas!$C71) -> 221 | F71: =IFERROR(VLOOKUP(Ventas!$E71,Clientes!$A$1:$E$48,2,0),"") | H71: =IFERROR(VLOOKUP(Ventas!$G71,Productos!$A$1:$I$24,2,0),"") | I71: 1 | K71: 5600 | M71: =Ventas!$I71*Ventas!$K71 -> 5600 | N71: E | O71: =IFERROR(IF(OR(N71="M",N71="T"),ROUND(M71*19/119,0),0),"") -> 0 | P71: =ROUND(M71*0.033333,0) -> 187 | Q71: =M71-O71-P71 -> 5413 | R71: =IFERROR(ROUND(VLOOKUP(Ventas!$G71,Productos!$A$1:$I$24,5,0),0)*Ventas!$I71,"") | S71: =IFERROR(IF(Ventas!$E71<>13,ROUND(VLOOKUP(Ventas!$G71,Productos!$A$1:$I$24,6,0)*Ventas!$I71,0),0),"")
A72: 22 | B72: 46012 | C72: 2 | D72: =CONCATENATE(Ventas!$A72,Ventas!$C72) -> 222 | F72: =IFERROR(VLOOKUP(Ventas!$E72,Clientes!$A$1:$E$48,2,0),"") | G72: Go-01 | H72: =IFERROR(VLOOKUP(Ventas!$G72,Productos!$A$1:$I$24,2,0),"") -> Gorra Natacion Lycra | I72: 1 | K72: =IFERROR(IF(Ventas!$E72<>13,VLOOKUP(Ventas!$G72,Productos!$A$1:$I$24,4,0),0),0) -> 4454 | M72: =Ventas!$I72*Ventas!$K72 -> 4454 | N72: M | O72: =IFERROR(IF(OR(N72="M",N72="T"),ROUND(M72*19/119,0),0),"") -> 711 | P72: =ROUND(M72*0.033333,0) -> 148 | Q72: =M72-O72-P72 -> 3595 | R72: =IFERROR(ROUND(VLOOKUP(Ventas!$G72,Productos!$A$1:$I$24,5,0),0)*Ventas!$I72,"") -> 846 | S72: =IFERROR(IF(Ventas!$E72<>13,ROUND(VLOOKUP(Ventas!$G72,Productos!$A$1:$I$24,6,0)*Ventas!$I72,0),0),"") -> 5300
A73: 23 | B73: 46013 | C73: 1 | D73: =CONCATENATE(Ventas!$A73,Ventas!$C73) -> 231 | F73: =IFERROR(VLOOKUP(Ventas!$E73,Clientes!$A$1:$E$48,2,0),"") | G73: TU-08 | H73: =IFERROR(VLOOKUP(Ventas!$G73,Productos!$A$1:$I$24,2,0),"") -> Turbante Ro | I73: 1 | K73: =IFERROR(IF(Ventas!$E73<>13,VLOOKUP(Ventas!$G73,Productos!$A$1:$I$24,4,0),0),0) -> 4706 | M73: =Ventas!$I73*Ventas!$K73 -> 4706 | N73: M | O73: =IFERROR(IF(OR(N73="M",N73="T"),ROUND(M73*19/119,0),0),"") -> 751 | P73: =ROUND(M73*0.033333,0) -> 157 | Q73: =M73-O73-P73 -> 3798 | R73: =IFERROR(ROUND(VLOOKUP(Ventas!$G73,Productos!$A$1:$I$24,5,0),0)*Ventas!$I73,"") -> 894 | S73: =IFERROR(IF(Ventas!$E73<>13,ROUND(VLOOKUP(Ventas!$G73,Productos!$A$1:$I$24,6,0)*Ventas!$I73,0),0),"") -> 5600
A74: 24 | B74: 46014 | C74: 1 | D74: =CONCATENATE(Ventas!$A74,Ventas!$C74) -> 241 | F74: =IFERROR(VLOOKUP(Ventas!$E74,Clientes!$A$1:$E$48,2,0),"") | G74: TU-01 | H74: =IFERROR(VLOOKUP(Ventas!$G74,Productos!$A$1:$I$24,2,0),"") -> Turbante Ca | I74: 1 | K74: =IFERROR(IF(Ventas!$E74<>13,VLOOKUP(Ventas!$G74,Productos!$A$1:$I$24,4,0),0),0) -> 4706 | M74: =Ventas!$I74*Ventas!$K74 -> 4706 | N74: E | O74: =IFERROR(IF(OR(N74="M",N74="T"),ROUND(M74*19/119,0),0),"") -> 0 | P74: =ROUND(M74*0.033333,0) -> 157 | Q74: =M74-O74-P74 -> 4549 | R74: =IFERROR(ROUND(VLOOKUP(Ventas!$G74,Productos!$A$1:$I$24,5,0),0)*Ventas!$I74,"") -> 894 | S74: =IFERROR(IF(Ventas!$E74<>13,ROUND(VLOOKUP(Ventas!$G74,Productos!$A$1:$I$24,6,0)*Ventas!$I74,0),0),"") -> 5600
A75: 24 | B75: 46014 | C75: 2 | D75: =CONCATENATE(Ventas!$A75,Ventas!$C75) -> 242 | F75: =IFERROR(VLOOKUP(Ventas!$E75,Clientes!$A$1:$E$48,2,0),"") | G75: TU-05 | H75: =IFERROR(VLOOKUP(Ventas!$G75,Productos!$A$1:$I$24,2,0),"") -> Turbante Ne | I75: 1 | K75: =IFERROR(IF(Ventas!$E75<>13,VLOOKUP(Ventas!$G75,Productos!$A$1:$I$24,4,0),0),0) -> 4706 | M75: =Ventas!$I75*Ventas!$K75 -> 4706 | N75: M | O75: =IFERROR(IF(OR(N75="M",N75="T"),ROUND(M75*19/119,0),0),"") -> 751 | P75: =ROUND(M75*0.033333,0) -> 157 | Q75: =M75-O75-P75 -> 3798 | R75: =IFERROR(ROUND(VLOOKUP(Ventas!$G75,Productos!$A$1:$I$24,5,0),0)*Ventas!$I75,"") -> 894 | S75: =IFERROR(IF(Ventas!$E75<>13,ROUND(VLOOKUP(Ventas!$G75,Productos!$A$1:$I$24,6,0)*Ventas!$I75,0),0),"") -> 5600
A76: 24 | B76: 46014 | C76: 3 | D76: =CONCATENATE(Ventas!$A76,Ventas!$C76) -> 243 | F76: =IFERROR(VLOOKUP(Ventas!$E76,Clientes!$A$1:$E$48,2,0),"") | G76: TO-02 | H76: =IFERROR(VLOOKUP(Ventas!$G76,Productos!$A$1:$I$24,2,0),"") -> Toalla 160x80 Ro | I76: 1 | K76: =IFERROR(IF(Ventas!$E76<>13,VLOOKUP(Ventas!$G76,Productos!$A$1:$I$24,4,0),0),0) -> 8992 | M76: =Ventas!$I76*Ventas!$K76 -> 8992 | N76: T | O76: =IFERROR(IF(OR(N76="M",N76="T"),ROUND(M76*19/119,0),0),"") -> 1436 | P76: =ROUND(M76*0.033333,0) -> 300 | Q76: =M76-O76-P76 -> 7256 | R76: =IFERROR(ROUND(VLOOKUP(Ventas!$G76,Productos!$A$1:$I$24,5,0),0)*Ventas!$I76,"") -> 1708 | S76: =IFERROR(IF(Ventas!$E76<>13,ROUND(VLOOKUP(Ventas!$G76,Productos!$A$1:$I$24,6,0)*Ventas!$I76,0),0),"") -> 10700
A77: 24 | B77: 46014 | C77: 4 | D77: =CONCATENATE(Ventas!$A77,Ventas!$C77) -> 244 | F77: =IFERROR(VLOOKUP(Ventas!$E77,Clientes!$A$1:$E$48,2,0),"") | G77: TO-05 | H77: =IFERROR(VLOOKUP(Ventas!$G77,Productos!$A$1:$I$24,2,0),"") -> Toalla 160x80 Ca | I77: 1 | K77: =IFERROR(IF(Ventas!$E77<>13,VLOOKUP(Ventas!$G77,Productos!$A$1:$I$24,4,0),0),0) -> 8992 | M77: =Ventas!$I77*Ventas!$K77 -> 8992 | N77: T | O77: =IFERROR(IF(OR(N77="M",N77="T"),ROUND(M77*19/119,0),0),"") -> 1436 | P77: =ROUND(M77*0.033333,0) -> 300 | Q77: =M77-O77-P77 -> 7256 | R77: =IFERROR(ROUND(VLOOKUP(Ventas!$G77,Productos!$A$1:$I$24,5,0),0)*Ventas!$I77,"") -> 1708 | S77: =IFERROR(IF(Ventas!$E77<>13,ROUND(VLOOKUP(Ventas!$G77,Productos!$A$1:$I$24,6,0)*Ventas!$I77,0),0),"") -> 10700
A78: 24 | B78: 46014 | C78: 5 | D78: =CONCATENATE(Ventas!$A78,Ventas!$C78) -> 245 | F78: =IFERROR(VLOOKUP(Ventas!$E78,Clientes!$A$1:$E$48,2,0),"") | G78: TO-03 | H78: =IFERROR(VLOOKUP(Ventas!$G78,Productos!$A$1:$I$24,2,0),"") -> Toalla 160x80 Am | I78: 1 | K78: =IFERROR(IF(Ventas!$E78<>13,VLOOKUP(Ventas!$G78,Productos!$A$1:$I$24,4,0),0),0) -> 8992 | M78: =Ventas!$I78*Ventas!$K78 -> 8992 | N78: T | O78: =IFERROR(IF(OR(N78="M",N78="T"),ROUND(M78*19/119,0),0),"") -> 1436 | P78: =ROUND(M78*0.033333,0) -> 300 | Q78: =M78-O78-P78 -> 7256 | R78: =IFERROR(ROUND(VLOOKUP(Ventas!$G78,Productos!$A$1:$I$24,5,0),0)*Ventas!$I78,"") -> 1708 | S78: =IFERROR(IF(Ventas!$E78<>13,ROUND(VLOOKUP(Ventas!$G78,Productos!$A$1:$I$24,6,0)*Ventas!$I78,0),0),"") -> 10700
A79: 24 | B79: 46014 | C79: 6 | D79: =CONCATENATE(Ventas!$A79,Ventas!$C79) -> 246 | F79: =IFERROR(VLOOKUP(Ventas!$E79,Clientes!$A$1:$E$48,2,0),"") | G79: TU-08 | H79: =IFERROR(VLOOKUP(Ventas!$G79,Productos!$A$1:$I$24,2,0),"") -> Turbante Ro | I79: 1 | K79: =IFERROR(IF(Ventas!$E79<>13,VLOOKUP(Ventas!$G79,Productos!$A$1:$I$24,4,0),0),0) -> 4706 | M79: =Ventas!$I79*Ventas!$K79 -> 4706 | N79: T | O79: =IFERROR(IF(OR(N79="M",N79="T"),ROUND(M79*19/119,0),0),"") -> 751 | P79: =ROUND(M79*0.033333,0) -> 157 | Q79: =M79-O79-P79 -> 3798 | R79: =IFERROR(ROUND(VLOOKUP(Ventas!$G79,Productos!$A$1:$I$24,5,0),0)*Ventas!$I79,"") -> 894 | S79: =IFERROR(IF(Ventas!$E79<>13,ROUND(VLOOKUP(Ventas!$G79,Productos!$A$1:$I$24,6,0)*Ventas!$I79,0),0),"") -> 5600
D80: =CONCATENATE(Ventas!$A80,Ventas!$C80) | F80: =IFERROR(VLOOKUP(Ventas!$E80,Clientes!$A$1:$E$48,2,0),"") | H80: =IFERROR(VLOOKUP(Ventas!$G80,Productos!$A$1:$I$24,2,0),"") | K80: =IFERROR(IF(Ventas!$E80<>13,VLOOKUP(Ventas!$G80,Productos!$A$1:$I$24,4,0),0),0) -> 0 | M80: =Ventas!$I80*Ventas!$K80 -> 0 | O80: =IFERROR(IF(OR(N80="M",N80="T"),ROUND(M80*19/119,0),0),"") -> 0 | P80: =ROUND(M80*0.033333,0) -> 0 | Q80: =M80-O80-P80 -> 0 | R80: =IFERROR(ROUND(VLOOKUP(Ventas!$G80,Productos!$A$1:$I$24,5,0),0)*Ventas!$I80,"") | S80: =IFERROR(IF(Ventas!$E80<>13,ROUND(VLOOKUP(Ventas!$G80,Productos!$A$1:$I$24,6,0)*Ventas!$I80,0),0),"")
D81: =CONCATENATE(Ventas!$A81,Ventas!$C81) | F81: =IFERROR(VLOOKUP(Ventas!$E81,Clientes!$A$1:$E$48,2,0),"") | H81: =IFERROR(VLOOKUP(Ventas!$G81,Productos!$A$1:$I$24,2,0),"") | K81: =IFERROR(IF(Ventas!$E81<>13,VLOOKUP(Ventas!$G81,Productos!$A$1:$I$24,4,0),0),0) -> 0 | M81: =Ventas!$I81*Ventas!$K81 -> 0 | O81: =IFERROR(IF(OR(N81="M",N81="T"),ROUND(M81*19/119,0),0),"") -> 0 | P81: =ROUND(M81*0.033333,0) -> 0 | Q81: =M81-O81-P81 -> 0 | R81: =IFERROR(ROUND(VLOOKUP(Ventas!$G81,Productos!$A$1:$I$24,5,0),0)*Ventas!$I81,"") | S81: =IFERROR(IF(Ventas!$E81<>13,ROUND(VLOOKUP(Ventas!$G81,Productos!$A$1:$I$24,6,0)*Ventas!$I81,0),0),"")
D82: =CONCATENATE(Ventas!$A82,Ventas!$C82) | F82: =IFERROR(VLOOKUP(Ventas!$E82,Clientes!$A$1:$E$48,2,0),"") | H82: =IFERROR(VLOOKUP(Ventas!$G82,Productos!$A$1:$I$24,2,0),"") | K82: =IFERROR(IF(Ventas!$E82<>13,VLOOKUP(Ventas!$G82,Productos!$A$1:$I$24,4,0),0),0) -> 0 | M82: =Ventas!$I82*Ventas!$K82 -> 0 | O82: =IFERROR(IF(OR(N82="M",N82="T"),ROUND(M82*19/119,0),0),"") -> 0 | P82: =ROUND(M82*0.033333,0) -> 0 | Q82: =M82-O82-P82 -> 0 | R82: =IFERROR(ROUND(VLOOKUP(Ventas!$G82,Productos!$A$1:$I$24,5,0),0)*Ventas!$I82,"") | S82: =IFERROR(IF(Ventas!$E82<>13,ROUND(VLOOKUP(Ventas!$G82,Productos!$A$1:$I$24,6,0)*Ventas!$I82,0),0),"")
D83: =CONCATENATE(Ventas!$A83,Ventas!$C83) | F83: =IFERROR(VLOOKUP(Ventas!$E83,Clientes!$A$1:$E$48,2,0),"") | H83: =IFERROR(VLOOKUP(Ventas!$G83,Productos!$A$1:$I$24,2,0),"") | K83: =IFERROR(IF(Ventas!$E83<>13,VLOOKUP(Ventas!$G83,Productos!$A$1:$I$24,4,0),0),0) -> 0 | M83: =Ventas!$I83*Ventas!$K83 -> 0 | O83: =IFERROR(IF(OR(N83="M",N83="T"),ROUND(M83*19/119,0),0),"") -> 0 | P83: =ROUND(M83*0.033333,0) -> 0 | Q83: =M83-O83-P83 -> 0 | R83: =IFERROR(ROUND(VLOOKUP(Ventas!$G83,Productos!$A$1:$I$24,5,0),0)*Ventas!$I83,"") | S83: =IFERROR(IF(Ventas!$E83<>13,ROUND(VLOOKUP(Ventas!$G83,Productos!$A$1:$I$24,6,0)*Ventas!$I83,0),0),"")
D84: =CONCATENATE(Ventas!$A84,Ventas!$C84) | F84: =IFERROR(VLOOKUP(Ventas!$E84,Clientes!$A$1:$E$48,2,0),"") | H84: =IFERROR(VLOOKUP(Ventas!$G84,Productos!$A$1:$I$24,2,0),"") | K84: =IFERROR(IF(Ventas!$E84<>13,VLOOKUP(Ventas!$G84,Productos!$A$1:$I$24,4,0),0),0) -> 0 | M84: =Ventas!$I84*Ventas!$K84 -> 0 | O84: =IFERROR(IF(OR(N84="M",N84="T"),ROUND(M84*19/119,0),0),"") -> 0 | P84: =ROUND(M84*0.033333,0) -> 0 | Q84: =M84-O84-P84 -> 0 | R84: =IFERROR(ROUND(VLOOKUP(Ventas!$G84,Productos!$A$1:$I$24,5,0),0)*Ventas!$I84,"") | S84: =IFERROR(IF(Ventas!$E84<>13,ROUND(VLOOKUP(Ventas!$G84,Productos!$A$1:$I$24,6,0)*Ventas!$I84,0),0),"")
D85: =CONCATENATE(Ventas!$A85,Ventas!$C85) | F85: =IFERROR(VLOOKUP(Ventas!$E85,Clientes!$A$1:$E$48,2,0),"") | H85: =IFERROR(VLOOKUP(Ventas!$G85,Productos!$A$1:$I$24,2,0),"") | K85: =IFERROR(IF(Ventas!$E85<>13,VLOOKUP(Ventas!$G85,Productos!$A$1:$I$24,4,0),0),0) -> 0 | M85: =Ventas!$I85*Ventas!$K85 -> 0 | O85: =IFERROR(IF(OR(N85="M",N85="T"),ROUND(M85*19/119,0),0),"") -> 0 | P85: =ROUND(M85*0.033333,0) -> 0 | Q85: =M85-O85-P85 -> 0 | R85: =IFERROR(ROUND(VLOOKUP(Ventas!$G85,Productos!$A$1:$I$24,5,0),0)*Ventas!$I85,"") | S85: =IFERROR(IF(Ventas!$E85<>13,ROUND(VLOOKUP(Ventas!$G85,Productos!$A$1:$I$24,6,0)*Ventas!$I85,0),0),"")
D86: =CONCATENATE(Ventas!$A86,Ventas!$C86) | F86: =IFERROR(VLOOKUP(Ventas!$E86,Clientes!$A$1:$E$48,2,0),"") | H86: =IFERROR(VLOOKUP(Ventas!$G86,Productos!$A$1:$I$24,2,0),"") | K86: =IFERROR(IF(Ventas!$E86<>13,VLOOKUP(Ventas!$G86,Productos!$A$1:$I$24,4,0),0),0) -> 0 | M86: =Ventas!$I86*Ventas!$K86 -> 0 | O86: =IFERROR(IF(OR(N86="M",N86="T"),ROUND(M86*19/119,0),0),"") -> 0 | P86: =ROUND(M86*0.033333,0) -> 0 | Q86: =M86-O86-P86 -> 0 | R86: =IFERROR(ROUND(VLOOKUP(Ventas!$G86,Productos!$A$1:$I$24,5,0),0)*Ventas!$I86,"") | S86: =IFERROR(IF(Ventas!$E86<>13,ROUND(VLOOKUP(Ventas!$G86,Productos!$A$1:$I$24,6,0)*Ventas!$I86,0),0),"")
D87: =CONCATENATE(Ventas!$A87,Ventas!$C87) | F87: =IFERROR(VLOOKUP(Ventas!$E87,Clientes!$A$1:$E$48,2,0),"") | H87: =IFERROR(VLOOKUP(Ventas!$G87,Productos!$A$1:$I$24,2,0),"") | K87: =IFERROR(IF(Ventas!$E87<>13,VLOOKUP(Ventas!$G87,Productos!$A$1:$I$24,4,0),0),0) -> 0 | M87: =Ventas!$I87*Ventas!$K87 -> 0 | O87: =IFERROR(IF(OR(N87="M",N87="T"),ROUND(M87*19/119,0),0),"") -> 0 | P87: =ROUND(M87*0.033333,0) -> 0 | Q87: =M87-O87-P87 -> 0 | R87: =IFERROR(ROUND(VLOOKUP(Ventas!$G87,Productos!$A$1:$I$24,5,0),0)*Ventas!$I87,"") | S87: =IFERROR(IF(Ventas!$E87<>13,ROUND(VLOOKUP(Ventas!$G87,Productos!$A$1:$I$24,6,0)*Ventas!$I87,0),0),"")
D88: =CONCATENATE(Ventas!$A88,Ventas!$C88) | F88: =IFERROR(VLOOKUP(Ventas!$E88,Clientes!$A$1:$E$48,2,0),"") | H88: =IFERROR(VLOOKUP(Ventas!$G88,Productos!$A$1:$I$24,2,0),"") | K88: =IFERROR(IF(Ventas!$E88<>13,VLOOKUP(Ventas!$G88,Productos!$A$1:$I$24,4,0),0),0) -> 0 | M88: =Ventas!$I88*Ventas!$K88 -> 0 | O88: =IFERROR(IF(OR(N88="M",N88="T"),ROUND(M88*19/119,0),0),"") -> 0 | P88: =ROUND(M88*0.033333,0) -> 0 | Q88: =M88-O88-P88 -> 0 | R88: =IFERROR(ROUND(VLOOKUP(Ventas!$G88,Productos!$A$1:$I$24,5,0),0)*Ventas!$I88,"") | S88: =IFERROR(IF(Ventas!$E88<>13,ROUND(VLOOKUP(Ventas!$G88,Productos!$A$1:$I$24,6,0)*Ventas!$I88,0),0),"")
D89: =CONCATENATE(Ventas!$A89,Ventas!$C89) | F89: =IFERROR(VLOOKUP(Ventas!$E89,Clientes!$A$1:$E$48,2,0),"") | H89: =IFERROR(VLOOKUP(Ventas!$G89,Productos!$A$1:$I$24,2,0),"") | K89: =IFERROR(IF(Ventas!$E89<>13,VLOOKUP(Ventas!$G89,Productos!$A$1:$I$24,4,0),0),0) -> 0 | M89: =Ventas!$I89*Ventas!$K89 -> 0 | O89: =IFERROR(IF(OR(N89="M",N89="T"),ROUND(M89*19/119,0),0),"") -> 0 | P89: =ROUND(M89*0.033333,0) -> 0 | Q89: =M89-O89-P89 -> 0 | R89: =IFERROR(ROUND(VLOOKUP(Ventas!$G89,Productos!$A$1:$I$24,5,0),0)*Ventas!$I89,"") | S89: =IFERROR(IF(Ventas!$E89<>13,ROUND(VLOOKUP(Ventas!$G89,Productos!$A$1:$I$24,6,0)*Ventas!$I89,0),0),"")
D90: =CONCATENATE(Ventas!$A90,Ventas!$C90) | F90: =IFERROR(VLOOKUP(Ventas!$E90,Clientes!$A$1:$E$48,2,0),"") | H90: =IFERROR(VLOOKUP(Ventas!$G90,Productos!$A$1:$I$24,2,0),"") | K90: =IFERROR(IF(Ventas!$E90<>13,VLOOKUP(Ventas!$G90,Productos!$A$1:$I$24,4,0),0),0) -> 0 | M90: =Ventas!$I90*Ventas!$K90 -> 0 | O90: =IFERROR(IF(OR(N90="M",N90="T"),ROUND(M90*19/119,0),0),"") -> 0 | P90: =ROUND(M90*0.033333,0) -> 0 | Q90: =M90-O90-P90 -> 0 | R90: =IFERROR(ROUND(VLOOKUP(Ventas!$G90,Productos!$A$1:$I$24,5,0),0)*Ventas!$I90,"") | S90: =IFERROR(IF(Ventas!$E90<>13,ROUND(VLOOKUP(Ventas!$G90,Productos!$A$1:$I$24,6,0)*Ventas!$I90,0),0),"")
D91: =CONCATENATE(Ventas!$A91,Ventas!$C91) | F91: =IFERROR(VLOOKUP(Ventas!$E91,Clientes!$A$1:$E$48,2,0),"") | H91: =IFERROR(VLOOKUP(Ventas!$G91,Productos!$A$1:$I$24,2,0),"") | K91: =IFERROR(IF(Ventas!$E91<>13,VLOOKUP(Ventas!$G91,Productos!$A$1:$I$24,4,0),0),0) -> 0 | M91: =Ventas!$I91*Ventas!$K91 -> 0 | O91: =IFERROR(IF(OR(N91="M",N91="T"),ROUND(M91*19/119,0),0),"") -> 0 | P91: =ROUND(M91*0.033333,0) -> 0 | Q91: =M91-O91-P91 -> 0 | R91: =IFERROR(ROUND(VLOOKUP(Ventas!$G91,Productos!$A$1:$I$24,5,0),0)*Ventas!$I91,"") | S91: =IFERROR(IF(Ventas!$E91<>13,ROUND(VLOOKUP(Ventas!$G91,Productos!$A$1:$I$24,6,0)*Ventas!$I91,0),0),"")
... D204: =CONCATENATE(Ventas!$A204,Ventas!$C204) | F204: =IFERROR(VLOOKUP(Ventas!$E204,Clientes!$A$1:$E$48,2,0),"") | H204: =IFERROR(VLOOKUP(Ventas!$G204,Productos!$A$1:$I$24,2,0),"") | K204: =IFERROR(IF(Ventas!$E204<>13,VLOOKUP(Ventas!$G204,Productos!$A$1:$I$24,4,0),0),0) -> 0 | M204: =Ventas!$I204*Ventas!$K204 -> 0 | O204: =IFERROR(IF(OR(N204="M",N204="T"),ROUND(M204*19/119,0),0),"") -> 0 | P204: =ROUND(M204*0.033333,0) -> 0 | Q204: =M204-O204-P204 -> 0 | R204: =IFERROR(ROUND(VLOOKUP(Ventas!$G204,Productos!$A$1:$I$24,5,0),0)*Ventas!$I204,"") | S204: =IFERROR(IF(Ventas!$E204<>13,ROUND(VLOOKUP(Ventas!$G204,Productos!$A$1:$I$24,6,0)*Ventas!$I204,0),0),"")
D205: =CONCATENATE(Ventas!$A205,Ventas!$C205) | H205: =IFERROR(VLOOKUP(Ventas!$G205,Productos!$A$1:$I$24,2,0),"") | K205: =IFERROR(IF(Ventas!$E205<>13,VLOOKUP(Ventas!$G205,Productos!$A$1:$I$24,4,0),0),0) -> 0 | M205: =SUBTOTAL(109,Ventas!$M$2:$M$204) -> 17984 | O205: =SUBTOTAL(109,Ventas!$O$2:$O$204) -> 2872 | P205: =ROUND(M205*0.033333,0) -> 599 | Q205: =M205-O205-P205 -> 14513 | R205: =SUBTOTAL(109,Ventas!$R$2:$R$204) -> 3416 | S205: =SUBTOTAL(109,Ventas!$S$2:$S$204) -> 21400

Sheet Despacho
A1: ID Venta | G1: : | H1: 1 | S1: ID Cliente | Y1: =VLOOKUP(Despacho!H1,Ventas!$A$1:$U$205,5,0) -> 0 | AE1: ID Venta | AK1: : | AL1: =H1+1 -> 2 | AW1: ID Cliente | BC1: =VLOOKUP(Despacho!AL1,Ventas!$A$1:$U$205,5,0) -> 0 | BI1: ID Venta | BO1: : | BP1: =AL1+1 -> 3 | CA1: ID Cliente | CG1: =VLOOKUP(Despacho!BP1,Ventas!$A$1:$U$205,5,0) -> 0 | CM1: ID Venta | CS1: : | CT1: =BP1+1 -> 4 | DE1: ID Cliente | DK1: =VLOOKUP(Despacho!CT1,Ventas!$A$1:$U$205,5,0) -> 0 | DQ1: ID Venta | DW1: : | DX1: =CT1+1 -> 5 | EI1: ID Cliente | EO1: =VLOOKUP(Despacho!DX1,Ventas!$A$1:$U$205,5,0) -> 0
A2: Cliente | G2: : | H2: =VLOOKUP(Despacho!H1,Ventas!$A$1:$U$205,6,0) | AE2: Cliente | AK2: : | AL2: =VLOOKUP(Despacho!AL1,Ventas!$A$1:$U$205,6,0) | BI2: Cliente | BO2: : | BP2: =VLOOKUP(Despacho!BP1,Ventas!$A$1:$U$205,6,0) | CM2: Cliente | CS2: : | CT2: =VLOOKUP(Despacho!CT1,Ventas!$A$1:$U$205,6,0) | DQ2: Cliente | DW2: : | DX2: =VLOOKUP(Despacho!DX1,Ventas!$A$1:$U$205,6,0)
A3: Fecha Entrega | G3: : | H3: =VLOOKUP(Despacho!H1,Ventas!$A$1:$U$205,15,0) -> 1436 | AE3: Fecha Entrega | AK3: : | AL3: =VLOOKUP(Despacho!AL1,Ventas!$A$1:$U$205,15,0) -> 0 | BI3: Fecha Entrega | BO3: : | BP3: =VLOOKUP(Despacho!BP1,Ventas!$A$1:$U$205,15,0) -> 0 | CM3: Fecha Entrega | CS3: : | CT3: =VLOOKUP(Despacho!CT1,Ventas!$A$1:$U$205,15,0) -> 751 | DQ3: Fecha Entrega | DW3: : | DX3: =VLOOKUP(Despacho!DX1,Ventas!$A$1:$U$205,15,0) -> 751
A4: Hora Entrega | H4: =VLOOKUP(Despacho!H1,Ventas!$A$1:$U$205,16,0) -> 300 | AE4: Hora Entrega | AL4: =VLOOKUP(Despacho!AL1,Ventas!$A$1:$U$205,16,0) -> 157 | BI4: Hora Entrega | BP4: =VLOOKUP(Despacho!BP1,Ventas!$A$1:$U$205,16,0) -> 370 | CM4: Hora Entrega | CT4: =VLOOKUP(Despacho!CT1,Ventas!$A$1:$U$205,16,0) -> 157 | DQ4: Hora Entrega | DX4: =VLOOKUP(Despacho!DX1,Ventas!$A$1:$U$205,16,0) -> 157
A5: Dirección | G5: : | H5: =VLOOKUP(Y1,Clientes!$A$1:$E$504,3,0) -> #N/A | Y5: Zona | AA5: =VLOOKUP(Y1,Clientes!$A$1:$E$48,4,0) -> #N/A | AE5: Dirección | AK5: : | AL5: =VLOOKUP(BC1,Clientes!$A$1:$E$504,3,0) -> #N/A | BC5: Zona | BE5: =VLOOKUP(BC1,Clientes!$A$1:$E$48,4,0) -> #N/A | BI5: Dirección | BO5: : | BP5: =VLOOKUP(CG1,Clientes!$A$1:$E$504,3,0) -> #N/A | CG5: Zona | CI5: =VLOOKUP(CG1,Clientes!$A$1:$E$48,4,0) -> #N/A | CM5: Dirección | CS5: : | CT5: =VLOOKUP(DK1,Clientes!$A$1:$E$504,3,0) -> #N/A | DK5: Zona | DM5: =VLOOKUP(DK1,Clientes!$A$1:$E$48,4,0) -> #N/A | DQ5: Dirección | DW5: : | DX5: =VLOOKUP(EO1,Clientes!$A$1:$E$504,3,0) -> #N/A | EO5: Zona | EQ5: =VLOOKUP(EO1,Clientes!$A$1:$E$48,4,0) -> #N/A
A8: Ítem | C8: Detalle | U8: Cant | W8: Precio Unit | AA8: Sub Tot | AE8: Ítem | AG8: Detalle | AY8: Cant | BA8: Precio Unit | BE8: Sub Tot | BI8: Ítem | BK8: Detalle | CC8: Cant | CE8: Precio Unit | CI8: Sub Tot | CM8: Ítem | CO8: Detalle | DG8: Cant | DI8: Precio Unit | DM8: Sub Tot | DQ8: Ítem | DS8: Detalle | EK8: Cant | EM8: Precio Unit | EQ8: Sub Tot
A9: 1 | C9: =IFERROR(VLOOKUP(CONCATENATE(H$1,A9),Ventas!$D$1:$M$205,5,0),"") -> Toalla 160x80 Fu | U9: =IFERROR(VLOOKUP(CONCATENATE(H$1,A9),Ventas!$D$1:$M$205,6,0),"") -> 1 | W9: =IFERROR(VLOOKUP(CONCATENATE(H$1,A9),Ventas!$D$1:$M$205,8,0),"") -> 8992 | AA9: =IFERROR(U9*W9,"") -> 8992 | AE9: 1 | AG9: =IFERROR(VLOOKUP(CONCATENATE(AL$1,AE9),Ventas!$D$1:$M$205,5,0),"") -> Turbante Li | AY9: =IFERROR(VLOOKUP(CONCATENATE(AL$1,AE9),Ventas!$D$1:$M$205,6,0),"") -> 1 | BA9: =IFERROR(VLOOKUP(CONCATENATE(AL$1,AE9),Ventas!$D$1:$M$205,8,0),"") -> 4706 | BE9: =IFERROR(AY9*BA9,"") -> 4706 | BI9: 1 | BK9: =IFERROR(VLOOKUP(CONCATENATE(BP$1,BI9),Ventas!$D$1:$M$205,5,0),"") -> Toalla 160x110 Li | CC9: =IFERROR(VLOOKUP(CONCATENATE(BP$1,BI9),Ventas!$D$1:$M$205,6,0),"") -> 1 | CE9: =IFERROR(VLOOKUP(CONCATENATE(BP$1,BI9),Ventas!$D$1:$M$205,8,0),"") -> 11092 | CI9: =IFERROR(CC9*CE9,"") -> 11092 | CM9: 1 | CO9: =IFERROR(VLOOKUP(CONCATENATE(CT$1,CM9),Ventas!$D$1:$M$205,5,0),"") -> Turbante Fu | DG9: =IFERROR(VLOOKUP(CONCATENATE(CT$1,CM9),Ventas!$D$1:$M$205,6,0),"") -> 1 | DI9: =IFERROR(VLOOKUP(CONCATENATE(CT$1,CM9),Ventas!$D$1:$M$205,8,0),"") -> 4706 | DM9: =IFERROR(DG9*DI9,"") -> 4706 | DQ9: 1 | DS9: =IFERROR(VLOOKUP(CONCATENATE(DX$1,DQ9),Ventas!$D$1:$M$205,5,0),"") -> Turbante Ca | EK9: =IFERROR(VLOOKUP(CONCATENATE(DX$1,DQ9),Ventas!$D$1:$M$205,6,0),"") -> 1 | EM9: =IFERROR(VLOOKUP(CONCATENATE(DX$1,DQ9),Ventas!$D$1:$M$205,8,0),"") -> 4706 | EQ9: =IFERROR(EK9*EM9,"") -> 4706
A10: 2 | C10: =IFERROR(VLOOKUP(CONCATENATE(H$1,A10),Ventas!$D$1:$M$205,5,0),"") -> Turbante Fu | U10: =IFERROR(VLOOKUP(CONCATENATE(H$1,A10),Ventas!$D$1:$M$205,6,0),"") -> 1 | W10: =IFERROR(VLOOKUP(CONCATENATE(H$1,A10),Ventas[[#All],[Idet]:[Total]],8,0),"") -> 4706 | AA10: =IFERROR(U10*W10,"") -> 4706 | AE10: 2 | AG10: =IFERROR(VLOOKUP(CONCATENATE(AL$1,AE10),Ventas!$D$1:$M$205,5,0),"") -> Turbante Fu | AY10: =IFERROR(VLOOKUP(CONCATENATE(AL$1,AE10),Ventas!$D$1:$M$205,6,0),"") -> 1 | BA10: =IFERROR(VLOOKUP(CONCATENATE(AL$1,AE10),Ventas[[#All],[Idet]:[Total]],8,0),"") -> 4706 | BE10: =IFERROR(AY10*BA10,"") -> 4706 | BI10: 2 | BK10: =IFERROR(VLOOKUP(CONCATENATE(BP$1,BI10),Ventas!$D$1:$M$205,5,0),"") | CC10: =IFERROR(VLOOKUP(CONCATENATE(BP$1,BI10),Ventas!$D$1:$M$205,6,0),"") | CE10: =IFERROR(VLOOKUP(CONCATENATE(BP$1,BI10),Ventas[[#All],[Idet]:[Total]],8,0),"") | CI10: =IFERROR(CC10*CE10,"") | CM10: 2 | CO10: =IFERROR(VLOOKUP(CONCATENATE(CT$1,CM10),Ventas!$D$1:$M$205,5,0),"") -> Toalla 160x80 Fu | DG10: =IFERROR(VLOOKUP(CONCATENATE(CT$1,CM10),Ventas!$D$1:$M$205,6,0),"") -> 1 | DI10: =IFERROR(VLOOKUP(CONCATENATE(CT$1,CM10),Ventas[[#All],[Idet]:[Total]],8,0),"") -> 8992 | DM10: =IFERROR(DG10*DI10,"") -> 8992 | DQ10: 2 | DS10: =IFERROR(VLOOKUP(CONCATENATE(DX$1,DQ10),Ventas!$D$1:$M$205,5,0),"") -> Turbante Li | EK10: =IFERROR(VLOOKUP(CONCATENATE(DX$1,DQ10),Ventas!$D$1:$M$205,6,0),"") -> 1 | EM10: =IFERROR(VLOOKUP(CONCATENATE(DX$1,DQ10),Ventas[[#All],[Idet]:[Total]],8,0),"") -> 4706 | EQ10: =IFERROR(EK10*EM10,"") -> 4706
A11: 3 | C11: =IFERROR(VLOOKUP(CONCATENATE(H$1,A11),Ventas!$D$1:$M$205,5,0),"") -> Turbante Ca | U11: =IFERROR(VLOOKUP(CONCATENATE(H$1,A11),Ventas!$D$1:$M$205,6,0),"") -> 1 | W11: =IFERROR(VLOOKUP(CONCATENATE(H$1,A11),Ventas!$D$1:$M$205,8,0),"") -> 4706 | AA11: =IFERROR(U11*W11,"") -> 4706 | AE11: 3 | AG11: =IFERROR(VLOOKUP(CONCATENATE(AL$1,AE11),Ventas!$D$1:$M$205,5,0),"") -> Turbante Fu | AY11: =IFERROR(VLOOKUP(CONCATENATE(AL$1,AE11),Ventas!$D$1:$M$205,6,0),"") -> 1 | BA11: =IFERROR(VLOOKUP(CONCATENATE(AL$1,AE11),Ventas!$D$1:$M$205,8,0),"") -> 4706 | BE11: =IFERROR(AY11*BA11,"") -> 4706 | BI11: 3 | BK11: =IFERROR(VLOOKUP(CONCATENATE(BP$1,BI11),Ventas!$D$1:$M$205,5,0),"") | CC11: =IFERROR(VLOOKUP(CONCATENATE(BP$1,BI11),Ventas!$D$1:$M$205,6,0),"") | CE11: =IFERROR(VLOOKUP(CONCATENATE(BP$1,BI11),Ventas!$D$1:$M$205,8,0),"") | CI11: =IFERROR(CC11*CE11,"") | CM11: 3 | CO11: =IFERROR(VLOOKUP(CONCATENATE(CT$1,CM11),Ventas!$D$1:$M$205,5,0),"") -> Gorra Natacion Lycra | DG11: =IFERROR(VLOOKUP(CONCATENATE(CT$1,CM11),Ventas!$D$1:$M$205,6,0),"") -> 1 | DI11: =IFERROR(VLOOKUP(CONCATENATE(CT$1,CM11),Ventas!$D$1:$M$205,8,0),"") -> 4454 | DM11: =IFERROR(DG11*DI11,"") -> 4454 | DQ11: 3 | DS11: =IFERROR(VLOOKUP(CONCATENATE(DX$1,DQ11),Ventas!$D$1:$M$205,5,0),"") -> Turbante Fu | EK11: =IFERROR(VLOOKUP(CONCATENATE(DX$1,DQ11),Ventas!$D$1:$M$205,6,0),"") -> 1 | EM11: =IFERROR(VLOOKUP(CONCATENATE(DX$1,DQ11),Ventas!$D$1:$M$205,8,0),"") -> 4706 | EQ11: =IFERROR(EK11*EM11,"") -> 4706
A12: 4 | C12: =IFERROR(VLOOKUP(CONCATENATE(H$1,A12),Ventas!$D$1:$M$205,5,0),"") -> Turbante Ca | U12: =IFERROR(VLOOKUP(CONCATENATE(H$1,A12),Ventas!$D$1:$M$205,6,0),"") -> 1 | W12: =IFERROR(VLOOKUP(CONCATENATE(H$1,A12),Ventas!$D$1:$M$205,8,0),"") -> 4706 | AA12: =IFERROR(U12*W12,"") -> 4706 | AE12: 4 | AG12: =IFERROR(VLOOKUP(CONCATENATE(AL$1,AE12),Ventas!$D$1:$M$205,5,0),"") | AY12: =IFERROR(VLOOKUP(CONCATENATE(AL$1,AE12),Ventas!$D$1:$M$205,6,0),"") | BA12: =IFERROR(VLOOKUP(CONCATENATE(AL$1,AE12),Ventas!$D$1:$M$205,8,0),"") | BE12: =IFERROR(AY12*BA12,"") | BI12: 4 | BK12: =IFERROR(VLOOKUP(CONCATENATE(BP$1,BI12),Ventas!$D$1:$M$205,5,0),"") | CC12: =IFERROR(VLOOKUP(CONCATENATE(BP$1,BI12),Ventas!$D$1:$M$205,6,0),"") | CE12: =IFERROR(VLOOKUP(CONCATENATE(BP$1,BI12),Ventas!$D$1:$M$205,8,0),"") | CI12: =IFERROR(CC12*CE12,"") | CM12: 4 | CO12: =IFERROR(VLOOKUP(CONCATENATE(CT$1,CM12),Ventas!$D$1:$M$205,5,0),"") -> Turbante Fu | DG12: =IFERROR(VLOOKUP(CONCATENATE(CT$1,CM12),Ventas!$D$1:$M$205,6,0),"") -> 1 | DI12: =IFERROR(VLOOKUP(CONCATENATE(CT$1,CM12),Ventas!$D$1:$M$205,8,0),"") -> 4706 | DM12: =IFERROR(DG12*DI12,"") -> 4706 | DQ12: 4 | DS12: =IFERROR(VLOOKUP(CONCATENATE(DX$1,DQ12),Ventas!$D$1:$M$205,5,0),"") | EK12: =IFERROR(VLOOKUP(CONCATENATE(DX$1,DQ12),Ventas!$D$1:$M$205,6,0),"") | EM12: =IFERROR(VLOOKUP(CONCATENATE(DX$1,DQ12),Ventas!$D$1:$M$205,8,0),"") | EQ12: =IFERROR(EK12*EM12,"")
A13: 5 | C13: =IFERROR(VLOOKUP(CONCATENATE(H$1,A13),Ventas!$D$1:$M$205,5,0),"") | U13: =IFERROR(VLOOKUP(CONCATENATE(H$1,A13),Ventas!$D$1:$M$205,6,0),"") | W13: =IFERROR(VLOOKUP(CONCATENATE(H$1,A13),Ventas!$D$1:$M$205,8,0),"") | AA13: =IFERROR(U13*W13,"") | AE13: 5 | AG13: =IFERROR(VLOOKUP(CONCATENATE(AL$1,AE13),Ventas!$D$1:$M$205,5,0),"") | AY13: =IFERROR(VLOOKUP(CONCATENATE(AL$1,AE13),Ventas!$D$1:$M$205,6,0),"") | BA13: =IFERROR(VLOOKUP(CONCATENATE(AL$1,AE13),Ventas!$D$1:$M$205,8,0),"") | BE13: =IFERROR(AY13*BA13,"") | BI13: 5 | BK13: =IFERROR(VLOOKUP(CONCATENATE(BP$1,BI13),Ventas!$D$1:$M$205,5,0),"") | CC13: =IFERROR(VLOOKUP(CONCATENATE(BP$1,BI13),Ventas!$D$1:$M$205,6,0),"") | CE13: =IFERROR(VLOOKUP(CONCATENATE(BP$1,BI13),Ventas!$D$1:$M$205,8,0),"") | CI13: =IFERROR(CC13*CE13,"") | CM13: 5 | CO13: =IFERROR(VLOOKUP(CONCATENATE(CT$1,CM13),Ventas!$D$1:$M$205,5,0),"") -> Turbante Vp | DG13: =IFERROR(VLOOKUP(CONCATENATE(CT$1,CM13),Ventas!$D$1:$M$205,6,0),"") -> 1 | DI13: =IFERROR(VLOOKUP(CONCATENATE(CT$1,CM13),Ventas!$D$1:$M$205,8,0),"") -> 4706 | DM13: =IFERROR(DG13*DI13,"") -> 4706 | DQ13: 5 | DS13: =IFERROR(VLOOKUP(CONCATENATE(DX$1,DQ13),Ventas!$D$1:$M$205,5,0),"") | EK13: =IFERROR(VLOOKUP(CONCATENATE(DX$1,DQ13),Ventas!$D$1:$M$205,6,0),"") | EM13: =IFERROR(VLOOKUP(CONCATENATE(DX$1,DQ13),Ventas!$D$1:$M$205,8,0),"") | EQ13: =IFERROR(EK13*EM13,"")
